Workbook

Sheet README
A1: Culturdle — Question Bank v2 (trimmed and scored)
A3: Daily guessing game: two editions (Global, India) × three modes (Movie, Music, Icon). Six guesses; a new hint after every miss; four options on guess six.
A5: What changed from v1 (15,110 rows):
A6: • Scope narrowed to well-known, theatrically released films, charting songs and famous people and brands.
A7: • Every row has a Fame score from 0 to 10 built from public popularity signals (see the Scoring tab). Rows scoring below 6.0 were removed.
A8: • Streaming-premiere films and TV movies were removed regardless of score (theatrical releases only).
A9: • Hint ladders were rebuilt so each hint carries more information — the target is now 75–90% of players solving, not 45–55%.
A10: • Difficulty is re-derived from the Fame score within each edition: top 45% Easy, next 35% Medium, last 20% Hard.
A11: • Every removed row is listed on the Removed tab with its score and the reason, so any can be restored by hand.
A13: Hint ladders (v2):
A14: Movie: genre · industry · release year → director → plot moment (names masked) → two co-stars → lead actor · composer → title initials + options
A15: English song: genre · year → chart peak and weeks → album or another hit → another hit → artist → title initials + options
... A22: Still to do before launch: rewrite Movie “Moment” hints in original words (several are source synopsis text), and verify curated rows.

Sheet Scoring
A1: How the Fame score works
A2: Each signal is scaled 0–1 between its anchors, weighted and summed. Scores are then calibrated within each pool so that 6.0 is the keep line; anything below 6.0 is removed.
A4: Category | B4: Signal | C4: Measured by | D4: Weight | E4: Anchors (0 → full marks)
A5: Movie | B5: Audience reach | C5: IMDb vote count (log scale) | D5: 40% | E5: Global 20k → 1M · India 1.5k → 80k
A6: Movie | B6: Wikipedia reach | C6: Number of Wikipedia language editions with an article (Wikidata sitelinks) | D6: 25% | E6: Global 8 → 60 · India 4 → 30
A7: Movie | B7: Star power | C7: Lead actor's Wikipedia reach | D7: 15% | E7: Global 15 → 110 · India 8 → 70
A8: Movie | B8: Audience rating | C8: IMDb rating | D8: 10% | E8: 5.0 → 8.0
A9: Movie | B9: Era familiarity | C9: Release year (newer = more familiar) | D9: 10% | E9: ≥1990: 1 · 1975–89: 0.8 · 1960–74: 0.6 · older 0.4
A10: Movie | B10: Exclusion | C10: Streaming premiere: every Wikidata distributor is a streaming service AND released 2016+ (Global) / 2020+ (India), since older films list later OTT rights; or IMDb type TV movie / video. Duplicate answers keep the better-known copy. | D10: removed | E10: theatrical releases only
A11: English song | B11: Chart peak | C11: Billboard Hot 100 peak position | D11: 30% | E11: #10 → #1
A12: English song | B12: Chart longevity | C12: Weeks on the Hot 100 | D12: 20% | E12: 10 → 40 weeks
A13: English song | B13: Artist fame | C13: Artist's Wikipedia reach | D13: 30% | E13: 15 → 110
A14: English song | B14: Era familiarity | C14: Chart year | D14: 20% | E14: ≥1980: 1 · 1970s 0.75 · 1960s 0.5 · older 0.35
A15: Hindi song | B15: Film fame | C15: IMDb votes for the song's film (log scale) | D15: 35% | E15: 500 → 60k
... A24: Icon | B24: Screen presence | C24: Films in the bank (derived actors only) | D24: 15% | E24: 3 → 20 films
A27: Retention by pool
A28: Sheet | B28: Edition | C28: Rows in v1 | D28: Kept (live count) | E28: Removed (live count) | F28: Retained % | G28: Keep target
A29: Movies | B29: Global | C29: 2161 | D29: =COUNTIFS(Movies!$B:$B,$B29) -> 1650 | E29: =COUNTIFS(Removed!$B:$B,$A29,Removed!$C:$C,$B29) -> 511 | F29: =IFERROR(D29/C29,0) -> 0.7635354 | G29: 0.75
A30: Movies | B30: India | C30: 2124 | D30: =COUNTIFS(Movies!$B:$B,$B30) -> 1187 | E30: =COUNTIFS(Removed!$B:$B,$A30,Removed!$C:$C,$B30) -> 937 | F30: =IFERROR(D30/C30,0) -> 0.55885122 | G30: 0.55
A31: Music | B31: Global | C31: 5752 | D31: =COUNTIFS(Music!$B:$B,$B31) -> 3475 | E31: =COUNTIFS(Removed!$B:$B,$A31,Removed!$C:$C,$B31) -> 2277 | F31: =IFERROR(D31/C31,0) -> 0.60413769 | G31: 0.6
A32: Music | B32: India | C32: 3832 | D32: =COUNTIFS(Music!$B:$B,$B32) -> 2374 | E32: =COUNTIFS(Removed!$B:$B,$A32,Removed!$C:$C,$B32) -> 1458 | F32: =IFERROR(D32/C32,0) -> 0.61951983 | G32: 0.6
A33: Icons | B33: Global | C33: 835 | D33: =COUNTIFS(Icons!$B:$B,$B33) -> 671 | E33: =COUNTIFS(Removed!$B:$B,$A33,Removed!$C:$C,$B33) -> 164 | F33: =IFERROR(D33/C33,0) -> 0.80359281 | G33: 0.8
A34: Icons | B34: India | C34: 406 | D34: =COUNTIFS(Icons!$B:$B,$B34) -> 333 | E34: =COUNTIFS(Removed!$B:$B,$A34,Removed!$C:$C,$B34) -> 73 | F34: =IFERROR(D34/C34,0) -> 0.82019704 | G34: 0.8
A35: Total | C35: =SUM(C29:C34) -> 15110 | D35: =SUM(D29:D34) -> 9690 | E35: =SUM(E29:E34) -> 5420 | F35: =IFERROR(D35/C35,0) -> 0.64129715
A37: Blue = fixed inputs (v1 counts and keep targets). Black = formulas over the Movies, Music, Icons and Removed tabs.
A39: Difficulty mix of kept rows
A40: Sheet | B40: Edition | C40: Easy | D40: Medium | E40: Hard
A41: Movies | B41: Global | C41: =COUNTIFS(Movies!$B:$B,$B41,Movies!$D:$D,"Easy") -> 742 | D41: =COUNTIFS(Movies!$B:$B,$B41,Movies!$D:$D,"Medium") -> 578 | E41: =COUNTIFS(Movies!$B:$B,$B41,Movies!$D:$D,"Hard") -> 330
A42: Movies | B42: India | C42: =COUNTIFS(Movies!$B:$B,$B42,Movies!$D:$D,"Easy") -> 534 | D42: =COUNTIFS(Movies!$B:$B,$B42,Movies!$D:$D,"Medium") -> 415 | E42: =COUNTIFS(Movies!$B:$B,$B42,Movies!$D:$D,"Hard") -> 238
A43: Music | B43: Global | C43: =COUNTIFS(Music!$B:$B,$B43,Music!$D:$D,"Easy") -> 1564 | D43: =COUNTIFS(Music!$B:$B,$B43,Music!$D:$D,"Medium") -> 1216 | E43: =COUNTIFS(Music!$B:$B,$B43,Music!$D:$D,"Hard") -> 695
A44: Music | B44: India | C44: =COUNTIFS(Music!$B:$B,$B44,Music!$D:$D,"Easy") -> 1068 | D44: =COUNTIFS(Music!$B:$B,$B44,Music!$D:$D,"Medium") -> 831 | E44: =COUNTIFS(Music!$B:$B,$B44,Music!$D:$D,"Hard") -> 475
A45: Icons | B45: Global | C45: =COUNTIFS(Icons!$B:$B,$B45,Icons!$E:$E,"Easy") -> 302 | D45: =COUNTIFS(Icons!$B:$B,$B45,Icons!$E:$E,"Medium") -> 235 | E45: =COUNTIFS(Icons!$B:$B,$B45,Icons!$E:$E,"Hard") -> 134
A46: Icons | B46: India | C46: =COUNTIFS(Icons!$B:$B,$B46,Icons!$E:$E,"Easy") -> 150 | D46: =COUNTIFS(Icons!$B:$B,$B46,Icons!$E:$E,"Medium") -> 117 | E46: =COUNTIFS(Icons!$B:$B,$B46,Icons!$E:$E,"Hard") -> 66

Sheet Movies
A1: ID | B1: Edition | C1: Industry | D1: Difficulty | E1: Answer | F1: Accepted aliases | G1: Year | H1: Hint 1 (shown at start) | I1: Hint 2 (after miss 1) | J1: Hint 3 (after miss 2) | K1: Hint 4 (after miss 3) | L1: Hint 5 (after miss 4) | M1: Hint 6 (after miss 5, with options) | N1: Wrong option A | O1: Wrong option B | P1: Wrong option C | Q1: Reveal-card fact | R1: Director | S1: Music | T1: Lead | U1: Source | V1: Verify flag | W1: Fame score (0-10) | X1: Score signals
A2: MOV-G-00009 | B2: Global | C2: Hollywood | D2: Easy | E2: A Beautiful Mind | F2: Beautiful Mind | G2: 2001 | H2: Genre: Biography, Drama · Hollywood · released 2001 | I2: Directed by: Ron Howard | J2: Moment: At ____ struggles to make a worthwhile contribution to serve as his legacy to the world of mathematics. | K2: Co-stars: Jennifer Connelly, Ed Harris | L2: Lead: Russell Crowe · music by James Horner | M2: Title initials: A. B. M. (3 words) | N2: Coach Carter | O2: Jarhead | P2: The Queen | Q2: Released 2001-12-11; 135 min; worldwide gross about US$314 million (TMDB); tagline: "I need to believe that something extra ordinary is possible..." | R2: Ron Howard | S2: James Horner | T2: Russell Crowe | U2: TMDB 5000 (vote count ≥300); cast from Wikipedia Movie Data | V2: Plot hint is source synopsis text – rewrite before launch; Hints rebuilt Oct 2026 for a 75–90% solve target | W2: 10 | X2: IMDb 1,066,185 votes · 8.2/10 · 86 Wikipedias · lead fame 125
A3: MOV-G-00028 | B3: Global | C3: Hollywood | D3: Easy | E3: Avengers: Endgame | F3: Avengers Endgame | G3: 2019 | H3: Genre: Action, Adventure · Hollywood · released 2019 | I3: Directed by: Anthony and Joe Russo | J3: Moment: Survivors travel through time to reverse the snap | K3: Co-stars: Chris Evans, Mark Ruffalo | L3: Lead: Robert Downey Jr. · music by Alan Silvestri | M3: Title initials: A. E. (2 words) | N3: Cop Out | O3: Tower Heist | P3: The Huntsman: Winter's War | Q3: Released 2019 | R3: Anthony and Joe Russo | S3: Alan Silvestri | T3: Robert Downey Jr. | U3: Curated by Claude; director and lead cross-checked against Wikipedia Movie Data where available | V3: Curated (2017–2025 gap in TMDB) – plot line written by Claude; Wikipedia cross-check: director OK, lead OK; Hints rebuilt Oct 2026 for a 75–90% solve target | W3: 10 | X3: IMDb 1,500,097 votes · 8.4/10 · 90 Wikipedias · lead fame 112
A4: MOV-G-00029 | B4: Global | C4: Hollywood | D4: Easy | E4: Avengers: Infinity War | F4: Avengers Infinity War | G4: 2018 | H4: Genre: Action, Adventure · Hollywood · released 2018 | I4: Directed by: Anthony and Joe Russo | J4: Moment: A villain collects six stones and wipes out half of all life with a snap | K4: Co-stars: Chris Hemsworth, Mark Ruffalo | L4: Lead: Robert Downey Jr. · music by Alan Silvestri | M4: Title initials: A. I. W. (3 words) | N4: The Legend of Hercules | O4: The Book of Eli | P4: Kung Fu Panda 3 | Q4: Released 2018 | R4: Anthony and Joe Russo | S4: Alan Silvestri | T4: Robert Downey Jr. | U4: Curated by Claude; director and lead cross-checked against Wikipedia Movie Data where available | V4: Curated (2017–2025 gap in TMDB) – plot line written by Claude; Wikipedia cross-check: director OK, lead OK; Hints rebuilt Oct 2026 for a 75–90% solve target | W4: 10 | X4: IMDb 1,417,740 votes · 8.4/10 · 86 Wikipedias · lead fame 112
A5: MOV-G-00043 | B5: Global | C5: Hollywood | D5: Easy | E5: Braveheart | G5: 1995 | H5: Genre: Drama, War · Hollywood · released 1995 | I5: Directed by: Mel Gibson | J5: Moment: Enraged at the slaughter of ____, his new bride and childhood love, ____ warrior ____ slays a platoon of the local ____ lord's soldiers. | K5: Co-stars: Sophie Marceau, Catherine McCormack | L5: Lead: Mel Gibson · music by James Horner | M5: Title: one word, 10 letters, starts with 'B' | N5: The Last of the Mohicans | O5: Enemy of the State | P5: Die Hard: With a Vengeance | Q5: Released 1995-05-24; 177 min; worldwide gross about US$210 million (TMDB); tagline: "Every man dies. Not every man truly lives." | R5: Mel Gibson | S5: James Horner | T5: Mel Gibson | U5: TMDB 5000 (vote count ≥300); cast from Wikipedia Movie Data | V5: Plot hint is source synopsis text – rewrite before launch; Hints rebuilt Oct 2026 for a 75–90% solve target | W5: 10 | X5: IMDb 1,174,695 votes · 8.3/10 · 92 Wikipedias · lead fame 119
A6: MOV-G-00052 | B6: Global | C6: Hollywood | D6: Easy | E6: Catch Me If You Can | G6: 2002 | H6: Genre: Biography, Crime · Hollywood · released 2002 | I6: Directed by: Steven Spielberg | J6: Moment: A true story about ____. | K6: Co-stars: Tom Hanks, Christopher Walken | L6: Lead: Leonardo DiCaprio · music by John Williams | M6: Title initials: C. M. I. Y. C. (5 words) | N6: Million Dollar Baby | O6: Vicky Cristina Barcelona | P6: The Young Victoria | Q6: Released 2002-12-25; 141 min; worldwide gross about US$352 million (TMDB); tagline: "The true story of a real fake." | R6: Steven Spielberg | S6: John Williams | T6: Leonardo DiCaprio | U6: TMDB 5000 (vote count ≥300); cast from Wikipedia Movie Data | V6: Plot hint is source synopsis text – rewrite before launch; Hints rebuilt Oct 2026 for a 75–90% solve target | W6: 10 | X6: IMDb 1,269,603 votes · 8.1/10 · 76 Wikipedias · lead fame 149
A7: MOV-G-00078 | B7: Global | C7: Hollywood | D7: Easy | E7: Eternal Sunshine of the Spotless Mind | G7: 2004 | H7: Genre: Drama, Romance · Hollywood · released 2004 | I7: Directed by: Michel Gondry | J7: Moment: Joel ____, heartbroken that his girlfriend underwent a procedure to erase him from her memory, decides to do the same. | K7: Co-stars: Kate Winslet, Kirsten Dunst | L7: Lead: Jim Carrey · music by Jon Brion | M7: Title initials: E. S. O. T. S. M. (6 words) | N7: Unbreakable | O7: Primer | P7: The Mist | Q7: Released 2004-03-19; 108 min; worldwide gross about US$72 million (TMDB); tagline: "You can erase someone from your mind. Getting them out of your heart is another story." | R7: Michel Gondry | S7: Jon Brion | T7: Jim Carrey | U7: TMDB 5000 (vote count ≥300); cast from Wikipedia Movie Data | V7: Plot hint is source synopsis text – rewrite before launch; Hints rebuilt Oct 2026 for a 75–90% solve target | W7: 10 | X7: IMDb 1,199,593 votes · 8.3/10 · 67 Wikipedias · lead fame 126
A8: MOV-G-00084 | B8: Global | C8: Hollywood | D8: Easy | E8: Fight Club | G8: 1999 | H8: Genre: Crime, Drama · Hollywood · released 1999 | I8: Directed by: David Fincher | J8: Moment: A ticking-time-bomb insomniac and a slippery soap salesman channel primal male aggression into a shocking new form of therapy. | K8: Co-stars: Edward Norton, Helena Bonham Carter | L8: Lead: Brad Pitt · music by John King & Michael Simpson | M8: Title initials: F. C. (2 words) | N8: The Shawshank Redemption | O8: Good Will Hunting | P8: Ever After: A Cinderella Story | Q8: Released 1999-10-15; 139 min; worldwide gross about US$101 million (TMDB); tagline: "Mischief. Mayhem. Soap." | R8: David Fincher | S8: John King & Michael Simpson | T8: Brad Pitt | U8: TMDB 5000 (vote count ≥300); cast from Wikipedia Movie Data | V8: Plot hint is source synopsis text – rewrite before launch; Hints rebuilt Oct 2026 for a 75–90% solve target | W8: 10 | X8: IMDb 2,673,124 votes · 8.8/10 · 102 Wikipedias · lead fame 147
A9: MOV-G-00087 | B9: Global | C9: Hollywood | D9: Easy | E9: Forrest Gump | G9: 1994 | H9: Genre: Drama, Romance · Hollywood · released 1994 | I9: Directed by: Robert Zemeckis | J9: Moment: A man with a low ____ has accomplished great things in his life and been present during significant historic events - in each case, far exceeding what anyone imagined he could do. | K9: Co-stars: Robin Wright Penn, Haley Joel Osment | L9: Lead: Tom Hanks · music by Alan Silvestri | M9: Title initials: F. G. (2 words) | N9: Dazed and Confused | O9: Four Weddings and a Funeral | P9: Man on the Moon | Q9: Released 1994-07-06; 142 min; worldwide gross about US$678 million (TMDB); tagline: "The world will never be the same, once you've seen it through the eyes of Forrest Gump." | R9: Robert Zemeckis | S9: Alan Silvestri | T9: Tom Hanks | U9: TMDB 5000 (vote count ≥300); cast from Wikipedia Movie Data | V9: Plot hint is source synopsis text – rewrite before launch; Hints rebuilt Oct 2026 for a 75–90% solve target | W9: 10 | X9: IMDb 2,544,942 votes · 8.8/10 · 137 Wikipedias · lead fame 136
A10: MOV-G-00094 | B10: Global | C10: Hollywood | D10: Easy | E10: Gladiator | G10: 2000 | H10: Genre: Action, Adventure · Hollywood · released 2000 | I10: Directed by: Ridley Scott | J10: Moment: In the year 180, the death of emperor ____ throws the ____ into chaos. | K10: Co-stars: Joaquin Phoenix, Connie Nielsen | L10: Lead: Russell Crowe · music by Hans Zimmer & Lisa Gerrard | M10: Title: one word, 9 letters, starts with 'G' | N10: The Scorpion King | O10: Get Smart | P10: Shaft | Q10: Released 2000-05-01; 155 min; worldwide gross about US$458 million (TMDB); tagline: "A Hero Will Rise." | R10: Ridley Scott | S10: Hans Zimmer & Lisa Gerrard | T10: Russell Crowe | U10: TMDB 5000 (vote count ≥300); cast from Wikipedia Movie Data | V10: Plot hint is source synopsis text – rewrite before launch; Hints rebuilt Oct 2026 for a 75–90% solve target | W10: 10 | X10: IMDb 1,888,826 votes · 8.5/10 · 108 Wikipedias · lead fame 125
A11: MOV-G-00095 | B11: Global | C11: Hollywood | D11: Easy | E11: Gone Girl | G11: 2014 | H11: Genre: Drama, Mystery · Hollywood · released 2014 | I11: Directed by: David Fincher | J11: Moment: With his wife's disappearance having become the focus of an intense media circus, a man sees the spotlight turned on him when it's suspected that he may not be innocent. | K11: Co-stars: Rosamund Pike, Neil Patrick Harris | L11: Lead: Ben Affleck · music by Trent Reznor & Atticus Ross | M11: Title initials: G. G. (2 words) | N11: Nerve | O11: The Witch | P11: The Crazies | Q11: Released 2014-10-01; 145 min; worldwide gross about US$369 million (TMDB); tagline: "You don't know what you've got 'til it's..." | R11: David Fincher | S11: Trent Reznor & Atticus Ross | T11: Ben Affleck | U11: TMDB 5000 (vote count ≥300); cast from Wikipedia Movie Data | V11: Plot hint is source synopsis text – rewrite before launch; Hints rebuilt Oct 2026 for a 75–90% solve target | W11: 10 | X11: IMDb 1,191,907 votes · 8.1/10 · 60 Wikipedias · lead fame 112
A12: MOV-G-00096 | B12: Global | C12: Hollywood | D12: Easy | E12: Good Will Hunting | G12: 1997 | H12: Genre: Drama, Romance · Hollywood · released 1997 | I12: Directed by: Gus Van Sant | J12: Moment: ____ has a genius-level ____ but chooses to work as a janitor at ____. | K12: Co-stars: Robin Williams, Ben Affleck | L12: Lead: Matt Damon · music by Danny Elfman | M12: Title initials: G. W. H. (3 words) | N12: Contact | O12: The Pelican Brief | P12: American History X | Q12: Released 1997-12-05; 126 min; worldwide gross about US$226 million (TMDB); tagline: "Some people can never believe in themselves, until someone believes in them." | R12: Gus Van Sant | S12: Danny Elfman | T12: Matt Damon | U12: TMDB 5000 (vote count ≥300); cast from Wikipedia Movie Data | V12: Plot hint is source synopsis text – rewrite before launch; Hints rebuilt Oct 2026 for a 75–90% solve target | W12: 10 | X12: IMDb 1,248,120 votes · 8.4/10 · 70 Wikipedias · lead fame 114
A13: MOV-G-00097 | B13: Global | C13: Hollywood | D13: Easy | E13: GoodFellas | G13: 1990 | H13: Genre: Biography, Crime · Hollywood · released 1990 | I13: Directed by: Martin Scorsese | J13: Moment: The true story of ____, a half-Irish, half-Sicilian ____ kid who is adopted by neighbourhood gangsters at an early age and climbs the ranks of a ____ family under the guidance of ____. | K13: Co-stars: Ray Liotta, Joe Pesci | L13: Lead: Robert De Niro | M13: Title: one word, 10 letters, starts with 'G' | N13: The Bridges of Madison County | O13: Fight Club | P13: Patriot Games | Q13: Released 1990-09-12; 145 min; worldwide gross about US$47 million (TMDB); tagline: "Three Decades of Life in the Mafia." | R13: Martin Scorsese | T13: Robert De Niro | U13: TMDB 5000 (vote count ≥300); cast from Wikipedia Movie Data | V13: Plot hint is source synopsis text – rewrite before launch; Hints rebuilt Oct 2026 for a 75–90% solve target | W13: 10 | X13: IMDb 1,418,891 votes · 8.7/10 · 73 Wikipedias · lead fame 139
A14: MOV-G-00100 | B14: Global | C14: Hollywood | D14: Easy | E14: Guardians of the Galaxy | G14: 2014 | H14: Genre: Action, Adventure · Hollywood · released 2014 | I14: Directed by: James Gunn | J14: Moment: Light years from ____, 26 years after being abducted, ____ finds himself the prime target of a manhunt after discovering an orb wanted by ____ the ____. | K14: Co-stars: Zoe Saldana, Dave Bautista | L14: Lead: Chris Pratt · music by Tyler Bates | M14: Title initials: G. O. T. G. (4 words) | N14: No Escape | O14: Killer Elite | P14: Sucker Punch | Q14: Released 2014-07-30; 121 min; worldwide gross about US$773 million (TMDB); tagline: "All heroes start somewhere." | R14: James Gunn | S14: Tyler Bates | T14: Chris Pratt | U14: TMDB 5000 (vote count ≥300); cast from Wikipedia Movie Data | V14: Plot hint is source synopsis text – rewrite before launch; Hints rebuilt Oct 2026 for a 75–90% solve target | W14: 10 | X14: IMDb 1,388,962 votes · 8.0/10 · 72 Wikipedias · lead fame 127
A15: MOV-G-00120 | B15: Global | C15: Hollywood | D15: Easy | E15: Inception | G15: 2010 | H15: Genre: Adventure, Sci-Fi · Hollywood · released 2010 | I15: Directed by: Christopher Nolan | J15: Moment: Cobb, a skilled thief who commits corporate espionage by infiltrating the subconscious of his targets is offered a chance to regain his old life as payment for a task considered to be impossible: "____", the… | K15: Co-stars: Ken Watanabe, Joseph Gordon-Levitt | L15: Lead: Leonardo DiCaprio · music by Hans Zimmer | M15: Title: one word, 9 letters, starts with 'I' | N15: The Last Stand | O15: The Tourist | P15: 30 Minutes or Less | Q15: Released 2010-07-14; 148 min; worldwide gross about US$826 million (TMDB); tagline: "Your mind is the scene of the crime." | R15: Christopher Nolan | S15: Hans Zimmer | T15: Leonardo DiCaprio | U15: TMDB 5000 (vote count ≥300); cast from Wikipedia Movie Data | V15: Plot hint is source synopsis text – rewrite before launch; Hints rebuilt Oct 2026 for a 75–90% solve target | W15: 10 | X15: IMDb 2,880,007 votes · 8.8/10 · 97 Wikipedias · lead fame 149
A16: MOV-G-00124 | B16: Global | C16: Hollywood | D16: Easy | E16: Inglourious Basterds | G16: 2009 | H16: Genre: Drama, War · Hollywood · released 2009 | I16: Directed by: Quentin Tarantino | J16: Moment: In Nazi-occupied ____ during ____, a group of Jewish-American soldiers known as "The ____" are chosen specifically to spread fear throughout the ____ by scalping and brutally killing ____. | K16: Co-stars: Mélanie Laurent, Christoph Waltz | L16: Lead: Brad Pitt | M16: Title initials: I. B. (2 words) | N16: Finding Forrester | O16: Rocky Balboa | P16: Syriana | Q16: Released 2009-08-18; 153 min; worldwide gross about US$319 million (TMDB); tagline: "Once upon a time in Nazi occupied France..." | R16: Quentin Tarantino | T16: Brad Pitt | U16: TMDB 5000 (vote count ≥300); cast from Wikipedia Movie Data | V16: Plot hint is source synopsis text – rewrite before launch; Hints rebuilt Oct 2026 for a 75–90% solve target | W16: 10 | X16: IMDb 1,824,292 votes · 8.4/10 · 80 Wikipedias · lead fame 147
A17: MOV-G-00130 | B17: Global | C17: Hollywood | D17: Easy | E17: Iron Man | G17: 2008 | H17: Genre: Action, Adventure · Hollywood · released 2008 | I17: Directed by: Jon Favreau | J17: Moment: After being held captive in an ____ cave, billionaire engineer ____ creates a unique weaponized suit of armor to fight evil. | K17: Co-stars: Terrence Howard, Jeff Bridges | L17: Lead: Robert Downey Jr. · music by Ramin Djawadi | M17: Title initials: I. M. (2 words) | N17: Lara Croft Tomb Raider: The Cradle of Life | O17: Sahara | P17: Kill Bill: Vol. 2 | Q17: Released 2008-04-30; 126 min; worldwide gross about US$585 million (TMDB); tagline: "Heroes aren't born. They're built." | R17: Jon Favreau | S17: Ramin Djawadi | T17: Robert Downey Jr. | U17: TMDB 5000 (vote count ≥300); cast from Wikipedia Movie Data | V17: Plot hint is source synopsis text – rewrite before launch; Hints rebuilt Oct 2026 for a 75–90% solve target | W17: 10 | X17: IMDb 1,254,769 votes · 7.9/10 · 84 Wikipedias · lead fame 112
A18: MOV-G-00198 | B18: Global | C18: Hollywood | D18: Easy | E18: Pulp Fiction | G18: 1994 | H18: Genre: Crime, Drama · Hollywood · released 1994 | I18: Directed by: Quentin Tarantino | J18: Moment: A burger-loving hit man, his philosophical partner, a drug-addled gangster's moll and a washed-up boxer converge in this sprawling, comedic crime caper. | K18: Co-stars: Samuel L. Jackson, Bruce Willis | L18: Lead: John Travolta · music by Mary Ramos | M18: Title initials: P. F. (2 words) | N18: The Talented Mr. Ripley | O18: Gattaca | P18: The Thirteenth Floor | Q18: Released 1994-10-08; 154 min; worldwide gross about US$214 million (TMDB); tagline: "Just because you are a character doesn't mean you have character." | R18: Quentin Tarantino | S18: Mary Ramos | T18: John Travolta | U18: TMDB 5000 (vote count ≥300); cast from Wikipedia Movie Data | V18: Plot hint is source synopsis text – rewrite before launch; Hints rebuilt Oct 2026 for a 75–90% solve target | W18: 10 | X18: IMDb 2,476,095 votes · 8.8/10 · 107 Wikipedias · lead fame 117
A19: MOV-G-00209 | B19: Global | C19: Hollywood | D19: Easy | E19: Saving Private Ryan | G19: 1998 | H19: Genre: Drama, War · Hollywood · released 1998 | I19: Directed by: Steven Spielberg | J19: Moment: As U.S. | K19: Co-stars: Edward Burns, Matt Damon | L19: Lead: Tom Hanks · music by John Williams | M19: Title initials: S. P. R. (3 words) | N19: The Bone Collector | O19: Fight Club | P19: Schindler's List | Q19: Released 1998-07-24; 169 min; worldwide gross about US$482 million (TMDB); tagline: "The mission is a man." | R19: Steven Spielberg | S19: John Williams | T19: Tom Hanks | U19: TMDB 5000 (vote count ≥300); cast from Wikipedia Movie Data | V19: Plot hint is source synopsis text – rewrite before launch; Hints rebuilt Oct 2026 for a 75–90% solve target | W19: 10 | X19: IMDb 1,667,972 votes · 8.6/10 · 86 Wikipedias · lead fame 136
A20: MOV-G-00212 | B20: Global | C20: Hollywood | D20: Easy | E20: Se7en | G20: 1995 | H20: Genre: Crime, Drama · Hollywood · released 1995 | I20: Directed by: David Fincher | J20: Moment: Two homicide detectives are on a desperate hunt for a serial killer whose crimes are based on the "seven deadly sins" in this dark and haunting film that takes viewers from the tortured remains of one victim to the next. | K20: Co-stars: Morgan Freeman | L20: Lead: Brad Pitt · music by Howard Shore | M20: Title: one word, 5 letters, starts with 'S' | N20: Four Rooms | O20: Boys Don't Cry | P20: Boyz n the Hood | Q20: Released 1995-09-22; 127 min; worldwide gross about US$327 million (TMDB); tagline: "Seven deadly sins. Seven ways to die." | R20: David Fincher | S20: Howard Shore | T20: Brad Pitt | U20: TMDB 5000 (vote count ≥300); cast from Wikipedia Movie Data | V20: Plot hint is source synopsis text – rewrite before launch; Hints rebuilt Oct 2026 for a 75–90% solve target | W20: 10 | X20: IMDb 2,068,870 votes · 8.6/10 · 73 Wikipedias · lead fame 147
A21: MOV-G-00217 | B21: Global | C21: Hollywood | D21: Easy | E21: Shutter Island | G21: 2010 | H21: Genre: Mystery, Thriller · Hollywood · released 2010 | I21: Directed by: Martin Scorsese | J21: Moment: World ____ soldier-turned-U.S. | K21: Co-stars: Mark Ruffalo, Ben Kingsley | L21: Lead: Leonardo DiCaprio | M21: Title initials: S. I. (2 words) | N21: Remember Me | O21: Rush | P21: The Martian | Q21: Released 2010-02-18; 138 min; worldwide gross about US$295 million (TMDB); tagline: "Someone is missing." | R21: Martin Scorsese | T21: Leonardo DiCaprio | U21: TMDB 5000 (vote count ≥300); cast from Wikipedia Movie Data | V21: Plot hint is source synopsis text – rewrite before launch; Hints rebuilt Oct 2026 for a 75–90% solve target | W21: 10 | X21: IMDb 1,691,256 votes · 8.2/10 · 71 Wikipedias · lead fame 149
A22: MOV-G-00233 | B22: Global | C22: Hollywood | D22: Easy | E22: Spider-Man: No Way Home | F22: SpiderMan No Way Home | G22: 2021 | H22: Genre: Action, Adventure · Hollywood · released 2021 | I22: Directed by: Jon Watts | J22: Moment: A spell goes wrong and villains from other universes arrive | K22: Co-stars: Benedict Cumberbatch, Zendaya | L22: Lead: Tom Holland · music by Michael Giacchino | M22: Title initials: S. N. W. H. (4 words) | N22: The Batman | O22: No Time to Die | P22: Shang-Chi and the Legend of the Ten Rings | Q22: Released 2021 | R22: Jon Watts | S22: Michael Giacchino | T22: Tom Holland | U22: Curated by Claude; director and lead cross-checked against Wikipedia Movie Data where available | V22: Curated (2017–2025 gap in TMDB) – plot line written by Claude; Wikipedia cross-check: director OK, lead OK; Hints rebuilt Oct 2026 for a 75–90% solve target | W22: 10 | X22: IMDb 1,081,846 votes · 8.1/10 · 70 Wikipedias · lead fame 118
A23: MOV-G-00252 | B23: Global | C23: Hollywood | D23: Easy | E23: Terminator 2: Judgment Day | F23: Terminator 2 Judgment Day | G23: 1991 | H23: Genre: Action, Adventure · Hollywood · released 1991 | I23: Directed by: James Cameron | J23: Moment: Nearly 10 years have passed since ____ was targeted for termination by a cyborg from the future. | K23: Co-stars: Linda Hamilton, Robert Patrick | L23: Lead: Arnold Schwarzenegger · music by Brad Fiedel | M23: Title initials: T. 2. J. D. (4 words) | N23: Speed 2: Cruise Control | O23: eXistenZ | P23: The Last of the Mohicans | Q23: Released 1991-07-01; 137 min; worldwide gross about US$520 million (TMDB); tagline: "It's nothing personal." | R23: James Cameron | S23: Brad Fiedel | T23: Arnold Schwarzenegger | U23: TMDB 5000 (vote count ≥300); cast from Wikipedia Movie Data | V23: Plot hint is source synopsis text – rewrite before launch; Hints rebuilt Oct 2026 for a 75–90% solve target | W23: 10 | X23: IMDb 1,306,414 votes · 8.6/10 · 93 Wikipedias · lead fame 153
A24: MOV-G-00256 | B24: Global | C24: Hollywood | D24: Easy | E24: The Avengers | F24: Avengers | G24: 2012 | H24: Genre: Action, Sci-Fi · Hollywood · released 2012 | I24: Directed by: Joss Whedon | J24: Moment: When an unexpected enemy emerges and threatens global safety and security, ____, director of the international peacekeeping agency known as S.H.I.E.L.D., finds himself in need of a team to pull the world back from… | K24: Co-stars: Chris Evans, Chris Hemsworth | L24: Lead: Robert Downey Jr. · music by Alan Silvestri | M24: Title initials: T. A. (2 words) | N24: Skyline | O24: Terminator Genisys | P24: The Hunger Games | Q24: Released 2012-04-25; 143 min; worldwide gross about US$1,520 million (TMDB); tagline: "Some assembly required." | R24: Joss Whedon | S24: Alan Silvestri | T24: Robert Downey Jr. | U24: TMDB 5000 (vote count ≥300); cast from Wikipedia Movie Data | V24: Plot hint is source synopsis text – rewrite before launch; Hints rebuilt Oct 2026 for a 75–90% solve target | W24: 10 | X24: IMDb 1,587,985 votes · 8.0/10 · 96 Wikipedias · lead fame 112
A25: MOV-G-00270 | B25: Global | C25: Hollywood | D25: Easy | E25: The Departed | F25: Departed | G25: 2006 | H25: Genre: Crime, Drama · Hollywood · released 2006 | I25: Directed by: Martin Scorsese | J25: Moment: To take down ____, the police send in one of their own to infiltrate the underworld, not realizing the syndicate has done likewise. | K25: Co-stars: Matt Damon, Jack Nicholson | L25: Lead: Leonardo DiCaprio · music by Howard Shore | M25: Title initials: T. D. (2 words) | N25: Dancer in the Dark | O25: The Life of David Gale | P25: Chloe | Q25: Released 2006-10-05; 151 min; worldwide gross about US$290 million (TMDB); tagline: "Lies. Betrayal. Sacrifice. How far will you take it?" | R25: Martin Scorsese | S25: Howard Shore | T25: Leonardo DiCaprio | U25: TMDB 5000 (vote count ≥300); cast from Wikipedia Movie Data | V25: Plot hint is source synopsis text – rewrite before launch; Hints rebuilt Oct 2026 for a 75–90% solve target | W25: 10 | X25: IMDb 1,584,785 votes · 8.5/10 · 80 Wikipedias · lead fame 149
A26: MOV-G-00283 | B26: Global | C26: Hollywood | D26: Easy | E26: The Green Mile | F26: Green Mile | G26: 1999 | H26: Genre: Crime, Drama · Hollywood · released 1999 | I26: Directed by: Frank Darabont | J26: Moment: A supernatural tale set on death row in a ____ prison, where gentle giant ____ possesses the mysterious power to heal people's ailments. | K26: Co-stars: David Morse, Bonnie Hunt | L26: Lead: Tom Hanks · music by Thomas Newman | M26: Title initials: T. G. M. (3 words) | N26: Meet Joe Black | O26: DragonHeart | P26: The Santa Clause | Q26: Released 1999-12-10; 189 min; worldwide gross about US$285 million (TMDB); tagline: "Miracles do happen." | R26: Frank Darabont | S26: Thomas Newman | T26: Tom Hanks | U26: TMDB 5000 (vote count ≥300); cast from Wikipedia Movie Data | V26: Plot hint is source synopsis text – rewrite before launch; Hints rebuilt Oct 2026 for a 75–90% solve target | W26: 10 | X26: IMDb 1,591,837 votes · 8.6/10 · 77 Wikipedias · lead fame 136
A27: MOV-G-00304 | B27: Global | C27: Hollywood | D27: Easy | E27: The Martian | F27: Martian | G27: 2015 | H27: Genre: Adventure, Drama · Hollywood · released 2015 | I27: Directed by: Ridley Scott | J27: Moment: During a manned mission to ____ is presumed dead after a fierce storm and left behind by his crew. | K27: Co-stars: Jessica Chastain, Kristen Wiig | L27: Lead: Matt Damon · music by Harry Gregson-Williams | M27: Title initials: T. M. (2 words) | N27: Dear John | O27: The Giver | P27: This Is Where I Leave You | Q27: Released 2015-09-30; 141 min; worldwide gross about US$630 million (TMDB); tagline: "Bring Him Home" | R27: Ridley Scott | S27: Harry Gregson-Williams | T27: Matt Damon | U27: TMDB 5000 (vote count ≥300); cast from Wikipedia Movie Data | V27: Plot hint is source synopsis text – rewrite before launch; Hints rebuilt Oct 2026 for a 75–90% solve target | W27: 10 | X27: IMDb 1,033,635 votes · 8.0/10 · 72 Wikipedias · lead fame 114
A28: MOV-G-00305 | B28: Global | C28: Hollywood | D28: Easy | E28: The Matrix | F28: Matrix | G28: 1999 | H28: Genre: Action, Sci-Fi · Hollywood · released 1999 | I28: Directed by: Lilly Wachowski | J28: Moment: Set in the 22nd century, The ____ tells the story of a computer hacker who joins a group of underground insurgents fighting the vast and powerful computers who now rule the earth. | K28: Co-stars: Laurence Fishburne, Carrie-Anne Moss | L28: Lead: Keanu Reeves · music by Don Davis | M28: Title initials: T. M. (2 words) | N28: The Man in the Iron Mask | O28: Deep Impact | P28: Bad Boys | Q28: Released 1999-03-30; 136 min; worldwide gross about US$464 million (TMDB); tagline: "Welcome to the Real World." | R28: Lilly Wachowski | S28: Don Davis | T28: Keanu Reeves | U28: TMDB 5000 (vote count ≥300); cast from Wikipedia Movie Data | V28: Plot hint is source synopsis text – rewrite before launch; Hints rebuilt Oct 2026 for a 75–90% solve target | W28: 10 | X28: IMDb 2,286,709 votes · 8.7/10 · 114 Wikipedias · lead fame 124
A29: MOV-G-00313 | B29: Global | C29: Hollywood | D29: Easy | E29: The Revenant | F29: Revenant | G29: 2015 | H29: Genre: Action, Drama · Hollywood · released 2015 | I29: Directed by: Alejandro Gonz\u00e1lez I\u00f1\u00e1rritu | J29: Moment: In the 1820s, a frontiersman, ____, sets out on a path of vengeance against those who left him for dead after a bear mauling. | K29: Co-stars: Tom Hardy | L29: Lead: Leonardo DiCaprio · music by Ryuichi Sakamoto & Carsten Nicolai | M29: Title initials: T. R. (2 words) | N29: Sanctum | O29: The Counselor | P29: This Is 40 | Q29: Released 2015-12-25; 156 min; worldwide gross about US$533 million (TMDB); tagline: "(n. One who has returned, as if from the dead.)" | R29: Alejandro Gonz\u00e1lez I\u00f1\u00e1rritu | S29: Ryuichi Sakamoto & Carsten Nicolai | T29: Leonardo DiCaprio | U29: TMDB 5000 (vote count ≥300); cast from Wikipedia Movie Data | V29: Plot hint is source synopsis text – rewrite before launch; Hints rebuilt Oct 2026 for a 75–90% solve target | W29: 10 | X29: IMDb 965,251 votes · 8.0/10 · 73 Wikipedias · lead fame 149
A30: MOV-G-00318 | B30: Global | C30: Hollywood | D30: Easy | E30: The Silence of the Lambs | F30: Silence of the Lambs | G30: 1991 | H30: Genre: Crime, Drama · Hollywood · released 1991 | I30: Directed by: Jonathan Demme | J30: Moment: FBI trainee, ____ ventures into a maximum-security asylum to pick the diseased brain of ____, a psychiatrist turned homicidal cannibal. | K30: Co-stars: Jodie Foster, Scott Glenn | L30: Lead: Anthony Hopkins · music by Howard Shore | M30: Title initials: T. S. O. T. L. (5 words) | N30: Donnie Brasco | O30: Wild Things | P30: Sleepers | Q30: Released 1991-02-01; 119 min; worldwide gross about US$273 million (TMDB); tagline: "To enter the mind of a killer she must challenge the mind of a madman." | R30: Jonathan Demme | S30: Howard Shore | T30: Anthony Hopkins | U30: TMDB 5000 (vote count ≥300); cast from Wikipedia Movie Data | V30: Plot hint is source synopsis text – rewrite before launch; Hints rebuilt Oct 2026 for a 75–90% solve target | W30: 10 | X30: IMDb 1,758,444 votes · 8.6/10 · 102 Wikipedias · lead fame 120
A31: MOV-G-00319 | B31: Global | C31: Hollywood | D31: Easy | E31: The Sixth Sense | F31: Sixth Sense | G31: 1999 | H31: Genre: Drama, Mystery · Hollywood · released 1999 | I31: Directed by: M. Night Shyamalan | J31: Moment: A psychological thriller about an eight year old boy named ____ who believes he can see into the world of the dead. | K31: Co-stars: Haley Joel Osment, Toni Collette | L31: Lead: Bruce Willis · music by James Newton Howard | M31: Title initials: T. S. S. (3 words) | N31: The X Files | O31: Eyes Wide Shut | P31: Dark City | Q31: Released 1999-08-06; 107 min; worldwide gross about US$673 million (TMDB); tagline: "Not every gift is a blessing." | R31: M. Night Shyamalan | S31: James Newton Howard | T31: Bruce Willis | U31: TMDB 5000 (vote count ≥300); cast from Wikipedia Movie Data | V31: Plot hint is source synopsis text – rewrite before launch; Hints rebuilt Oct 2026 for a 75–90% solve target | W31: 10 | X31: IMDb 1,170,146 votes · 8.2/10 · 68 Wikipedias · lead fame 117
A32: MOV-G-00324 | B32: Global | C32: Hollywood | D32: Easy | E32: The Truman Show | F32: Truman Show | G32: 1998 | H32: Genre: Comedy, Drama · Hollywood · released 1998 | I32: Directed by: Peter Weir | J32: Moment: ____ is the star of "The ____", a 24-hour-a-day "reality" ____ that broadcasts every aspect of his life -- live and in color -- without his knowledge. | K32: Co-stars: Ed Harris, Laura Linney | L32: Lead: Jim Carrey · music by Burkhard von Dallwitz | M32: Title initials: T. T. S. (3 words) | N32: Mars Attacks! | O32: The Naked Gun 33⅓: The Final Insult | P32: Deuce Bigalow: Male Gigolo | Q32: Released 1998-06-04; 103 min; worldwide gross about US$264 million (TMDB); tagline: "On the air. Unaware." | R32: Peter Weir | S32: Burkhard von Dallwitz | T32: Jim Carrey | U32: TMDB 5000 (vote count ≥300); cast from Wikipedia Movie Data | V32: Plot hint is source synopsis text – rewrite before launch; Hints rebuilt Oct 2026 for a 75–90% solve target | W32: 10 | X32: IMDb 1,412,965 votes · 8.2/10 · 73 Wikipedias · lead fame 126
A33: MOV-G-00327 | B33: Global | C33: Hollywood | D33: Easy | E33: The Wolf of Wall Street | F33: Wolf of Wall Street | G33: 2013 | H33: Genre: Biography, Comedy · Hollywood · released 2013 | I33: Directed by: Martin Scorsese | J33: Moment: A ____ stockbroker refuses to cooperate in a large securities fraud case involving corruption on ____, corporate banking world and mob infiltration. | K33: Co-stars: Jonah Hill, Matthew McConaughey | L33: Lead: Leonardo DiCaprio · music by Bryan Carrigan & Meghan Currier | M33: Title initials: T. W. O. W. S. (5 words) | N33: Faster | O33: A Most Violent Year | P33: Edge of Darkness | Q33: Released 2013-12-25; 180 min; worldwide gross about US$392 million (TMDB); tagline: "EARN. SPEND. PARTY." | R33: Martin Scorsese | S33: Bryan Carrigan & Meghan Currier | T33: Leonardo DiCaprio | U33: TMDB 5000 (vote count ≥300); cast from Wikipedia Movie Data | V33: Plot hint is source synopsis text – rewrite before launch; Hints rebuilt Oct 2026 for a 75–90% solve target | W33: 10 | X33: IMDb 1,832,407 votes · 8.2/10 · 75 Wikipedias · lead fame 149
A34: MOV-G-00332 | B34: Global | C34: Hollywood | D34: Easy | E34: Titanic | G34: 1997 | H34: Genre: Drama, Romance · Hollywood · released 1997 | I34: Directed by: James Cameron | J34: Moment: 84 years later, a 101-year-old woman named ____ tells the story to her granddaughter ____ and ____ on the ____ about her life set in… | K34: Co-stars: Kate Winslet, Billy Zane | L34: Lead: Leonardo DiCaprio · music by James Horner | M34: Title: one word, 7 letters, starts with 'T' | N34: The Bone Collector | O34: Child's Play 2 | P34: Flatliners | Q34: Released 1997-11-18; 194 min; worldwide gross about US$1,845 million (TMDB); tagline: "Nothing on Earth could come between them." | R34: James Cameron | S34: James Horner | T34: Leonardo DiCaprio | U34: TMDB 5000 (vote count ≥300); cast from Wikipedia Movie Data | V34: Plot hint is source synopsis text – rewrite before launch; Hints rebuilt Oct 2026 for a 75–90% solve target | W34: 10 | X34: IMDb 1,416,970 votes · 8.0/10 · 137 Wikipedias · lead fame 149
A35: MOV-G-00337 | B35: Global | C35: Hollywood | D35: Easy | E35: Toy Story 3 | G35: 2010 | H35: Genre: Adventure, Animation · Hollywood · released 2010 | I35: Directed by: Lee Unkrich | J35: Moment: Woody, ____, and the rest of ____ haven't been played with in years. | K35: Co-stars: Tim Allen, Joan Cusack | L35: Lead: Tom Hanks · music by Randy Newman | M35: Title initials: T. S. 3. (3 words) | N35: The Smurfs | O35: Hop | P35: The Boxtrolls | Q35: Released 2010-06-16; 103 min; worldwide gross about US$1,067 million (TMDB); tagline: "No toy gets left behind." | R35: Lee Unkrich | S35: Randy Newman | T35: Tom Hanks | U35: TMDB 5000 (vote count ≥300); cast from Wikipedia Movie Data | V35: Plot hint is source synopsis text – rewrite before launch; Hints rebuilt Oct 2026 for a 75–90% solve target | W35: 10 | X35: IMDb 993,860 votes · 8.3/10 · 87 Wikipedias · lead fame 136
A36: MOV-G-00347 | B36: Global | C36: Hollywood | D36: Easy | E36: V for Vendetta | G36: 2006 | H36: Genre: Action, Drama · Hollywood · released 2006 | I36: Directed by: James McTeigue | J36: Moment: In a world in which ____ has become a fascist state, a masked vigilante known only as 'V' conducts guerrilla warfare against the oppressive ____ government. | K36: Co-stars: Hugo Weaving, Stephen Rea | L36: Lead: Natalie Portman · music by Dario Marianelli | M36: Title initials: V. F. V. (3 words) | N36: Around the World in 80 Days | O36: Righteous Kill | P36: Babylon A.D. | Q36: Released 2006-03-15; 132 min; worldwide gross about US$133 million (TMDB); tagline: "People should not be afraid of their governments. Governments should be afraid of their people." | R36: James McTeigue | S36: Dario Marianelli | T36: Natalie Portman | U36: TMDB 5000 (vote count ≥300); cast from Wikipedia Movie Data | V36: Plot hint is source synopsis text – rewrite before launch; Hints rebuilt Oct 2026 for a 75–90% solve target | W36: 10 | X36: IMDb 1,258,699 votes · 8.1/10 · 98 Wikipedias · lead fame 136
A37: MOV-G-00039 | B37: Global | C37: Hollywood | D37: Easy | E37: Black Swan | G37: 2010 | H37: Genre: Drama, Thriller · Hollywood · released 2010 | I37: Directed by: Darren Aronofsky | J37: Moment: A ballet dancer wins the lead in "____" and is perfect for the role of the delicate ____ - ____ - but slowly loses her mind as she becomes more and more like ____, the ____. | K37: Co-stars: Mila Kunis, Vincent Cassel | L37: Lead: Natalie Portman · music by Clint Mansell | M37: Title initials: B. S. (2 words) | N37: Arthur Christmas | O37: The Best Offer | P37: Monsters | Q37: Released 2010-12-02; 108 min; worldwide gross about US$328 million (TMDB); tagline: "In the era of personal branding, the scariest possibility is that someone might be better at being you than you are." | R37: Darren Aronofsky | S37: Clint Mansell | T37: Natalie Portman | U37: TMDB 5000 (vote count ≥300); cast from Wikipedia Movie Data | V37: Plot hint is source synopsis text – rewrite before launch; Hints rebuilt Oct 2026 for a 75–90% solve target | W37: 9.9 | X37: IMDb 899,757 votes · 8.0/10 · 74 Wikipedias · lead fame 136
A38: MOV-G-00151 | B38: Global | C38: Hollywood | D38: Easy | E38: Logan | G38: 2017 | H38: Genre: Action, Drama · Hollywood · released 2017 | I38: Directed by: James Mangold | J38: Moment: An ageing mutant protects a young girl who shares his claws | K38: Co-stars: Patrick Stewart, Boyd Holbrook | L38: Lead: Hugh Jackman · music by Marco Beltrami | M38: Title: one word, 5 letters, starts with 'L' | N38: The Grey | O38: The Interview | P38: Kick-Ass | Q38: Released 2017 | R38: James Mangold | S38: Marco Beltrami | T38: Hugh Jackman | U38: Curated by Claude; director and lead cross-checked against Wikipedia Movie Data where available | V38: Curated (2017–2025 gap in TMDB) – plot line written by Claude; Wikipedia cross-check: director OK, lead OK; Hints rebuilt Oct 2026 for a 75–90% solve target | W38: 9.9 | X38: IMDb 943,958 votes · 8.1/10 · 61 Wikipedias · lead fame 106
A39: MOV-G-00311 | B39: Global | C39: Hollywood | D39: Easy | E39: The Prestige | F39: Prestige | G39: 2006 | H39: Genre: Drama, Mystery · Hollywood · released 2006 | I39: Directed by: Christopher Nolan | J39: Moment: A mysterious story of two magicians whose intense rivalry leads them on a life-long battle for supremacy -- full of obsession, deceit and jealousy with dangerous and deadly consequences. | K39: Co-stars: Christian Bale, Michael Caine | L39: Lead: Hugh Jackman · music by David Julyan | M39: Title initials: T. P. (2 words) | N39: Lost in Translation | O39: Valkyrie | P39: Something's Gotta Give | Q39: Released 2006-10-19; 130 min; worldwide gross about US$110 million (TMDB); tagline: "Are You Watching Closely?" | R39: Christopher Nolan | S39: David Julyan | T39: Hugh Jackman | U39: TMDB 5000 (vote count ≥300); cast from Wikipedia Movie Data | V39: Plot hint is source synopsis text – rewrite before launch; Hints rebuilt Oct 2026 for a 75–90% solve target | W39: 9.9 | X39: IMDb 1,634,089 votes · 8.5/10 · 77 Wikipedias · lead fame 106
A40: MOV-G-00017 | B40: Global | C40: Hollywood | D40: Easy | E40: Alien | G40: 1979 | H40: Genre: Horror, Sci-Fi · Hollywood · released 1979 | I40: Directed by: Ridley Scott | J40: Moment: During its return to the earth, commercial spaceship ____ intercepts a distress signal from a distant planet. | K40: Co-stars: Tom Skerritt, Harry Dean Stanton | L40: Lead: Sigourney Weaver · music by Jerry Goldsmith | M40: Title: one word, 5 letters, starts with 'A' | N40: Jaws | O40: Halloween | P40: The Texas Chain Saw Massacre | Q40: Released 1979-05-25; 117 min; worldwide gross about US$105 million (TMDB); tagline: "In space no one can hear you scream." | R40: Ridley Scott | S40: Jerry Goldsmith | T40: Sigourney Weaver | U40: TMDB 5000 (vote count ≥300); cast from Wikipedia Movie Data | V40: Plot hint is source synopsis text – rewrite before launch; Hints rebuilt Oct 2026 for a 75–90% solve target | W40: 9.8 | X40: IMDb 1,080,095 votes · 8.4/10 · 83 Wikipedias · lead fame 122
A41: MOV-G-00027 | B41: Global | C41: Hollywood | D41: Easy | E41: Avengers: Age of Ultron | F41: Avengers Age of Ultron | G41: 2015 | H41: Genre: Action, Adventure · Hollywood · released 2015 | I41: Directed by: Joss Whedon | J41: Moment: When ____ tries to jumpstart a dormant peacekeeping program, things go awry and Earth’s ____ are put to the ultimate test as the fate of the planet hangs in the balance. | K41: Co-stars: Chris Hemsworth, Mark Ruffalo | L41: Lead: Robert Downey Jr. · music by Danny Elfman & Brian Tyler | M41: Title initials: A. A. O. U. (4 words) | N41: Homefront | O41: This Is the End | P41: Warrior | Q41: Released 2015-04-22; 141 min; worldwide gross about US$1,405 million (TMDB); tagline: "A New Age Has Come." | R41: Joss Whedon | S41: Danny Elfman & Brian Tyler | T41: Robert Downey Jr. | U41: TMDB 5000 (vote count ≥300); cast from Wikipedia Movie Data | V41: Plot hint is source synopsis text – rewrite before launch; Hints rebuilt Oct 2026 for a 75–90% solve target | W41: 9.8 | X41: IMDb 1,026,390 votes · 7.3/10 · 82 Wikipedias · lead fame 112
A42: MOV-G-00034 | B42: Global | C42: Hollywood | D42: Easy | E42: Batman Begins | G42: 2005 | H42: Genre: Crime · Hollywood · released 2005 | I42: Directed by: Christopher Nolan | J42: Moment: Driven by tragedy, billionaire ____ dedicates his life to uncovering and defeating the corruption that plagues his home, ____. | K42: Co-stars: Michael Caine, Liam Neeson | L42: Lead: Christian Bale · music by Hans Zimmer & James Newton Howard | M42: Title initials: B. B. (2 words) | N42: I, Robot | O42: Rush Hour 2 | P42: Epic Movie | Q42: Released 2005-06-10; 140 min; worldwide gross about US$374 million (TMDB); tagline: "Evil fears the knight." | R42: Christopher Nolan | S42: Hans Zimmer & James Newton Howard | T42: Christian Bale | U42: TMDB 5000 (vote count ≥300); cast from Wikipedia Movie Data | V42: Plot hint is source synopsis text – rewrite before launch; Hints rebuilt Oct 2026 for a 75–90% solve target | W42: 9.8 | X42: IMDb 1,749,516 votes · 8.2/10 · 85 Wikipedias · lead fame 99
A43: MOV-G-00064 | B43: Global | C43: Hollywood | D43: Easy | E43: Die Hard | G43: 1988 | H43: Genre: Action, Thriller · Hollywood · released 1988 | I43: Directed by: John McTiernan | J43: Moment: NYPD cop, ____ plan to reconcile with his estranged wife is thrown for a serious loop when minutes after he arrives at her office, the entire building is overtaken by a group of terrorists. | K43: Co-stars: Alan Rickman, Alexander Godunov | L43: Lead: Bruce Willis · music by Michael Kamen | M43: Title initials: D. H. (2 words) | N43: The Golden Child | O43: Tango & Cash | P43: Scarface | Q43: Released 1988-07-15; 131 min; worldwide gross about US$141 million (TMDB); tagline: "40 Stories. Twelve Terrorists. One Cop." | R43: John McTiernan | S43: Michael Kamen | T43: Bruce Willis | U43: TMDB 5000 (vote count ≥300); cast from Wikipedia Movie Data | V43: Plot hint is source synopsis text – rewrite before launch; Hints rebuilt Oct 2026 for a 75–90% solve target | W43: 9.8 | X43: IMDb 1,042,356 votes · 8.2/10 · 78 Wikipedias · lead fame 117
A44: MOV-G-00099 | B44: Global | C44: Hollywood | D44: Easy | E44: Gravity | G44: 2013 | H44: Genre: Drama, Sci-Fi · Hollywood · released 2013 | I44: Directed by: Alfonso Cuar\u00f3n | J44: Moment: Dr. | K44: Co-stars: George Clooney | L44: Lead: Sandra Bullock · music by Steven Price | M44: Title: one word, 7 letters, starts with 'G' | N44: Terminator Genisys | O44: The Adjustment Bureau | P44: Hot Tub Time Machine | Q44: Released 2013-09-27; 91 min; worldwide gross about US$716 million (TMDB); tagline: "Don't Let Go" | R44: Alfonso Cuar\u00f3n | S44: Steven Price | T44: Sandra Bullock | U44: TMDB 5000 (vote count ≥300); cast from Wikipedia Movie Data | V44: Plot hint is source synopsis text – rewrite before launch; Hints rebuilt Oct 2026 for a 75–90% solve target | W44: 9.8 | X44: IMDb 908,061 votes · 7.7/10 · 77 Wikipedias · lead fame 129
A45: MOV-G-00173 | B45: Global | C45: Hollywood | D45: Easy | E45: Monsters, Inc. | F45: Monsters Inc | G45: 2001 | H45: Genre: Adventure, Animation · Hollywood · released 2001 | I45: Directed by: Pete Docter | J45: Moment: James ____ and ____ are ____, they earn their living scaring children and are the best in the business... | K45: Co-stars: Billy Crystal, Mary Gibbs | L45: Lead: John Goodman · music by Randy Newman | M45: Title initials: M. I. (2 words) | N45: Garfield: A Tail of Two Kitties | O45: Up | P45: Finding Nemo | Q45: Released 2001-11-01; 92 min; worldwide gross about US$563 million (TMDB); tagline: "We Scare Because We Care." | R45: Pete Docter | S45: Randy Newman | T45: John Goodman | U45: TMDB 5000 (vote count ≥300); cast from Wikipedia Movie Data | V45: Plot hint is source synopsis text – rewrite before launch; Hints rebuilt Oct 2026 for a 75–90% solve target | W45: 9.8 | X45: IMDb 1,094,887 votes · 8.1/10 · 88 Wikipedias · lead fame 99
A46: MOV-G-00185 | B46: Global | C46: Hollywood | D46: Easy | E46: Once Upon a Time in Hollywood | G46: 2019 | H46: Genre: Comedy, Drama · ____ · released 2019 | I46: Directed by: Quentin Tarantino | J46: Moment: A fading ____ actor and his stunt double in 1969 ____ | K46: Co-stars: Brad Pitt, Margot Robbie | L46: Lead: Leonardo DiCaprio | M46: Title initials: O. U. A. T. I. H. (6 words) | N46: The Descendants | O46: Neighbors | P46: Pitch Perfect | Q46: Released 2019 | R46: Quentin Tarantino | S46: No original score | T46: Leonardo DiCaprio | U46: Curated by Claude; director and lead cross-checked against Wikipedia Movie Data where available | V46: Curated (2017–2025 gap in TMDB) – plot line written by Claude; Wikipedia cross-check: director OK, lead OK; Hints rebuilt Oct 2026 for a 75–90% solve target | W46: 9.8 | X46: IMDb 982,602 votes · 7.6/10 · 69 Wikipedias · lead fame 149
A47: MOV-G-00186 | B47: Global | C47: Hollywood | D47: Easy | E47: One Flew Over the Cuckoo's Nest | F47: One Flew Over the Cuckoos Nest | G47: 1975 | H47: Genre: Drama · Hollywood · released 1975 | I47: Directed by: Milo\u0161 Forman | J47: Moment: While serving time for insanity at a state mental hospital, implacable rabble-rouser, ____ inspires his fellow patients to rebel against the authoritarian rule of head nurse, ____. | K47: Co-stars: Louise Fletcher, Brad Dourif | L47: Lead: Jack Nicholson · music by Jack Nitzsche | M47: Title initials: O. F. O. T. C. N. (6 words) | N47: Eraserhead | O47: The Godfather | P47: The Deer Hunter | Q47: Released 1975-11-18; 133 min; worldwide gross about US$109 million (TMDB); tagline: "If he's crazy, what does that make you?" | R47: Milo\u0161 Forman | S47: Jack Nitzsche | T47: Jack Nicholson | U47: TMDB 5000 (vote count ≥300); cast from Wikipedia Movie Data | V47: Plot hint is source synopsis text – rewrite before launch; Hints rebuilt Oct 2026 for a 75–90% solve target | W47: 9.8 | X47: IMDb 1,170,758 votes · 8.6/10 · 78 Wikipedias · lead fame 129
A48: MOV-G-00194 | B48: Global | C48: Hollywood | D48: Easy | E48: Pirates of the Caribbean: The Curse of the Black Pearl | F48: Pirates of the Caribbean The Curse of the Black Pearl | G48: 2003 | H48: Genre: Action, Adventure · Hollywood · released 2003 | I48: Directed by: Gore Verbinski | J48: Moment: Jack ____, a freewheeling 17th-century pirate who roams the ____, butts heads with a rival pirate bent on pillaging the village of ____. | K48: Co-stars: Johnny Depp, Keira Knightley | L48: Lead: Orlando Bloom · music by Klaus Badelt | M48: Title initials: P. O. T. C. T. C. O. T. B. P. (10 words) | N48: The Matrix Reloaded | O48: Harry Potter and the Goblet of Fire | P48: National Treasure | Q48: Released 2003-07-09; 143 min; worldwide gross about US$655 million (TMDB); tagline: "Prepare to be blown out of the water." | R48: Gore Verbinski | S48: Klaus Badelt | T48: Orlando Bloom | U48: TMDB 5000 (vote count ≥300); cast from Wikipedia Movie Data | V48: Plot hint is source synopsis text – rewrite before launch; Hints rebuilt Oct 2026 for a 75–90% solve target | W48: 9.8 | X48: IMDb 1,349,551 votes · 8.1/10 · 90 Wikipedias · lead fame 96
A49: MOV-G-00201 | B49: Global | C49: Hollywood | D49: Easy | E49: Raiders of the Lost Ark | G49: 1981 | H49: Genre: Adventure · Hollywood · released 1981 | I49: Directed by: Steven Spielberg | J49: Moment: When ____. | K49: Co-stars: Karen Allen, Denholm Elliott | L49: Lead: Harrison Ford · music by John Williams | M49: Title initials: R. O. T. L. A. (5 words) | N49: Conan the Destroyer | O49: Crocodile Dundee II | P49: Bill & Ted's Excellent Adventure | Q49: Released 1981-06-12; 115 min; worldwide gross about US$390 million (TMDB); tagline: "Indiana Jones - the new hero from the creators of JAWS and STAR WARS." | R49: Steven Spielberg | S49: John Williams | T49: Harrison Ford | U49: TMDB 5000 (vote count ≥300); cast from Wikipedia Movie Data | V49: Plot hint is source synopsis text – rewrite before launch; Hints rebuilt Oct 2026 for a 75–90% solve target | W49: 9.8 | X49: IMDb 1,123,488 votes · 8.4/10 · 80 Wikipedias · lead fame 116
A50: MOV-G-00210 | B50: Global | C50: Hollywood | D50: Easy | E50: Scarface | G50: 1983 | H50: Genre: Crime, Drama · Hollywood · released 1983 | I50: Directed by: Brian De Palma | J50: Moment: After getting a green card in exchange for assassinating a ____ government official, ____ stakes a claim on the drug trade in ____. | K50: Co-stars: Michelle Pfeiffer, Steven Bauer | L50: Lead: Al Pacino · music by Giorgio Moroder | M50: Title: one word, 8 letters, starts with 'S' | N50: Beverly Hills Cop II | O50: The Terminator | P50: Die Hard | Q50: Released 1983-12-08; 170 min; worldwide gross about US$66 million (TMDB); tagline: "The world is yours..." | R50: Brian De Palma | S50: Giorgio Moroder | T50: Al Pacino | U50: TMDB 5000 (vote count ≥300); cast from Wikipedia Movie Data | V50: Plot hint is source synopsis text – rewrite before launch; Hints rebuilt Oct 2026 for a 75–90% solve target | W50: 9.8 | X50: IMDb 1,038,534 votes · 8.3/10 · 72 Wikipedias · lead fame 134
A51: MOV-G-00211 | B51: Global | C51: Hollywood | D51: Easy | E51: Schindler's List | F51: Schindlers List | G51: 1993 | H51: Genre: Biography, Drama · Hollywood · released 1993 | I51: Directed by: Steven Spielberg | J51: Moment: The true story of how businessman ____ saved over a thousand ____ lives from the ____ while they worked as slaves in his factory during ____. | K51: Co-stars: Ralph Fiennes, Ben Kingsley | L51: Lead: Liam Neeson · music by John Williams | M51: Title initials: S. L. (2 words) | N51: The Game | O51: Before Sunrise | P51: The Firm | Q51: Released 1993-11-29; 195 min; worldwide gross about US$321 million (TMDB); tagline: "Whoever saves one life, saves the world entire." | R51: Steven Spielberg | S51: John Williams | T51: Liam Neeson | U51: TMDB 5000 (vote count ≥300); cast from Wikipedia Movie Data | V51: Plot hint is source synopsis text – rewrite before launch; Hints rebuilt Oct 2026 for a 75–90% solve target | W51: 9.8 | X51: IMDb 1,608,944 votes · 9.0/10 · 102 Wikipedias · lead fame 98
A52: MOV-G-00219 | B52: Global | C52: Hollywood | D52: Easy | E52: Sin City | G52: 2005 | H52: Genre: Crime, Thriller · Hollywood · released 2005 | I52: Directed by: Robert Rodriguez | J52: Moment: Welcome to ____. | K52: Co-stars: Benicio del Toro, Brittany Murphy | L52: Lead: Jessica Alba · music by Robert Rodriguez & John Debney | M52: Title initials: S. C. (2 words) | N52: Avatar | O52: The Island | P52: Righteous Kill | Q52: Released 2005-04-01; 124 min; worldwide gross about US$159 million (TMDB); tagline: "Walk down the right back alley in Sin City and you can find anything..." | R52: Robert Rodriguez | S52: Robert Rodriguez & John Debney | T52: Jessica Alba | U52: TMDB 5000 (vote count ≥300); cast from Wikipedia Movie Data | V52: Plot hint is source synopsis text – rewrite before launch; Hints rebuilt Oct 2026 for a 75–90% solve target | W52: 9.8 | X52: IMDb 824,955 votes · 8.0/10 · 63 Wikipedias · lead fame 114
A53: MOV-G-00248 | B53: Global | C53: Hollywood | D53: Easy | E53: Taxi Driver (1976) | F53: Taxi Driver | Taxi Driver 1976 | G53: 1976 | H53: Genre: Crime, Drama · Hollywood · released ____ | I53: Directed by: Martin Scorsese | J53: Moment: A mentally unstable ____ veteran works as a night-time ____ in ____ where the perceived decadence and sleaze feeds his urge for violent action, attempting to save a preadolescent prostitute in the… | K53: Co-stars: Jodie Foster, Cybill Shepherd | L53: Lead: Robert De Niro · music by Bernard Herrmann | M53: Title initials: T. D. (2 words) | N53: The Conversation | O53: Escape from Alcatraz | P53: Mad Max | Q53: Released 1976-02-07; 114 min; worldwide gross about US$28 million (TMDB); tagline: "On every street in every city, there's a nobody who dreams of being a somebody." | R53: Martin Scorsese | S53: Bernard Herrmann | T53: Robert De Niro | U53: TMDB 5000 (vote count ≥300); cast from Wikipedia Movie Data | V53: Plot hint is source synopsis text – rewrite before launch; Hints rebuilt Oct 2026 for a 75–90% solve target | W53: 9.8 | X53: IMDb 1,045,554 votes · 8.2/10 · 79 Wikipedias · lead fame 139
A54: MOV-G-00268 | B54: Global | C54: Hollywood | D54: Easy | E54: The Dark Knight | F54: Dark Knight | G54: 2008 | H54: Genre: Crime, Thriller · Hollywood · released 2008 | I54: Directed by: Christopher Nolan | J54: Moment: Batman raises the stakes in his war on crime. | K54: Co-stars: Heath Ledger, Michael Caine | L54: Lead: Christian Bale · music by Hans Zimmer & James Newton Howard | M54: Title initials: T. D. K. (3 words) | N54: The Young Victoria | O54: The Bucket List | P54: The Queen | Q54: Released 2008-07-16; 152 min; worldwide gross about US$1,005 million (TMDB); tagline: "Why So Serious?" | R54: Christopher Nolan | S54: Hans Zimmer & James Newton Howard | T54: Christian Bale | U54: TMDB 5000 (vote count ≥300); cast from Wikipedia Movie Data | V54: Plot hint is source synopsis text – rewrite before launch; Hints rebuilt Oct 2026 for a 75–90% solve target | W54: 9.8 | X54: IMDb 3,239,701 votes · 9.1/10 · 107 Wikipedias · lead fame 99
A55: MOV-G-00269 | B55: Global | C55: Hollywood | D55: Easy | E55: The Dark Knight Rises | F55: Dark Knight Rises | G55: 2012 | H55: Genre: Crime, Thriller · Hollywood · released 2012 | I55: Directed by: Christopher Nolan | J55: Moment: Following the death of ____ assumes responsibility for ____ crimes to protect the late attorney's reputation and is subsequently hunted by the ____. | K55: Co-stars: Michael Caine, Gary Oldman | L55: Lead: Christian Bale · music by Hans Zimmer | M55: Title initials: T. D. K. R. (4 words) | N55: Taken 2 | O55: The Last Airbender | P55: Race (2016) | Q55: Released 2012-07-16; 165 min; worldwide gross about US$1,085 million (TMDB); tagline: "The Legend Ends" | R55: Christopher Nolan | S55: Hans Zimmer | T55: Christian Bale | U55: TMDB 5000 (vote count ≥300); cast from Wikipedia Movie Data | V55: Plot hint is source synopsis text – rewrite before launch; Hints rebuilt Oct 2026 for a 75–90% solve target | W55: 9.8 | X55: IMDb 2,033,283 votes · 8.4/10 · 71 Wikipedias · lead fame 99
A56: MOV-G-00317 | B56: Global | C56: Hollywood | D56: Easy | E56: The Shining | F56: Shining | G56: 1980 | H56: Genre: Drama, Horror · Hollywood · released 1980 | I56: Directed by: Stanley Kubrick | J56: Moment: Jack ____ accepts a caretaker job at the ____, where he, along with his wife ____ and their son ____, must live isolated from the rest of the world for the winter. | K56: Co-stars: Shelley Duvall, Scatman Crothers | L56: Lead: Jack Nicholson · music by Wendy Carlos & Rachel Elkind | M56: Title initials: T. S. (2 words) | N56: A Nightmare on Elm Street Part 2: Freddy's Revenge | O56: Aliens | P56: The Evil Dead | Q56: Released 1980-05-22; 144 min; worldwide gross about US$44 million (TMDB); tagline: "A masterpiece of modern horror." | R56: Stanley Kubrick | S56: Wendy Carlos & Rachel Elkind | T56: Jack Nicholson | U56: TMDB 5000 (vote count ≥300); cast from Wikipedia Movie Data | V56: Plot hint is source synopsis text – rewrite before launch; Hints rebuilt Oct 2026 for a 75–90% solve target | W56: 9.8 | X56: IMDb 1,248,230 votes · 8.4/10 · 75 Wikipedias · lead fame 129
A57: MOV-G-00322 | B57: Global | C57: Hollywood | D57: Easy | E57: The Terminator | F57: Terminator | G57: 1984 | H57: Genre: Action, Adventure · Hollywood · released 1984 | I57: Directed by: James Cameron | J57: Moment: In the post-apocalyptic future, reigning tyrannical supercomputers teleport a cyborg assassin known as the "____" back to 1984 to kill ____, whose unborn son is destined to lead insurgents against 21st… | K57: Co-stars: Linda Hamilton, Michael Biehn | L57: Lead: Arnold Schwarzenegger · music by Brad Fiedel | M57: Title initials: T. T. (2 words) | N57: Superman II | O57: Superman IV: The Quest for Peace | P57: The Golden Child | Q57: Released 1984-10-26; 108 min; worldwide gross about US$78 million (TMDB); tagline: "Your future is in his hands." | R57: James Cameron | S57: Brad Fiedel | T57: Arnold Schwarzenegger | U57: TMDB 5000 (vote count ≥300); cast from Wikipedia Movie Data | V57: Plot hint is source synopsis text – rewrite before launch; Hints rebuilt Oct 2026 for a 75–90% solve target | W57: 9.8 | X57: IMDb 1,021,499 votes · 8.1/10 · 100 Wikipedias · lead fame 153
A58: MOV-G-00018 | B58: Global | C58: Hollywood | D58: Easy | E58: Aliens | G58: 1986 | H58: Genre: Action, Adventure · Hollywood · released 1986 | I58: Directed by: James Cameron | J58: Moment: When ____ lifepod is found by a salvage crew over 50 years later, she finds that terra-formers are on the very planet they found the alien species. | K58: Co-stars: Michael Biehn, Lance Henriksen | L58: Lead: Sigourney Weaver · music by James Horner | M58: Title: one word, 6 letters, starts with 'A' | N58: The Lost Boys | O58: The Dead Zone | P58: Friday the 13th Part 2 | Q58: Released 1986-07-18; 137 min; worldwide gross about US$183 million (TMDB); tagline: "This Time It's War" | R58: James Cameron | S58: James Horner | T58: Sigourney Weaver | U58: TMDB 5000 (vote count ≥300); cast from Wikipedia Movie Data | V58: Plot hint is source synopsis text – rewrite before launch; Hints rebuilt Oct 2026 for a 75–90% solve target | W58: 9.7 | X58: IMDb 850,502 votes · 8.4/10 · 70 Wikipedias · lead fame 122
A59: MOV-G-00019 | B59: Global | C59: Hollywood | D59: Easy | E59: American Beauty | G59: 1999 | H59: Genre: Drama · Hollywood · released 1999 | I59: Directed by: Sam Mendes | J59: Moment: Lester ____, a depressed suburban father in a mid-life crisis, decides to turn his hectic life around after developing an infatuation with his daughter's attractive friend. | K59: Co-stars: Annette Bening, Chris Cooper | L59: Lead: Kevin Spacey · music by Thomas Newman | M59: Title initials: A. B. (2 words) | N59: The Bridges of Madison County | O59: Schindler's List | P59: Fight Club | Q59: Released 1999-09-15; 122 min; worldwide gross about US$356 million (TMDB); tagline: "Look closer." | R59: Sam Mendes | S59: Thomas Newman | T59: Kevin Spacey | U59: TMDB 5000 (vote count ≥300); cast from Wikipedia Movie Data | V59: Plot hint is source synopsis text – rewrite before launch; Hints rebuilt Oct 2026 for a 75–90% solve target | W59: 9.7 | X59: IMDb 1,290,622 votes · 8.3/10 · 79 Wikipedias · lead fame 91
A60: MOV-G-00020 | B60: Global | C60: Hollywood | D60: Easy | E60: American History X | G60: 1998 | H60: Genre: Crime, Drama · Hollywood · released 1998 | I60: Directed by: Tony Kaye | J60: Moment: Derek ____ is paroled after serving 3 years in prison for killing two thugs who tried to break into/steal his truck. | K60: Co-stars: Edward Furlong, Beverly D'Angelo | L60: Lead: Edward Norton · music by Anne Dudley | M60: Title initials: A. H. X. (3 words) | N60: Before Sunrise | O60: Contact | P60: The Bridges of Madison County | Q60: Released 1998-10-30; 119 min; worldwide gross about US$24 million (TMDB); tagline: "Some Legacies Must End." | R60: Tony Kaye | S60: Anne Dudley | T60: Edward Norton | U60: TMDB 5000 (vote count ≥300); cast from Wikipedia Movie Data | V60: Plot hint is source synopsis text – rewrite before launch; Hints rebuilt Oct 2026 for a 75–90% solve target | W60: 9.7 | X60: IMDb 1,290,115 votes · 8.5/10 · 64 Wikipedias · lead fame 90
A61: MOV-G-00040 | B61: Global | C61: Hollywood | D61: Easy | E61: Blade Runner | G61: 1982 | H61: Genre: Action, Drama · Hollywood · released 1982 | I61: Directed by: Ridley Scott | J61: Moment: In the smog-choked dystopian ____ of 2019, ____ is called out of retirement to terminate a quartet of replicants who have escaped to ____ seeking their creator for a way to extend their… | K61: Co-stars: Rutger Hauer, Edward James Olmos | L61: Lead: Harrison Ford · music by Vangelis | M61: Title initials: B. R. (2 words) | N61: Star Trek V: The Final Frontier | O61: Predator | P61: Star Trek IV: The Voyage Home | Q61: Released 1982-06-25; 117 min; worldwide gross about US$33 million (TMDB); tagline: "Man has made his match... now it's his problem." | R61: Ridley Scott | S61: Vangelis | T61: Harrison Ford | U61: TMDB 5000 (vote count ≥300); cast from Wikipedia Movie Data | V61: Plot hint is source synopsis text – rewrite before launch; Hints rebuilt Oct 2026 for a 75–90% solve target | W61: 9.7 | X61: IMDb 894,067 votes · 8.1/10 · 84 Wikipedias · lead fame 116
A62: MOV-G-00046 | B62: Global | C62: Hollywood | D62: Easy | E62: Captain America: Civil War | F62: Captain America Civil War | G62: 2016 | H62: Genre: Action, Sci-Fi · Hollywood · released 2016 | I62: Directed by: Anthony Russo | J62: Moment: Following the events of ____ of ____, the collective governments of the world pass an act designed to regulate all superhuman activity. | K62: Co-stars: Robert Downey Jr., Scarlett Johansson | L62: Lead: Chris Evans · music by Henry Jackman | M62: Title initials: C. A. C. W. (4 words) | N62: The Hobbit: The Desolation of Smaug | O62: Journey 2: The Mysterious Island | P62: Tomorrowland | Q62: Released 2016-04-27; 147 min; worldwide gross about US$1,153 million (TMDB); tagline: "Divided We Fall" | R62: Anthony Russo | S62: Henry Jackman | T62: Chris Evans | U62: TMDB 5000 (vote count ≥300); cast from Wikipedia Movie Data | V62: Plot hint is source synopsis text – rewrite before launch; Hints rebuilt Oct 2026 for a 75–90% solve target | W62: 9.7 | X62: IMDb 953,508 votes · 7.8/10 · 71 Wikipedias · lead fame 99
A63: MOV-G-00048 | B63: Global | C63: Hollywood | D63: Easy | E63: Captain America: The Winter Soldier | F63: Captain America The Winter Soldier | G63: 2014 | H63: Genre: Action, Adventure · Hollywood · released 2014 | I63: Directed by: Anthony Russo | J63: Moment: After the cataclysmic events in ____ with The ____, aka ____ is living quietly in ____, D.C. | K63: Co-stars: Scarlett Johansson, Sebastian Stan | L63: Lead: Chris Evans · music by Henry Jackman | M63: Title initials: C. A. T. W. S. (5 words) | N63: The Mortal Instruments: City of Bones | O63: Now You See Me 2 | P63: X-Men: Days of Future Past | Q63: Released 2014-03-20; 136 min; worldwide gross about US$715 million (TMDB); tagline: "In heroes we trust." | R63: Anthony Russo | S63: Henry Jackman | T63: Chris Evans | U63: TMDB 5000 (vote count ≥300); cast from Wikipedia Movie Data | V63: Plot hint is source synopsis text – rewrite before launch; Hints rebuilt Oct 2026 for a 75–90% solve target | W63: 9.7 | X63: IMDb 993,385 votes · 7.7/10 · 71 Wikipedias · lead fame 99
A64: MOV-G-00050 | B64: Global | C64: Hollywood | D64: Easy | E64: Casino Royale | G64: 2006 | H64: Genre: Action, Adventure · Hollywood · released 2006 | I64: Directed by: Martin Campbell | J64: Moment: Le ____, a banker to the world's terrorists, is scheduled to participate in a high-stakes poker game in ____, where he intends to use his winnings to establish his financial grip on the terrorist market. | K64: Co-stars: Eva Green, Mads Mikkelsen | L64: Lead: Daniel Craig · music by David Arnold | M64: Title initials: C. R. (2 words) | N64: Holes | O64: The Life Aquatic with Steve Zissou | P64: The Polar Express | Q64: Released 2006-11-14; 144 min; worldwide gross about US$599 million (TMDB); tagline: "Everyone has a past. Every legend has a beginning." | R64: Martin Campbell | S64: David Arnold | T64: Daniel Craig | U64: TMDB 5000 (vote count ≥300); cast from Wikipedia Movie Data | V64: Plot hint is source synopsis text – rewrite before launch; Hints rebuilt Oct 2026 for a 75–90% solve target | W64: 9.7 | X64: IMDb 756,484 votes · 8.0/10 · 71 Wikipedias · lead fame 105
A65: MOV-G-00051 | B65: Global | C65: Hollywood | D65: Easy | E65: Cast Away | G65: 2000 | H65: Genre: Adventure, Drama · Hollywood · released 2000 | I65: Directed by: Robert Zemeckis | J65: Moment: Chuck, a top international manager for ____, and ____, a Ph.D. | K65: Co-stars: Helen Hunt | L65: Lead: Tom Hanks · music by Alan Silvestri | M65: Title initials: C. A. (2 words) | N65: Rat Race | O65: Agora | P65: The Lord of the Rings: The Two Towers | Q65: Released 2000-12-22; 143 min; worldwide gross about US$430 million (TMDB); tagline: "At the edge of the world, his journey begins." | R65: Robert Zemeckis | S65: Alan Silvestri | T65: Tom Hanks | U65: TMDB 5000 (vote count ≥300); cast from Wikipedia Movie Data | V65: Plot hint is source synopsis text – rewrite before launch; Hints rebuilt Oct 2026 for a 75–90% solve target | W65: 9.7 | X65: IMDb 698,419 votes · 7.8/10 · 68 Wikipedias · lead fame 136
A66: MOV-G-00060 | B66: Global | C66: Hollywood | D66: Easy | E66: Deadpool | G66: 2016 | H66: Genre: Action, Comedy · Hollywood · released 2016 | I66: Directed by: Tim Miller | J66: Moment: ____ tells the origin story of former ____ operative turned mercenary ____, who after being subjected to a rogue experiment that leaves him with accelerated healing powers, adopts the alter ego… | K66: Co-stars: Morena Baccarin, Ed Skrein | L66: Lead: Ryan Reynolds · music by Junkie XL | M66: Title: one word, 8 letters, starts with 'D' | N66: Unstoppable | O66: Hot Pursuit | P66: Knight and Day | Q66: Released 2016-02-09; 108 min; worldwide gross about US$783 million (TMDB); tagline: "Witness the beginning of a happy ending" | R66: Tim Miller | S66: Junkie XL | T66: Ryan Reynolds | U66: TMDB 5000 (vote count ≥300); cast from Wikipedia Movie Data | V66: Plot hint is source synopsis text – rewrite before launch; Hints rebuilt Oct 2026 for a 75–90% solve target | W66: 9.7 | X66: IMDb 1,275,553 votes · 8.0/10 · 72 Wikipedias · lead fame 91
A67: MOV-G-00070 | B67: Global | C67: Hollywood | D67: Easy | E67: Dune | G67: 2021 | H67: Genre: Action, Adventure · Hollywood · released 2021 | I67: Directed by: Denis Villeneuve | J67: Moment: A noble family takes control of a desert planet that produces "spice" | K67: Co-stars: Timothee Chalamet, Rebecca Ferguson | L67: Lead: Timothée Chalamet · music by Hans Zimmer | M67: Title: one word, 4 letters, starts with 'D' | N67: Avatar: Fire and Ash | O67: Mickey 17 | P67: Dune: Part Two | Q67: Released 2021 | R67: Denis Villeneuve | S67: Hans Zimmer | T67: Timothée Chalamet | U67: Curated by Claude; director and lead cross-checked against Wikipedia Movie Data where available | V67: Curated (2017–2025 gap in TMDB) – plot line written by Claude; Wikipedia cross-check: director OK, lead OK; Hints rebuilt Oct 2026 for a 75–90% solve target | W67: 9.7 | X67: IMDb 1,095,798 votes · 8.0/10 · 70 Wikipedias · lead fame 84
A68: MOV-G-00098 | B68: Global | C68: Hollywood | D68: Easy | E68: Gran Torino | G68: 2008 | H68: Genre: Drama · Hollywood · released 2008 | I68: Directed by: Clint Eastwood | J68: Moment: Walt ____ is a widower who holds onto his prejudices despite the changes in his ____ neighborhood and the world around him. | K68: Co-stars: Christopher Carley, Bee Vang | L68: Lead: Clint Eastwood · music by Kyle Eastwood & Michael Stevens | M68: Title initials: G. T. (2 words) | N68: The Jacket | O68: Erin Brockovich | P68: The Blind Side | Q68: Released 2008-12-09; 116 min; worldwide gross about US$270 million (TMDB); tagline: "Ever come across somebody you shouldn't have messed with?" | R68: Clint Eastwood | S68: Kyle Eastwood & Michael Stevens | T68: Clint Eastwood | U68: TMDB 5000 (vote count ≥300); cast from Wikipedia Movie Data | V68: Plot hint is source synopsis text – rewrite before launch; Hints rebuilt Oct 2026 for a 75–90% solve target | W68: 9.7 | X68: IMDb 872,189 votes · 8.1/10 · 57 Wikipedias · lead fame 135
A69: MOV-G-00104 | B69: Global | C69: Hollywood | D69: Easy | E69: Harry Potter and the Chamber of Secrets | G69: 2002 | H69: Genre: Adventure, Family · Hollywood · released 2002 | I69: Directed by: Chris Columbus | J69: Moment: Ignoring threats to his life, ____ returns to ____ to investigate – aided by ____ and ____ – a mysterious series of attacks. | K69: Co-stars: Rupert Grint, Emma Watson | L69: Lead: Daniel Radcliffe · music by John Williams | M69: Title initials: H. P. A. T. C. O. S. (7 words) | N69: AVP: Alien vs. Predator | O69: Treasure Planet | P69: Eight Below | Q69: Released 2002-11-13; 161 min; worldwide gross about US$877 million (TMDB); tagline: "Hogwarts is back in session." | R69: Chris Columbus | S69: John Williams | T69: Daniel Radcliffe | U69: TMDB 5000 (vote count ≥300); cast from Wikipedia Movie Data | V69: Plot hint is source synopsis text – rewrite before launch; Hints rebuilt Oct 2026 for a 75–90% solve target | W69: 9.7 | X69: IMDb 780,477 votes · 7.5/10 · 94 Wikipedias · lead fame 112
A70: MOV-G-00105 | B70: Global | C70: Hollywood | D70: Easy | E70: Harry Potter and the Goblet of Fire | G70: 2005 | H70: Genre: Adventure, Family · Hollywood · released 2005 | I70: Directed by: Mike Newell | J70: Moment: ____ starts his fourth year at ____, competes in the treacherous ____ and faces the evil ____. | K70: Co-stars: Rupert Grint, Emma Watson | L70: Lead: Daniel Radcliffe · music by Patrick Doyle | M70: Title initials: H. P. A. T. G. O. F. (7 words) | N70: Quantum of Solace | O70: Shrek | P70: Agora | Q70: Released 2005-11-05; 157 min; worldwide gross about US$896 million (TMDB); tagline: "Dark And Difficult Times Lie Ahead." | R70: Mike Newell | S70: Patrick Doyle | T70: Daniel Radcliffe | U70: TMDB 5000 (vote count ≥300); cast from Wikipedia Movie Data | V70: Plot hint is source synopsis text – rewrite before launch; Hints rebuilt Oct 2026 for a 75–90% solve target | W70: 9.7 | X70: IMDb 767,403 votes · 7.7/10 · 90 Wikipedias · lead fame 112
A71: MOV-G-00109 | B71: Global | C71: Hollywood | D71: Easy | E71: Harry Potter and the Prisoner of Azkaban | G71: 2004 | H71: Genre: Adventure, Family · Hollywood · released 2004 | I71: Directed by: Alfonso Cuar\u00f3n | J71: Moment: ____ and ____ return to ____ for another magic-filled year. | K71: Co-stars: Rupert Grint, Emma Watson | L71: Lead: Daniel Radcliffe · music by John Williams | M71: Title initials: H. P. A. T. P. O. A. (7 words) | N71: Transformers | O71: Stardust | P71: The Matrix Revolutions | Q71: Released 2004-05-31; 141 min; worldwide gross about US$790 million (TMDB); tagline: "Something wicked this way comes." | R71: Alfonso Cuar\u00f3n | S71: John Williams | T71: Daniel Radcliffe | U71: TMDB 5000 (vote count ≥300); cast from Wikipedia Movie Data | V71: Plot hint is source synopsis text – rewrite before launch; Hints rebuilt Oct 2026 for a 75–90% solve target | W71: 9.7 | X71: IMDb 781,559 votes · 8.0/10 · 90 Wikipedias · lead fame 112
A72: MOV-G-00114 | B72: Global | C72: Hollywood | D72: Easy | E72: I Am Legend | G72: 2007 | H72: Genre: Drama, Horror · Hollywood · released 2007 | I72: Directed by: Francis Lawrence | J72: Moment: Robert ____ is a scientist who was unable to stop the spread of the terrible virus that was incurable and man-made. | K72: Co-stars: Alice Braga, Dash Mihok | L72: Lead: Will Smith · music by James Newton Howard | M72: Title initials: I. A. L. (3 words) | N72: Hachi: A Dog's Tale | O72: Collateral | P72: The Patriot | Q72: Released 2007-12-14; 101 min; worldwide gross about US$585 million (TMDB); tagline: "The last man on Earth is not alone" | R72: Francis Lawrence | S72: James Newton Howard | T72: Will Smith | U72: TMDB 5000 (vote count ≥300); cast from Wikipedia Movie Data | V72: Plot hint is source synopsis text – rewrite before launch; Hints rebuilt Oct 2026 for a 75–90% solve target | W72: 9.7 | X72: IMDb 890,698 votes · 7.2/10 · 62 Wikipedias · lead fame 135
A73: MOV-G-00122 | B73: Global | C73: Hollywood | D73: Easy | E73: Indiana Jones and the Last Crusade | G73: 1989 | H73: Genre: Adventure · Hollywood · released 1989 | I73: Directed by: Steven Spielberg | J73: Moment: When ____. | K73: Co-stars: Sean Connery, Denholm Elliott | L73: Lead: Harrison Ford · music by John Williams | M73: Title initials: I. J. A. T. L. C. (6 words) | N73: Highlander | O73: Conan the Destroyer | P73: Conan the Barbarian | Q73: Released 1989-05-24; 127 min; worldwide gross about US$474 million (TMDB); tagline: "The man with the hat is back. And this time, he's bringing his Dad." | R73: Steven Spielberg | S73: John Williams | T73: Harrison Ford | U73: TMDB 5000 (vote count ≥300); cast from Wikipedia Movie Data | V73: Plot hint is source synopsis text – rewrite before launch; Hints rebuilt Oct 2026 for a 75–90% solve target | W73: 9.7 | X73: IMDb 873,479 votes · 8.2/10 · 68 Wikipedias · lead fame 116
A74: MOV-G-00128 | B74: Global | C74: Hollywood | D74: Easy | E74: Interstellar | G74: 2014 | H74: Genre: Adventure, Sci-Fi · Hollywood · released 2014 | I74: Directed by: Christopher Nolan | J74: Moment: ____ chronicles the adventures of a group of explorers who make use of a newly discovered wormhole to surpass the limitations on human space travel and conquer the vast distances involved in an ____… | K74: Co-stars: Anne Hathaway, Jessica Chastain | L74: Lead: Matthew McConaughey · music by Hans Zimmer | M74: Title: one word, 12 letters, starts with 'I' | N74: The Secret Life of Walter Mitty | O74: The Croods | P74: Seventh Son | Q74: Released 2014-11-05; 169 min; worldwide gross about US$675 million (TMDB); tagline: "Mankind was born on Earth. It was never meant to die here." | R74: Christopher Nolan | S74: Hans Zimmer | T74: Matthew McConaughey | U74: TMDB 5000 (vote count ≥300); cast from Wikipedia Movie Data | V74: Plot hint is source synopsis text – rewrite before launch; Hints rebuilt Oct 2026 for a 75–90% solve target | W74: 9.7 | X74: IMDb 2,621,294 votes · 8.7/10 · 98 Wikipedias · lead fame 93
A75: MOV-G-00131 | B75: Global | C75: Hollywood | D75: Easy | E75: Iron Man 2 | G75: 2010 | H75: Genre: Action, Sci-Fi · Hollywood · released 2010 | I75: Directed by: Jon Favreau | J75: Moment: With the world now aware of his dual life as the armored superhero ____, billionaire inventor ____ faces pressure from the government, the press and the public to share his technology with the military. | K75: Co-stars: Don Cheadle, Mickey Rourke | L75: Lead: Robert Downey Jr. · music by John Debney | M75: Title initials: I. M. 2. (3 words) | N75: The Chronicles of Narnia: The Voyage of the Dawn Treader | O75: Clash of the Titans | P75: Allegiant | Q75: Released 2010-04-28; 124 min; worldwide gross about US$624 million (TMDB); tagline: "It's not the armor that makes the hero, but the man inside." | R75: Jon Favreau | S75: John Debney | T75: Robert Downey Jr. | U75: TMDB 5000 (vote count ≥300); cast from Wikipedia Movie Data | V75: Plot hint is source synopsis text – rewrite before launch; Hints rebuilt Oct 2026 for a 75–90% solve target | W75: 9.7 | X75: IMDb 961,346 votes · 6.9/10 · 74 Wikipedias · lead fame 112
... A77: MOV-G-00138 | B77: Global | C77: Hollywood | D77: Easy | E77: Joker | G77: 2019 | H77: Genre: Drama · Hollywood · released 2019 | I77: Directed by: Todd Phillips | J77: Moment: A failed stand-up comic in ____ descends into violence | K77: Co-stars: Robert De Niro, Zazie Beetz | L77: Lead: Joaquin Phoenix · music by Hildur Guðnadóttir | M77: Title: one word, 5 letters, starts with 'J' | N77: Jack Reacher | O77: A Most Violent Year | P77: Heist | Q77: Released 2019 | R77: Todd Phillips | S77: Hildur Guðnadóttir | T77: Joaquin Phoenix | U77: Curated by Claude; director and lead cross-checked against Wikipedia Movie Data where available | V77: Curated (2017–2025 gap in TMDB) – plot line written by Claude; Wikipedia cross-check: director OK, lead OK; Hints rebuilt Oct 2026 for a 75–90% solve target | W77: 9.7 | X77: IMDb 1,731,319 votes · 8.3/10 · 77 Wikipedias · lead fame 92
A78: MOV-G-00145 | B78: Global | C78: Hollywood | D78: Easy | E78: Kill Bill: Vol. 1 | F78: Kill Bill Vol 1 | G78: 2003 | H78: Genre: Action, Crime · Hollywood · released 2003 | I78: Directed by: Quentin Tarantino | J78: Moment: An assassin is shot at the altar by her ruthless employer, ____ and other members of their assassination circle – but 'The ____ lives to plot her vengeance. | K78: Co-stars: Lucy Liu | L78: Lead: Uma Thurman · music by RZA | M78: Title initials: K. B. V. 1. (4 words) | N78: V for Vendetta | O78: Gamer | P78: The Core | Q78: Released 2003-10-10; 111 min; worldwide gross about US$181 million (TMDB); tagline: "Go for the kill." | R78: Quentin Tarantino | S78: RZA | T78: Uma Thurman | U78: TMDB 5000 (vote count ≥300); cast from Wikipedia Movie Data | V78: Plot hint is source synopsis text – rewrite before launch; Hints rebuilt Oct 2026 for a 75–90% solve target | W78: 9.7 | X78: IMDb 1,328,870 votes · 8.2/10 · 57 Wikipedias · lead fame 103
A79: MOV-G-00154 | B79: Global | C79: Hollywood | D79: Easy | E79: Mad Max: Fury Road | F79: Mad Max Fury Road | G79: 2015 | H79: Genre: Action, Adventure · Hollywood · released 2015 | I79: Directed by: George Miller | J79: Moment: An apocalyptic story set in the furthest reaches of our planet, in a stark desert landscape where humanity is broken, and most everyone is crazed fighting for the necessities of life. | K79: Co-stars: Charlize Theron, Nicholas Hoult | L79: Lead: Tom Hardy · music by Junkie XL | M79: Title initials: M. M. F. R. (4 words) | N79: White House Down | O79: I Am Number Four | P79: Jurassic World | Q79: Released 2015-05-13; 120 min; worldwide gross about US$379 million (TMDB); tagline: "What a Lovely Day." | R79: George Miller | S79: Junkie XL | T79: Tom Hardy | U79: TMDB 5000 (vote count ≥300); cast from Wikipedia Movie Data | V79: Plot hint is source synopsis text – rewrite before launch; Hints rebuilt Oct 2026 for a 75–90% solve target | W79: 9.7 | X79: IMDb 1,224,235 votes · 8.1/10 · 62 Wikipedias · lead fame 88
A80: MOV-G-00178 | B80: Global | C80: Hollywood | D80: Easy | E80: No Country for Old Men | G80: 2007 | H80: Genre: Crime, Drama · Hollywood · released 2007 | I80: Directed by: Joel Coen | J80: Moment: Llewelyn ____ stumbles upon dead bodies, $2 million and a hoard of heroin in a ____ desert, but methodical killer ____ comes looking for it, with local sheriff ____ hot on his trail. | K80: Co-stars: Javier Bardem, Josh Brolin | L80: Lead: Tommy Lee Jones · music by Carter Burwell | M80: Title initials: N. C. F. O. M. (5 words) | N80: Zodiac | O80: Hannibal Rising | P80: Changeling | Q80: Released 2007-11-08; 122 min; worldwide gross about US$172 million (TMDB); tagline: "There are no clean getaways." | R80: Joel Coen | S80: Carter Burwell | T80: Tommy Lee Jones | U80: TMDB 5000 (vote count ≥300); cast from Wikipedia Movie Data | V80: Plot hint is source synopsis text – rewrite before launch; Hints rebuilt Oct 2026 for a 75–90% solve target | W80: 9.7 | X80: IMDb 1,218,266 votes · 8.2/10 · 79 Wikipedias · lead fame 82
A81: MOV-G-00187 | B81: Global | C81: Hollywood | D81: Easy | E81: Oppenheimer | G81: 2023 | H81: Genre: Biography, Drama · Hollywood · released 2023 | I81: Directed by: Christopher Nolan | J81: Moment: A physicist leads the ____ and watches the ____ test | K81: Co-stars: Emily Blunt, Matt Damon | L81: Lead: Cillian Murphy · music by Ludwig Göransson | M81: Title: one word, 11 letters, starts with 'O' | N81: A Complete Unknown | O81: Elvis | P81: Spider-Man: No Way Home | Q81: Released 2023 | R81: Christopher Nolan | S81: Ludwig Göransson | T81: Cillian Murphy | U81: Curated by Claude; director and lead cross-checked against Wikipedia Movie Data where available | V81: Curated (2017–2025 gap in TMDB) – plot line written by Claude; Wikipedia cross-check: director OK, lead OK; Hints rebuilt Oct 2026 for a 75–90% solve target | W81: 9.7 | X81: IMDb 1,105,580 votes · 8.2/10 · 81 Wikipedias · lead fame 89
A82: MOV-G-00192 | B82: Global | C82: Hollywood | D82: Easy | E82: Pirates of the Caribbean: Dead Man's Chest | F82: Pirates of the Caribbean Dead Mans Chest | G82: 2006 | H82: Genre: Action, Adventure · Hollywood · released 2006 | I82: Directed by: Gore Verbinski | J82: Moment: Captain ____ works his way out of a blood debt with the ghostly ____, he also attempts to avoid eternal damnation. | K82: Co-stars: Orlando Bloom, Keira Knightley | L82: Lead: Johnny Depp · music by Hans Zimmer | M82: Title initials: P. O. T. C. D. M. C. (7 words) | N82: Harry Potter and the Chamber of Secrets | O82: The Twilight Saga: New Moon | P82: Star Wars: Episode II - Attack of the Clones | Q82: Released 2006-06-20; 151 min; worldwide gross about US$1,066 million (TMDB); tagline: "Jack is back!" | R82: Gore Verbinski | S82: Hans Zimmer | T82: Johnny Depp | U82: TMDB 5000 (vote count ≥300); cast from Wikipedia Movie Data | V82: Plot hint is source synopsis text – rewrite before launch; Hints rebuilt Oct 2026 for a 75–90% solve target | W82: 9.7 | X82: IMDb 838,938 votes · 7.4/10 · 84 Wikipedias · lead fame 147
A83: MOV-G-00218 | B83: Global | C83: Hollywood | D83: Easy | E83: Silver Linings Playbook | G83: 2012 | H83: Genre: Drama, Romance · Hollywood · released 2012 | I83: Directed by: David O. Russell | J83: Moment: After spending eight months in a mental institution, a former teacher moves back in with his parents and tries to reconcile with his ex-wife. | K83: Co-stars: Jennifer Lawrence, Brea Bee | L83: Lead: Bradley Cooper · music by Danny Elfman | M83: Title initials: S. L. P. (3 words) | N83: Drive (2011) | O83: Black Swan | P83: 12 Years a Slave | Q83: Released 2012-09-08; 122 min; worldwide gross about US$206 million (TMDB); tagline: "Watch For The Signs" | R83: David O. Russell | S83: Danny Elfman | T83: Bradley Cooper | U83: TMDB 5000 (vote count ≥300); cast from Wikipedia Movie Data | V83: Plot hint is source synopsis text – rewrite before launch; Hints rebuilt Oct 2026 for a 75–90% solve target | W83: 9.7 | X83: IMDb 779,334 votes · 7.7/10 · 59 Wikipedias · lead fame 135
A84: MOV-G-00221 | B84: Global | C84: Hollywood | D84: Easy | E84: Skyfall | G84: 2012 | H84: Genre: Action, Adventure · Hollywood · released 2012 | I84: Directed by: Sam Mendes | J84: Moment: When ____ latest assignment goes gravely wrong and agents around the world are exposed, ____ is attacked forcing ____ to relocate the agency. | K84: Co-stars: Ralph Fiennes, Judi Dench | L84: Lead: Daniel Craig · music by Thomas Newman | M84: Title: one word, 7 letters, starts with 'S' | N84: Abraham Lincoln: Vampire Hunter | O84: Captain Phillips | P84: Inception | Q84: Released 2012-10-25; 143 min; worldwide gross about US$1,109 million (TMDB); tagline: "Think on your sins." | R84: Sam Mendes | S84: Thomas Newman | T84: Daniel Craig | U84: TMDB 5000 (vote count ≥300); cast from Wikipedia Movie Data | V84: Plot hint is source synopsis text – rewrite before launch; Hints rebuilt Oct 2026 for a 75–90% solve target | W84: 9.7 | X84: IMDb 782,065 votes · 7.8/10 · 78 Wikipedias · lead fame 105
A85: MOV-G-00257 | B85: Global | C85: Hollywood | D85: Easy | E85: The Batman | F85: Batman | G85: 2022 | H85: Genre: Action, Crime · Hollywood · released 2022 | I85: Directed by: Matt Reeves | J85: Moment: A young vigilante hunts a killer who leaves riddles | K85: Co-stars: Zoë Kravitz, Paul Dano | L85: Lead: Robert Pattinson · music by Michael Giacchino | M85: Title initials: T. B. (2 words) | N85: Guardians of the Galaxy Vol. 3 | O85: Thunderbolts* | P85: Mission: Impossible – The Final Reckoning | Q85: Released 2022 | R85: Matt Reeves | S85: Michael Giacchino | T85: Robert Pattinson | U85: Curated by Claude; director and lead cross-checked against Wikipedia Movie Data where available | V85: Curated (2017–2025 gap in TMDB) – plot line written by Claude; Wikipedia cross-check: director OK, lead OK; Hints rebuilt Oct 2026 for a 75–90% solve target | W85: 9.7 | X85: IMDb 953,483 votes · 7.8/10 · 64 Wikipedias · lead fame 93
A86: MOV-G-00263 | B86: Global | C86: Hollywood | D86: Easy | E86: The Bourne Ultimatum | F86: Bourne Ultimatum | G86: 2007 | H86: Genre: Action, Mystery · Hollywood · released 2007 | I86: Directed by: Paul Greengrass | J86: Moment: ____ is brought out of hiding once again by reporter ____ who is trying to unveil ____, an upgrade to ____, in a series of newspaper columns. | K86: Co-stars: Julia Stiles, David Strathairn | L86: Lead: Matt Damon · music by John Powell | M86: Title initials: T. B. U. (3 words) | N86: Dragonball Evolution | O86: Elektra | P86: The Scorpion King | Q86: Released 2007-08-03; 115 min; worldwide gross about US$443 million (TMDB); tagline: "Remember everything. Forgive nothing." | R86: Paul Greengrass | S86: John Powell | T86: Matt Damon | U86: TMDB 5000 (vote count ≥300); cast from Wikipedia Movie Data | V86: Plot hint is source synopsis text – rewrite before launch; Hints rebuilt Oct 2026 for a 75–90% solve target | W86: 9.7 | X86: IMDb 689,960 votes · 8.0/10 · 62 Wikipedias · lead fame 114
A87: MOV-G-00266 | B87: Global | C87: Hollywood | D87: Easy | E87: The Curious Case of Benjamin Button | F87: Curious Case of Benjamin Button | G87: 2008 | H87: Genre: Drama, Fantasy · Hollywood · released 2008 | I87: Directed by: David Fincher | J87: Moment: Tells the story of ____, a man who starts aging backwards with bizarre consequences. | K87: Co-stars: Cate Blanchett, Taraji P. Henson | L87: Lead: Brad Pitt · music by Alexandre Desplat | M87: Title initials: T. C. C. O. B. B. (6 words) | N87: Spider-Man | O87: Underworld: Evolution | P87: Spider-Man 3 | Q87: Released 2008-11-24; 166 min; worldwide gross about US$334 million (TMDB); tagline: "Life isn't measured in minutes, but in moments." | R87: David Fincher | S87: Alexandre Desplat | T87: Brad Pitt | U87: TMDB 5000 (vote count ≥300); cast from Wikipedia Movie Data | V87: Plot hint is source synopsis text – rewrite before launch; Hints rebuilt Oct 2026 for a 75–90% solve target | W87: 9.7 | X87: IMDb 756,353 votes · 7.8/10 · 63 Wikipedias · lead fame 147
A88: MOV-G-00279 | B88: Global | C88: Hollywood | D88: Easy | E88: The Godfather | F88: Godfather | G88: 1972 | H88: Genre: Crime, Drama · Hollywood · released 1972 | I88: Directed by: Francis Ford Coppola | J88: Moment: Spanning the years 1945 to 1955, a chronicle of the fictional Italian-American ____ crime family. | K88: Co-stars: Al Pacino, James Caan | L88: Lead: Marlon Brando · music by Nino Rota | M88: Title initials: T. G. (2 words) | N88: Eraserhead | O88: Barry Lyndon | P88: Patton | Q88: Released 1972-03-14; 175 min; worldwide gross about US$245 million (TMDB); tagline: "An offer you can't refuse." | R88: Francis Ford Coppola | S88: Nino Rota | T88: Marlon Brando | U88: TMDB 5000 (vote count ≥300); cast from Wikipedia Movie Data | V88: Plot hint is source synopsis text – rewrite before launch; Hints rebuilt Oct 2026 for a 75–90% solve target | W88: 9.7 | X88: IMDb 2,265,173 votes · 9.2/10 · 132 Wikipedias · lead fame 158
A89: MOV-G-00280 | B89: Global | C89: Hollywood | D89: Easy | E89: The Godfather: Part II | F89: Godfather: Part II | The Godfather Part II | G89: 1974 | H89: Genre: Crime, Drama · Hollywood · released 1974 | I89: Directed by: Francis Ford Coppola | J89: Moment: In the continuing saga of the ____ crime family, a young ____ grows up in ____ and in 1910s ____. | K89: Co-stars: Robert De Niro, Lee Strasberg | L89: Lead: Al Pacino · music by Carmine Coppola & Nino Rota | M89: Title initials: T. G. P. I. (4 words) | N89: Mean Streets | O89: Network | P89: One Flew Over the Cuckoo's Nest | Q89: Released 1974-12-20; 200 min; worldwide gross about US$48 million (TMDB); tagline: "I don't feel I have to wipe everybody out, Tom. Just my enemies." | R89: Francis Ford Coppola | S89: Carmine Coppola & Nino Rota | T89: Al Pacino | U89: TMDB 5000 (vote count ≥300); cast from Wikipedia Movie Data | V89: Plot hint is source synopsis text – rewrite before launch; Hints rebuilt Oct 2026 for a 75–90% solve target | W89: 9.7 | X89: IMDb 1,519,127 votes · 9.0/10 · 86 Wikipedias · lead fame 134
A90: MOV-G-00284 | B90: Global | C90: Hollywood | D90: Easy | E90: The Hangover | F90: Hangover | G90: 2009 | H90: Genre: Comedy · Hollywood · released 2009 | I90: Directed by: Todd Phillips | J90: Moment: When three friends finally come to after a raucous night of bachelor-party revelry, they find a baby in the closet and a tiger in the bathroom. | K90: Co-stars: Ed Helms, Zach Galifianakis | L90: Lead: Bradley Cooper · music by Christophe Beck | M90: Title initials: T. H. (2 words) | N90: High Fidelity | O90: High School Musical 2 | P90: Brüno | Q90: Released 2009-06-05; 100 min; worldwide gross about US$459 million (TMDB); tagline: "Some guys just can't handle Vegas." | R90: Todd Phillips | S90: Christophe Beck | T90: Bradley Cooper | U90: TMDB 5000 (vote count ≥300); cast from Wikipedia Movie Data | V90: Plot hint is source synopsis text – rewrite before launch; Hints rebuilt Oct 2026 for a 75–90% solve target | W90: 9.7 | X90: IMDb 947,653 votes · 7.7/10 · 54 Wikipedias · lead fame 135
A91: MOV-G-00290 | B91: Global | C91: Hollywood | D91: Easy | E91: The Hunger Games | F91: Hunger Games | G91: 2012 | H91: Genre: Action, Adventure · Hollywood · released 2012 | I91: Directed by: Gary Ross | J91: Moment: Every year in the ruins of what was once ____, the nation of ____ forces each of its twelve districts to send a teenage boy and girl to compete in the ____. | K91: Co-stars: Josh Hutcherson, Liam Hemsworth | L91: Lead: Jennifer Lawrence · music by James Newton Howard | M91: Title initials: T. H. G. (3 words) | N91: The Purge | O91: Skyline | P91: Gravity | Q91: Released 2012-03-12; 142 min; worldwide gross about US$691 million (TMDB); tagline: "May The Odds Be Ever In Your Favor." | R91: Gary Ross | S91: James Newton Howard | T91: Jennifer Lawrence | U91: TMDB 5000 (vote count ≥300); cast from Wikipedia Movie Data | V91: Plot hint is source synopsis text – rewrite before launch; Hints rebuilt Oct 2026 for a 75–90% solve target | W91: 9.7 | X91: IMDb 1,098,231 votes · 7.2/10 · 73 Wikipedias · lead fame 120
A92: MOV-G-00301 | B92: Global | C92: Hollywood | D92: Easy | E92: The Lord of the Rings: The Fellowship of the Ring | F92: Lord of the Rings: The Fellowship of the Ring | The Lord of the Rings The Fellowship of the Ring | G92: 2001 | H92: Genre: Adventure, Drama · Hollywood · released 2001 | I92: Directed by: Peter Jackson | J92: Moment: Young hobbit ____, after inheriting a mysterious ____ from his uncle ____, must leave his home in order to keep it from falling into the hands of its evil creator. | K92: Co-stars: Ian McKellen, Liv Tyler | L92: Lead: Elijah Wood · music by Howard Shore | M92: Title initials: T. L. O. T. R. T. F. O. T. R. (10 words) | N92: The Imaginarium of Doctor Parnassus | O92: Into the Wild | P92: Night at the Museum: Battle of the Smithsonian | Q92: Released 2001-12-18; 178 min; worldwide gross about US$871 million (TMDB); tagline: "One ring to rule them all" | R92: Peter Jackson | S92: Howard Shore | T92: Elijah Wood | U92: TMDB 5000 (vote count ≥300); cast from Wikipedia Movie Data | V92: Plot hint is source synopsis text – rewrite before launch; Hints rebuilt Oct 2026 for a 75–90% solve target | W92: 9.7 | X92: IMDb 2,245,134 votes · 8.9/10 · 97 Wikipedias · lead fame 86
A93: MOV-G-00302 | B93: Global | C93: Hollywood | D93: Easy | E93: The Lord of the Rings: The Return of the King | F93: Lord of the Rings: The Return of the King | The Lord of the Rings The Return of the King | G93: 2003 | H93: Genre: Adventure, Drama · Hollywood · released 2003 | I93: Directed by: Peter Jackson | J93: Moment: Aragorn is revealed as the heir to the ancient ____ as he, ____ and the other members of the broken fellowship struggle to save ____ from ____ forces. | K93: Co-stars: Ian McKellen, Liv Tyler | L93: Lead: Elijah Wood · music by Howard Shore | M93: Title initials: T. L. O. T. R. T. R. O. T. K. (10 words) | N93: Kung Fu Panda | O93: Harry Potter and the Half-Blood Prince | P93: Shanghai Noon | Q93: Released 2003-12-01; 201 min; worldwide gross about US$1,119 million (TMDB); tagline: "The eye of the enemy is moving." | R93: Peter Jackson | S93: Howard Shore | T93: Elijah Wood | U93: TMDB 5000 (vote count ≥300); cast from Wikipedia Movie Data | V93: Plot hint is source synopsis text – rewrite before launch; Hints rebuilt Oct 2026 for a 75–90% solve target | W93: 9.7 | X93: IMDb 2,201,132 votes · 9.0/10 · 93 Wikipedias · lead fame 86
A94: MOV-G-00303 | B94: Global | C94: Hollywood | D94: Easy | E94: The Lord of the Rings: The Two Towers | F94: Lord of the Rings: The Two Towers | The Lord of the Rings The Two Towers | G94: 2002 | H94: Genre: Adventure, Drama · Hollywood · released 2002 | I94: Directed by: Peter Jackson | J94: Moment: Frodo and ____ are trekking to ____ to destroy the One ____ of ____ while ____ and ____ search for the orc-captured ____ and ____. | K94: Co-stars: Ian McKellen, Liv Tyler | L94: Lead: Elijah Wood · music by Howard Shore & Elizabeth Fraser | M94: Title initials: T. L. O. T. R. T. T. T. (8 words) | N94: Indiana Jones and the Kingdom of the Crystal Skull | O94: Troy | P94: Cast Away | Q94: Released 2002-12-18; 179 min; worldwide gross about US$926 million (TMDB); tagline: "A New Power Is Rising." | R94: Peter Jackson | S94: Howard Shore & Elizabeth Fraser | T94: Elijah Wood | U94: TMDB 5000 (vote count ≥300); cast from Wikipedia Movie Data | V94: Plot hint is source synopsis text – rewrite before launch; Hints rebuilt Oct 2026 for a 75–90% solve target | W94: 9.7 | X94: IMDb 1,990,904 votes · 8.8/10 · 88 Wikipedias · lead fame 86
A95: MOV-G-00330 | B95: Global | C95: Hollywood | D95: Easy | E95: Thor: Ragnarok | F95: Thor Ragnarok | G95: 2017 | H95: Genre: Action, Adventure · Hollywood · released 2017 | I95: Directed by: Taika Waititi | J95: Moment: A god loses his hammer and fights his friend in a gladiator arena | K95: Co-stars: Tom Hiddleston, Cate Blanchett | L95: Lead: Chris Hemsworth · music by Mark Mothersbaugh | M95: Title initials: T. R. (2 words) | N95: No Escape | O95: Black Panther | P95: Sucker Punch | Q95: Released 2017 | R95: Taika Waititi | S95: Mark Mothersbaugh | T95: Chris Hemsworth | U95: Curated by Claude; director and lead cross-checked against Wikipedia Movie Data where available | V95: Curated (2017–2025 gap in TMDB) – plot line written by Claude; Wikipedia cross-check: director OK, lead OK; Hints rebuilt Oct 2026 for a 75–90% solve target | W95: 9.7 | X95: IMDb 916,988 votes · 7.9/10 · 71 Wikipedias · lead fame 93
A96: MOV-G-00361 | B96: Global | C96: Hollywood | D96: Easy | E96: X-Men: Days of Future Past | F96: XMen Days of Future Past | G96: 2014 | H96: Genre: Action, Adventure · Hollywood · released 2014 | I96: Directed by: Bryan Singer | J96: Moment: The ultimate X-____ ensemble fights a war for the survival of the species across two time periods as they join forces with their younger selves in an epic battle that must change the ____ – to save our ____. | K96: Co-stars: James McAvoy, Michael Fassbender | L96: Lead: Hugh Jackman · music by John Ottman | M96: Title initials: X. D. O. F. P. (5 words) | N96: Paul Blart: Mall Cop 2 | O96: This Is the End | P96: The Other Guys | Q96: Released 2014-05-15; 131 min; worldwide gross about US$748 million (TMDB); tagline: "To save the future, they must alter the past" | R96: Bryan Singer | S96: John Ottman | T96: Hugh Jackman | U96: TMDB 5000 (vote count ≥300); cast from Wikipedia Movie Data | V96: Plot hint is source synopsis text – rewrite before launch; Hints rebuilt Oct 2026 for a 75–90% solve target | W96: 9.7 | X96: IMDb 799,916 votes · 7.9/10 · 60 Wikipedias · lead fame 106
A97: MOV-G-00710 | B97: Global | C97: Hollywood | D97: Easy | E97: Million Dollar Baby | G97: 2004 | H97: Genre: Drama, Sport · Hollywood · released 2004 | I97: Directed by: Clint Eastwood | J97: Moment: Despondent over a painful estrangement from his daughter, trainer ____ isn't prepared for boxer ____ to enter his life. | K97: Co-stars: Hilary Swank, Morgan Freeman | L97: Lead: Clint Eastwood · music by Clint Eastwood | M97: Title initials: M. D. B. (3 words) | N97: Ali | O97: 21 | P97: A.I. Artificial Intelligence | Q97: Released 2004-12-15; 132 min; worldwide gross about US$217 million (TMDB); tagline: "Beyond his silence, there is a past. Beyond her dreams, there is a feeling. Beyond hope, there is a memory. Beyond their journey, there is a love." | R97: Clint Eastwood | S97: Clint Eastwood | T97: Clint Eastwood | U97: TMDB 5000 (vote count ≥300); cast from Wikipedia Movie Data | V97: Plot hint is source synopsis text – rewrite before launch; Hints rebuilt Oct 2026 for a 75–90% solve target | W97: 9.7 | X97: IMDb 775,408 votes · 8.1/10 · 71 Wikipedias · lead fame 135
A98: MOV-G-00024 | B98: Global | C98: Hollywood | D98: Easy | E98: Argo | G98: 2012 | H98: Genre: Biography, Drama · Hollywood · released 2012 | I98: Directed by: Ben Affleck | J98: Moment: As the ____ revolution reaches a boiling point, a ____ 'exfiltration' specialist concocts a risky plan to free six ____ who have found shelter at the home of the ____ ambassador. | K98: Co-stars: John Goodman, Alan Arkin | L98: Lead: Ben Affleck · music by Alexandre Desplat | M98: Title: one word, 4 letters, starts with 'A' | N98: Arthur Christmas | O98: Buried | P98: The Theory of Everything | Q98: Released 2012-10-11; 120 min; worldwide gross about US$232 million (TMDB); tagline: "The movie was fake. The mission was real." | R98: Ben Affleck | S98: Alexandre Desplat | T98: Ben Affleck | U98: TMDB 5000 (vote count ≥300); cast from Wikipedia Movie Data | V98: Plot hint is source synopsis text – rewrite before launch; Hints rebuilt Oct 2026 for a 75–90% solve target | W98: 9.6 | X98: IMDb 674,521 votes · 7.7/10 · 65 Wikipedias · lead fame 112
A99: MOV-G-00047 | B99: Global | C99: Hollywood | D99: Easy | E99: Captain America: The First Avenger | F99: Captain America The First Avenger | G99: 2011 | H99: Genre: Action, Adventure · Hollywood · released 2011 | I99: Directed by: Joe Johnston | J99: Moment: Predominantly set during ____ is a sickly man from ____ who's transformed into super-soldier ____ to aid in the war effort. | K99: Co-stars: Tommy Lee Jones, Hugo Weaving | L99: Lead: Chris Evans · music by Alan Silvestri | M99: Title initials: C. A. T. F. A. (5 words) | N99: The Hobbit: The Battle of the Five Armies | O99: Men in Black 3 | P99: Furious 7 | Q99: Released 2011-07-22; 124 min; worldwide gross about US$371 million (TMDB); tagline: "When patriots become heroes" | R99: Joe Johnston | S99: Alan Silvestri | T99: Chris Evans | U99: TMDB 5000 (vote count ≥300); cast from Wikipedia Movie Data | V99: Plot hint is source synopsis text – rewrite before launch; Hints rebuilt Oct 2026 for a 75–90% solve target | W99: 9.6 | X99: IMDb 991,259 votes · 6.9/10 · 79 Wikipedias · lead fame 99
A100: MOV-G-00067 | B100: Global | C100: Hollywood | D100: Easy | E100: Django Unchained | G100: 2012 | H100: Genre: Drama, Western · Hollywood · released 2012 | I100: Directed by: Quentin Tarantino | J100: Moment: With the help of a ____ bounty hunter, a freed slave sets out to rescue his wife from a brutal ____ plantation owner. | K100: Co-stars: Jamie Foxx, Leonardo DiCaprio | L100: Lead: Christoph Waltz · music by Luis Bacalov | M100: Title initials: D. U. (2 words) | N100: The Artist | O100: We Are Your Friends | P100: The Best Exotic Marigold Hotel | Q100: Released 2012-12-25; 165 min; worldwide gross about US$425 million (TMDB); tagline: "Life, liberty and the pursuit of vengeance." | R100: Quentin Tarantino | S100: Luis Bacalov | T100: Christoph Waltz | U100: TMDB 5000 (vote count ≥300); cast from Wikipedia Movie Data | V100: Plot hint is source synopsis text – rewrite before launch; Hints rebuilt Oct 2026 for a 75–90% solve target | W100: 9.6 | X100: IMDb 1,920,577 votes · 8.5/10 · 74 Wikipedias · lead fame 80
A101: MOV-G-00068 | B101: Global | C101: Hollywood | D101: Easy | E101: Donnie Darko | G101: 2001 | H101: Genre: Drama, Mystery · Hollywood · released 2001 | I101: Directed by: Richard Kelly | J101: Moment: After narrowly escaping a bizarre accident, a troubled teenager is plagued by visions of a large bunny rabbit that manipulates him to commit a series of crimes. | K101: Co-stars: Jena Malone, Drew Barrymore | L101: Lead: Jake Gyllenhaal · music by Michael Andrews | M101: Title initials: D. D. (2 words) | N101: Underworld: Rise of the Lycans | O101: The Ant Bully | P101: Hancock | Q101: Released 2001-01-18; 113 min; worldwide gross about US$1 million (TMDB); tagline: "You can never go too far" | R101: Richard Kelly | S101: Michael Andrews | T101: Jake Gyllenhaal | U101: TMDB 5000 (vote count ≥300); cast from Wikipedia Movie Data | V101: Plot hint is source synopsis text – rewrite before launch; Hints rebuilt Oct 2026 for a 75–90% solve target | W101: 9.6 | X101: IMDb 922,926 votes · 8.0/10 · 64 Wikipedias · lead fame 84
...

Sheet Music
A1: ID | B1: Edition | C1: Answer type | D1: Difficulty | E1: Answer | F1: Accepted aliases | G1: Artist | H1: Year | I1: Hint 1 (shown at start) | J1: Hint 2 (after miss 1) | K1: Hint 3 (after miss 2) | L1: Hint 4 (after miss 3) | M1: Hint 5 (after miss 4) | N1: Hint 6 (after miss 5, with options) | O1: Wrong option A | P1: Wrong option B | Q1: Wrong option C | R1: Reveal-card fact | S1: Source | T1: Verify flag | U1: Fame score (0-10) | V1: Score signals
A2: MUS-G-00034 | B2: Global | C2: Song | D2: Easy | E2: All I Want For Christmas Is You | G2: Mariah Carey | H2: 2000 | I2: Vibe: Dance Pop · 2000 | J2: Chart: peaked at #1 on the Billboard Hot 100, 79 weeks on the chart | K2: Album: Merry ____ | L2: Same artist also charted with: 'We Belong Together' | M2: Artist: Mariah Carey | N2: Title initials: A. I. W. F. C. I. Y. (7 words) | O2: Baby Boy | P2: Sweet Dreams — Beyonce | Q2: Waking Up In Vegas | R2: All I Want For Christmas Is You by Mariah Carey; peak #1 on the Billboard Hot 100 (2000) | S2: Billboard Hot 100 weekly charts 1958–Oct 2026 (utdata/rwd-billboard-data); genre/album from Spotify via TidyTuesday 2021-09-14 | T2: Hints rebuilt Oct 2026 for a 75–90% solve target | U2: 10 | V2: peak #1 · 79 weeks · artist fame 126
A3: MUS-G-00054 | B3: Global | C3: Song | D3: Easy | E3: Anti-Hero | F3: AntiHero | G3: Taylor Swift | H3: 2022 | I3: Vibe: Chart hit · 2022 | J3: Chart: peaked at #1 on the Billboard Hot 100, 53 weeks on the chart | K3: Same artist also charted with: 'Cruel Summer' | L3: Chart year: entered the Hot 100 in 2022 | M3: Artist: Taylor Swift | N3: Title: one word, 9 letters, starts with 'A' | O3: Monster | P3: Something In The Orange | Q3: How It's Done | R3: Anti-Hero by Taylor Swift; peak #1 on the Billboard Hot 100 (2022) | S3: Billboard Hot 100 weekly charts 1958–Oct 2026 (utdata/rwd-billboard-data); genre/album from Spotify via TidyTuesday 2021-09-14 | T3: Hints rebuilt Oct 2026 for a 75–90% solve target | U3: 10 | V3: peak #1 · 53 weeks · artist fame 178
A4: MUS-G-00057 | B4: Global | C4: Artist/Band | D4: Easy | E4: Ariana Grande | G4: Ariana Grande | H4: 2014 | I4: Era: in the Hot 100 top 10 between 2015 and 2026 · Dance Pop | J4: Chart record: 14 top-10 hits, 6 #1 hit(s) on the Billboard Hot 100 | K4: First top-10 hit: 'Santa Tell Me' (2014) | L4: Number of words in name: 2 | M4: Biggest hit: 'Save Your Tears' | N4: Name: 2 words — 6 + 6 letters, initials A.G. | O4: Demi Lovato | P4: Harry Styles | Q4: Dua Lipa | R4: Ariana Grande: 14 Hot 100 top-10 hits (2014–2026) | S4: Billboard Hot 100 1958–Oct 2026; Rolling Stone 500 Albums via TidyTuesday 2024-05-07 | T4: Counts are solo-credited entries only (features excluded); Hints rebuilt Oct 2026 for a 75–90% solve target | U4: 10 | V4: fame 141 · 14 top-10s
A5: MUS-G-00070 | B5: Global | C5: Song | D5: Easy | E5: Bad Guy | G5: Billie Eilish | H5: 2019 | I5: Vibe: Electropop · 2019 | J5: Chart: peaked at #1 on the Billboard Hot 100, 49 weeks on the chart | K5: Album: WHEN WE ALL FALL ASLEE | L5: Same artist also charted with: 'Birds Of A Feather' | M5: Artist: Billie Eilish | N5: Title initials: B. G. (2 words) | O5: Roses — The Chainsmokers Featuring Rozes | P5: Don't Let Me Down | Q5: Paris | R5: Bad Guy by Billie Eilish; peak #1 on the Billboard Hot 100 (2019) | S5: Billboard Hot 100 weekly charts 1958–Oct 2026 (utdata/rwd-billboard-data); genre/album from Spotify via TidyTuesday 2021-09-14 | T5: Hints rebuilt Oct 2026 for a 75–90% solve target | U5: 10 | V5: peak #1 · 49 weeks · artist fame 125
A6: MUS-G-00097 | B6: Global | C6: Artist/Band | D6: Easy | E6: Beyonce | G6: Beyonce | H6: 2003 | I6: Era: in the Hot 100 top 10 between 2004 and 2024 · Dance Pop | J6: Chart record: 12 top-10 hits, 4 #1 hit(s) on the Billboard Hot 100 | K6: First top-10 hit: 'Me, Myself And I' (2003) | L6: Rolling Stone 500 (2020) album: 'Lemonade' (2016), ranked #32 | M6: Biggest hit: 'Irreplaceable' | N6: Name: one word, 7 letters, starts with 'B' | O6: Fergie | P6: Ne-Yo | Q6: Katy Perry | R6: Beyonce: 12 Hot 100 top-10 hits (2003–2024) | S6: Billboard Hot 100 1958–Oct 2026; Rolling Stone 500 Albums via TidyTuesday 2024-05-07 | T6: Counts are solo-credited entries only (features excluded); Hints rebuilt Oct 2026 for a 75–90% solve target | U6: 10 | V6: fame 175 · 12 top-10s
A7: MUS-G-00129 | B7: Global | C7: Artist/Band | D7: Easy | E7: Britney Spears | G7: Britney Spears | H7: 1998 | I7: Era: in the Hot 100 top 10 between 1998 and 2011 · Dance Pop | J7: Chart record: 10 top-10 hits, 4 #1 hit(s) on the Billboard Hot 100 | K7: First top-10 hit: '...Baby One More Time' (1998) | L7: Rolling Stone 500 (2020) album: 'Blackout' (2007), ranked #441 | M7: Biggest hit: '...Baby One More Time' | N7: Name: 2 words — 7 + 6 letters, initials B.S. | O7: Christina Aguilera | P7: En Vogue | Q7: Jennifer Lopez | R7: Britney Spears: 10 Hot 100 top-10 hits (1998–2011) | S7: Billboard Hot 100 1958–Oct 2026; Rolling Stone 500 Albums via TidyTuesday 2024-05-07 | T7: Counts are solo-credited entries only (features excluded); Hints rebuilt Oct 2026 for a 75–90% solve target | U7: 10 | V7: fame 146 · 10 top-10s
A8: MUS-G-00144 | B8: Global | C8: Song | D8: Easy | E8: Can't Stop The Feeling! | F8: Cant Stop The Feeling | G8: Justin Timberlake | H8: 2016 | I8: Vibe: Dance Pop · 2016 | J8: Chart: peaked at #1 on the Billboard Hot 100, 52 weeks on the chart | K8: Album: TROLLS (Original Motion Picture Soundtrack) | L8: Same artist also charted with: 'SexyBack' | M8: Artist: Justin Timberlake | N8: Title initials: C. S. T. F. (4 words) | O8: Mr. Know It All | P8: Firework | Q8: Habits (Stay High) | R8: Can't Stop The Feeling! by Justin Timberlake; peak #1 on the Billboard Hot 100 (2016) | S8: Billboard Hot 100 weekly charts 1958–Oct 2026 (utdata/rwd-billboard-data); genre/album from Spotify via TidyTuesday 2021-09-14 | T8: Hints rebuilt Oct 2026 for a 75–90% solve target | U8: 10 | V8: peak #1 · 52 weeks · artist fame 111
A9: MUS-G-00145 | B9: Global | C9: Song | D9: Easy | E9: Candle In The Wind 1997/Something About The Way You Look Tonight | F9: Candle In The Wind 1997Something About The Way You Look Tonight | G9: Elton John | H9: 1997 | I9: Vibe: Glam Rock · ____ | J9: Chart: peaked at #1 on the Billboard Hot 100, 42 weeks on the chart | K9: Same artist also charted with: 'Bennie And The Jets' | L9: Chart year: entered the Hot 100 in ____ | M9: Artist: Elton John | N9: Title initials: C. I. T. W. 1. S. A. T. W. Y. L. T. (12 words) | O9: The One | P9: Can You Feel The Love Tonight (From "The Lion King") | Q9: I Believe In You And Me (From "The Preacher's Wife") | R9: Candle In The Wind 1997/Something About The Way You Look Tonight by Elton John; peak #1 on the Billboard Hot 100 (1997) | S9: Billboard Hot 100 weekly charts 1958–Oct 2026 (utdata/rwd-billboard-data); genre/album from Spotify via TidyTuesday 2021-09-14 | T9: Hints rebuilt Oct 2026 for a 75–90% solve target | U9: 10 | V9: peak #1 · 42 weeks · artist fame 117
A10: MUS-G-00178 | B10: Global | C10: Song | D10: Easy | E10: Cruel Summer — Taylor Swift | F10: Cruel Summer Taylor Swift | G10: Taylor Swift | H10: 2019 | I10: Vibe: Dance Pop · 2019 | J10: Chart: peaked at #1 on the Billboard Hot 100, 54 weeks on the chart | K10: Album: Lover | L10: Same artist also charted with: 'Anti-Hero' | M10: Artist: ____ ____ | N10: Title initials: C. S. T. S. (4 words) | O10: Wild Thoughts | P10: Without Me — Halsey | Q10: Cooler Than Me | R10: Cruel Summer by Taylor Swift; peak #1 on the Billboard Hot 100 (2019) | S10: Billboard Hot 100 weekly charts 1958–Oct 2026 (utdata/rwd-billboard-data); genre/album from Spotify via TidyTuesday 2021-09-14 | T10: Hints rebuilt Oct 2026 for a 75–90% solve target | U10: 10 | V10: peak #1 · 54 weeks · artist fame 178
A11: MUS-G-00199 | B11: Global | C11: Song | D11: Easy | E11: Die For You — The Weeknd & Ariana Grande | F11: Die For You The Weeknd Ariana Grande | G11: The Weeknd & Ariana Grande | H11: 2023 | I11: Vibe: Chart hit · 2023 | J11: Chart: peaked at #1 on the Billboard Hot 100, 52 weeks on the chart | K11: Same artist also charted with: 'Save Your Tears' | L11: Chart year: entered the Hot 100 in 2023 | M11: Artist: The ____ & ____ ____ | N11: Title initials: D. F. Y. T. W. A. G. (7 words) | O11: II Most Wanted | P11: pride.is.the.devil | Q11: Hey Now | R11: Die For You by The Weeknd & Ariana Grande; peak #1 on the Billboard Hot 100 (2023) | S11: Billboard Hot 100 weekly charts 1958–Oct 2026 (utdata/rwd-billboard-data); genre/album from Spotify via TidyTuesday 2021-09-14 | T11: Hints rebuilt Oct 2026 for a 75–90% solve target | U11: 10 | V11: peak #1 · 52 weeks · artist fame 141
A12: MUS-G-00200 | B12: Global | C12: Song | D12: Easy | E12: Die With A Smile | G12: Lady Gaga & Bruno Mars | H12: 2024 | I12: Vibe: Chart hit · 2024 | J12: Chart: peaked at #1 on the Billboard Hot 100, 60 weeks on the chart | K12: Chart year: entered the Hot 100 in 2024 | L12: Artist initials: L.G.&.B.M. | M12: Artist: Lady Gaga & Bruno Mars | N12: Title initials: D. W. A. S. (4 words) | O12: Wants And Needs | P12: Super Freaky Girl | Q12: Stay — The Kid LAROI & Justin Bieber | R12: Die With A Smile by Lady Gaga & Bruno Mars; peak #1 on the Billboard Hot 100 (2024) | S12: Billboard Hot 100 weekly charts 1958–Oct 2026 (utdata/rwd-billboard-data); genre/album from Spotify via TidyTuesday 2021-09-14 | T12: Hints rebuilt Oct 2026 for a 75–90% solve target | U12: 10 | V12: peak #1 · 60 weeks · artist fame 197
A13: MUS-G-00244 | B13: Global | C13: Artist/Band | D13: Easy | E13: Eminem | G13: Eminem | H13: 2000 | I13: Era: in the Hot 100 top 10 between 2000 and 2024 · Detroit Hip Hop | J13: Chart record: 13 top-10 hits, 2 #1 hit(s) on the Billboard Hot 100 | K13: First top-10 hit: 'The Real Slim Shady' (2000) | L13: Rolling Stone 500 (2020) album: 'The Marshall Mathers LP' (2000), ranked #145 | M13: Biggest hit: 'Love The Way You Lie' | N13: Name: one word, 6 letters, starts with 'E' | O13: Fergie | P13: Miley Cyrus | Q13: Flo Rida | R13: Eminem: 13 Hot 100 top-10 hits (2000–2024) | S13: Billboard Hot 100 1958–Oct 2026; Rolling Stone 500 Albums via TidyTuesday 2024-05-07 | T13: Counts are solo-credited entries only (features excluded); Hints rebuilt Oct 2026 for a 75–90% solve target | U13: 10 | V13: fame 175 · 13 top-10s
A14: MUS-G-00273 | B14: Global | C14: Song | D14: Easy | E14: Flowers | G14: Miley Cyrus | H14: 2023 | I14: Vibe: Chart hit · 2023 | J14: Chart: peaked at #1 on the Billboard Hot 100, 55 weeks on the chart | K14: Same artist also charted with: 'Wrecking Ball' | L14: Chart year: entered the Hot 100 in 2023 | M14: Artist: Miley Cyrus | N14: Title: one word, 7 letters, starts with 'F' | O14: Save Your Tears — The Weeknd & Ariana Grande | P14: The Kind Of Love We Make | Q14: Super Gremlin | R14: Flowers by Miley Cyrus; peak #1 on the Billboard Hot 100 (2023) | S14: Billboard Hot 100 weekly charts 1958–Oct 2026 (utdata/rwd-billboard-data); genre/album from Spotify via TidyTuesday 2021-09-14 | T14: Hints rebuilt Oct 2026 for a 75–90% solve target | U14: 10 | V14: peak #1 · 55 weeks · artist fame 141
A15: MUS-G-00446 | B15: Global | C15: Artist/Band | D15: Easy | E15: Katy Perry | G15: Katy Perry | H15: 2008 | I15: Era: in the Hot 100 top 10 between 2008 and 2014 · Dance Pop | J15: Chart record: 10 top-10 hits, 6 #1 hit(s) on the Billboard Hot 100 | K15: First top-10 hit: 'I Kissed A Girl' (2008) | L15: Number of words in name: 2 | M15: Biggest hit: 'Dark Horse' | N15: Name: 2 words — 4 + 5 letters, initials K.P. | O15: OneRepublic | P15: Lady Gaga | Q15: Flo Rida | R15: Katy Perry: 10 Hot 100 top-10 hits (2008–2013) | S15: Billboard Hot 100 1958–Oct 2026; Rolling Stone 500 Albums via TidyTuesday 2024-05-07 | T15: Counts are solo-credited entries only (features excluded); Hints rebuilt Oct 2026 for a 75–90% solve target | U15: 10 | V15: fame 136 · 10 top-10s
A16: MUS-G-00460 | B16: Global | C16: Artist/Band | D16: Easy | E16: Lady Gaga | G16: Lady Gaga | H16: 2009 | I16: Era: in the Hot 100 top 10 between 2009 and 2020 · Dance Pop | J16: Chart record: 13 top-10 hits, 2 #1 hit(s) on the Billboard Hot 100 | K16: First top-10 hit: 'Poker Face' (2009) | L16: Rolling Stone 500 (2020) album: 'Born This Way' (2011), ranked #484 | M16: Biggest hit: 'Die With A Smile' | N16: Name: 2 words — 4 + 4 letters, initials L.G. | O16: Beyonce | P16: Akon | Q16: Fergie | R16: Lady Gaga: 13 Hot 100 top-10 hits (2009–2020) | S16: Billboard Hot 100 1958–Oct 2026; Rolling Stone 500 Albums via TidyTuesday 2024-05-07 | T16: Counts are solo-credited entries only (features excluded); Hints rebuilt Oct 2026 for a 75–90% solve target | U16: 10 | V16: fame 197 · 13 top-10s
A17: MUS-G-00507 | B17: Global | C17: Song | D17: Easy | E17: Love Yourself | G17: Justin Bieber | H17: 2015 | I17: Vibe: Canadian Pop · 2015 | J17: Chart: peaked at #1 on the Billboard Hot 100, 41 weeks on the chart | K17: Album: Purpose (Deluxe) | L17: Same artist also charted with: 'Sorry' | M17: Artist: Justin Bieber | N17: Title initials: L. Y. (2 words) | O17: Call Me Maybe | P17: Senorita | Q17: If I Can't Have You — Shawn Mendes | R17: Love Yourself by Justin Bieber; peak #1 on the Billboard Hot 100 (2015) | S17: Billboard Hot 100 weekly charts 1958–Oct 2026 (utdata/rwd-billboard-data); genre/album from Spotify via TidyTuesday 2021-09-14 | T17: Hints rebuilt Oct 2026 for a 75–90% solve target | U17: 10 | V17: peak #1 · 41 weeks · artist fame 180
A18: MUS-G-00516 | B18: Global | C18: Artist/Band | D18: Easy | E18: Madonna | G18: Madonna | H18: 1984 | I18: Era: in the Hot 100 top 10 between 1984 and 2005 · Dance Pop | J18: Chart record: 36 top-10 hits, 12 #1 hit(s) on the Billboard Hot 100 | K18: First top-10 hit: 'Borderline' (1984) | L18: Rolling Stone 500 (2020) album: 'The Immaculate Collection' (1990), ranked #138 | M18: Biggest hit: 'Take A Bow' | N18: Name: one word, 7 letters, starts with 'M' | O18: Janet Jackson | P18: Gloria Estefan | Q18: Babyface | R18: Madonna: 36 Hot 100 top-10 hits (1984–2005) | S18: Billboard Hot 100 1958–Oct 2026; Rolling Stone 500 Albums via TidyTuesday 2024-05-07 | T18: Counts are solo-credited entries only (features excluded); Hints rebuilt Oct 2026 for a 75–90% solve target | U18: 10 | V18: fame 193 · 36 top-10s
A19: MUS-G-00609 | B19: Global | C19: Song | D19: Easy | E19: Poker Face | G19: Lady Gaga | H19: 2009 | I19: Vibe: Dance Pop · 2009 | J19: Chart: peaked at #1 on the Billboard Hot 100, 40 weeks on the chart | K19: Album: The Fame | L19: Same artist also charted with: 'Born This Way' | M19: Artist: Lady Gaga | N19: Title initials: P. F. (2 words) | O19: Buttons | P19: Good Girls Go Bad | Q19: Too Little Too Late | R19: Poker Face by Lady Gaga; peak #1 on the Billboard Hot 100 (2009) | S19: Billboard Hot 100 weekly charts 1958–Oct 2026 (utdata/rwd-billboard-data); genre/album from Spotify via TidyTuesday 2021-09-14 | T19: Hints rebuilt Oct 2026 for a 75–90% solve target | U19: 10 | V19: peak #1 · 40 weeks · artist fame 197
A20: MUS-G-00634 | B20: Global | C20: Artist/Band | D20: Easy | E20: Rihanna | G20: Rihanna | H20: 2005 | I20: Era: in the Hot 100 top 10 between 2005 and 2022 · Barbadian Pop | J20: Chart record: 15 top-10 hits, 6 #1 hit(s) on the Billboard Hot 100 | K20: First top-10 hit: 'Pon de Replay' (2005) | L20: Rolling Stone 500 (2020) album: 'Anti' (2016), ranked #230 | M20: Biggest hit: 'We Found Love' | N20: Name: one word, 7 letters, starts with 'R' | O20: Fall Out Boy | P20: Ashanti | Q20: Kelly Clarkson | R20: Rihanna: 15 Hot 100 top-10 hits (2005–2022) | S20: Billboard Hot 100 1958–Oct 2026; Rolling Stone 500 Albums via TidyTuesday 2024-05-07 | T20: Counts are solo-credited entries only (features excluded); Hints rebuilt Oct 2026 for a 75–90% solve target | U20: 10 | V20: fame 156 · 15 top-10s
A21: MUS-G-00641 | B21: Global | C21: Song | D21: Easy | E21: Rolling In The Deep | G21: Adele | H21: 2010 | I21: Vibe: British Soul · 2010 | J21: Chart: peaked at #1 on the Billboard Hot 100, 65 weeks on the chart | K21: Album: 21 | L21: Same artist also charted with: 'Set Fire To The Rain' | M21: Artist: Adele | N21: Title initials: R. I. T. D. (4 words) | O21: Set Fire To The Rain | P21: Hello — Adele | Q21: Someone Like You | R21: Rolling In The Deep by Adele; peak #1 on the Billboard Hot 100 (2010) | S21: Billboard Hot 100 weekly charts 1958–Oct 2026 (utdata/rwd-billboard-data); genre/album from Spotify via TidyTuesday 2021-09-14 | T21: Hints rebuilt Oct 2026 for a 75–90% solve target | U21: 10 | V21: peak #1 · 65 weeks · artist fame 136
A22: MUS-G-00656 | B22: Global | C22: Song | D22: Easy | E22: Save Your Tears — The Weeknd & Ariana Grande | F22: Save Your Tears The Weeknd Ariana Grande | G22: The Weeknd & Ariana Grande | H22: 2021 | I22: Vibe: Chart hit · 2021 | J22: Chart: peaked at #1 on the Billboard Hot 100, 69 weeks on the chart | K22: Same artist also charted with: 'Die For You' | L22: Chart year: entered the Hot 100 in 2021 | M22: Artist: The ____ & ____ ____ | N22: Title initials: S. Y. T. T. W. A. G. (7 words) | O22: I Ain't Worried | P22: Bzrp Music Sessions, Vol. 53 | Q22: Not Like Us | R22: Save Your Tears by The Weeknd & Ariana Grande; peak #1 on the Billboard Hot 100 (2021) | S22: Billboard Hot 100 weekly charts 1958–Oct 2026 (utdata/rwd-billboard-data); genre/album from Spotify via TidyTuesday 2021-09-14 | T22: Hints rebuilt Oct 2026 for a 75–90% solve target | U22: 10 | V22: peak #1 · 69 weeks · artist fame 141
A23: MUS-G-00666 | B23: Global | C23: Song | D23: Easy | E23: Set Fire To The Rain | G23: Adele | H23: 2011 | I23: Vibe: British Soul · 2011 | J23: Chart: peaked at #1 on the Billboard Hot 100, 43 weeks on the chart | K23: Album: 21 | L23: Same artist also charted with: 'Rolling In The Deep' | M23: Artist: Adele | N23: Title initials: S. F. T. T. R. (5 words) | O23: Send My Love (To Your New Lover) | P23: Hello — Adele | Q23: Rolling In The Deep | R23: Set Fire To The Rain by Adele; peak #1 on the Billboard Hot 100 (2011) | S23: Billboard Hot 100 weekly charts 1958–Oct 2026 (utdata/rwd-billboard-data); genre/album from Spotify via TidyTuesday 2021-09-14 | T23: Hints rebuilt Oct 2026 for a 75–90% solve target | U23: 10 | V23: peak #1 · 43 weeks · artist fame 136
A24: MUS-G-00670 | B24: Global | C24: Song | D24: Easy | E24: Shake It Off — Taylor Swift | F24: Shake It Off Taylor Swift | G24: Taylor Swift | H24: 2014 | I24: Vibe: Pop · 2014 | J24: Chart: peaked at #1 on the Billboard Hot 100, 50 weeks on the chart | K24: Album: 1989 | L24: Same artist also charted with: 'Cruel Summer' | M24: Artist: ____ ____ | N24: Title initials: S. I. O. T. S. (5 words) | O24: Bad Blood — Taylor Swift Featuring Kendrick Lamar | P24: Today Was A Fairytale | Q24: Good Time | R24: Shake It Off by Taylor Swift; peak #1 on the Billboard Hot 100 (2014) | S24: Billboard Hot 100 weekly charts 1958–Oct 2026 (utdata/rwd-billboard-data); genre/album from Spotify via TidyTuesday 2021-09-14 | T24: Hints rebuilt Oct 2026 for a 75–90% solve target | U24: 10 | V24: peak #1 · 50 weeks · artist fame 178
A25: MUS-G-00673 | B25: Global | C25: Song | D25: Easy | E25: Shallow | G25: Lady Gaga & Bradley Cooper | H25: 2018 | I25: Vibe: Dance Pop · 2018 | J25: Chart: peaked at #1 on the Billboard Hot 100, 45 weeks on the chart | K25: Album: A Star Is Born Soundtrack | L25: Chart year: entered the Hot 100 in 2018 | M25: Artist: Lady Gaga & Bradley Cooper | N25: Title: one word, 7 letters, starts with 'S' | O25: You And I — Lady Gaga | P25: Thank U, Next | Q25: This Is What You Came For | R25: Shallow by Lady Gaga & Bradley Cooper; peak #1 on the Billboard Hot 100 (2018) | S25: Billboard Hot 100 weekly charts 1958–Oct 2026 (utdata/rwd-billboard-data); genre/album from Spotify via TidyTuesday 2021-09-14 | T25: Hints rebuilt Oct 2026 for a 75–90% solve target | U25: 10 | V25: peak #1 · 45 weeks · artist fame 197
A26: MUS-G-00697 | B26: Global | C26: Song | D26: Easy | E26: Sorry — Justin Bieber | F26: Sorry Justin Bieber | G26: Justin Bieber | H26: 2015 | I26: Vibe: Canadian Pop · 2015 | J26: Chart: peaked at #1 on the Billboard Hot 100, 42 weeks on the chart | K26: Album: Purpose (Deluxe) | L26: Same artist also charted with: 'Love Yourself' | M26: Artist: ____ ____ | N26: Title initials: S. J. B. (3 words) | O26: There's Nothing Holdin' Me Back | P26: As Long As You Love Me | Q26: If I Can't Have You — Shawn Mendes | R26: Sorry by Justin Bieber; peak #1 on the Billboard Hot 100 (2015) | S26: Billboard Hot 100 weekly charts 1958–Oct 2026 (utdata/rwd-billboard-data); genre/album from Spotify via TidyTuesday 2021-09-14 | T26: Hints rebuilt Oct 2026 for a 75–90% solve target | U26: 10 | V26: peak #1 · 42 weeks · artist fame 180
A27: MUS-G-00706 | B27: Global | C27: Song | D27: Easy | E27: Stay — The Kid LAROI & Justin Bieber | F27: Stay The Kid LAROI Justin Bieber | G27: The Kid LAROI & Justin Bieber | H27: 2021 | I27: Vibe: Chart hit · 2021 | J27: Chart: peaked at #1 on the Billboard Hot 100, 63 weeks on the chart | K27: Same artist also charted with: ____ | L27: Chart year: entered the Hot 100 in 2021 | M27: Artist: The ____ ____ & ____ ____ | N27: Title initials: S. T. K. L. J. B. (6 words) | O27: Type Shit | P27: Stuck With U | Q27: Outside | R27: Stay by The Kid LAROI & Justin Bieber; peak #1 on the Billboard Hot 100 (2021) | S27: Billboard Hot 100 weekly charts 1958–Oct 2026 (utdata/rwd-billboard-data); genre/album from Spotify via TidyTuesday 2021-09-14 | T27: Hints rebuilt Oct 2026 for a 75–90% solve target | U27: 10 | V27: peak #1 · 63 weeks · artist fame 180
A28: MUS-G-00737 | B28: Global | C28: Artist/Band | D28: Easy | E28: Taylor Swift | G28: Taylor Swift | H28: 2008 | I28: Era: in the Hot 100 top 10 between 2008 and 2026 · Pop | J28: Chart record: 66 top-10 hits, 14 #1 hit(s) on the Billboard Hot 100 | K28: First top-10 hit: 'Change' (2008) | L28: Rolling Stone 500 (2020) album: 'Red' (2012), ranked #99 | M28: Biggest hit: 'Cruel Summer' | N28: Name: 2 words — 6 + 5 letters, initials T.S. | O28: Ke$ha | P28: Maroon 5 | Q28: JAY-Z | R28: Taylor Swift: 66 Hot 100 top-10 hits (2008–2026) | S28: Billboard Hot 100 1958–Oct 2026; Rolling Stone 500 Albums via TidyTuesday 2024-05-07 | T28: Counts are solo-credited entries only (features excluded); Hints rebuilt Oct 2026 for a 75–90% solve target | U28: 10 | V28: fame 178 · 66 top-10s
A29: MUS-G-00845 | B29: Global | C29: Song | D29: Easy | E29: We Belong Together | G29: Mariah Carey | H29: 2005 | I29: Vibe: Dance Pop · 2005 | J29: Chart: peaked at #1 on the Billboard Hot 100, 43 weeks on the chart | K29: Album: The Emancipation of Mimi | L29: Same artist also charted with: 'All I Want For Christmas Is You' | M29: Artist: Mariah Carey | N29: Title initials: W. B. T. (3 words) | O29: In My Head | P29: Grillz | Q29: LoveGame | R29: We Belong Together by Mariah Carey; peak #1 on the Billboard Hot 100 (2005) | S29: Billboard Hot 100 weekly charts 1958–Oct 2026 (utdata/rwd-billboard-data); genre/album from Spotify via TidyTuesday 2021-09-14 | T29: Hints rebuilt Oct 2026 for a 75–90% solve target | U29: 10 | V29: peak #1 · 43 weeks · artist fame 126
A30: MUS-G-00869 | B30: Global | C30: Artist/Band | D30: Easy | E30: Whitney Houston | G30: Whitney Houston | H30: 1985 | I30: Era: in the Hot 100 top 10 between 1985 and 2012 · Dance Pop | J30: Chart record: 21 top-10 hits, 11 #1 hit(s) on the Billboard Hot 100 | K30: First top-10 hit: 'You Give Good Love' (1985) | L30: Rolling Stone 500 (2020) album: '____ ____' (1985), ranked #249 | M30: Biggest hit: 'I Will Always Love You' | N30: Name: 2 words — 7 + 7 letters, initials W.H. | O30: Eurythmics | P30: Gloria Estefan | Q30: Madonna | R30: Whitney Houston: 21 Hot 100 top-10 hits (1985–1999) | S30: Billboard Hot 100 1958–Oct 2026; Rolling Stone 500 Albums via TidyTuesday 2024-05-07 | T30: Counts are solo-credited entries only (features excluded); Hints rebuilt Oct 2026 for a 75–90% solve target | U30: 10 | V30: fame 137 · 21 top-10s
A31: MUS-G-01869 | B31: Global | C31: Artist/Band | D31: Easy | E31: Miley Cyrus | G31: Miley Cyrus | H31: 2007 | I31: Era: in the Hot 100 top 10 between 2008 and 2024 · Dance Pop | J31: Chart record: 10 top-10 hits, 2 #1 hit(s) on the Billboard Hot 100 | K31: First top-10 hit: 'See You Again' (2007) | L31: Number of words in name: 2 | M31: Biggest hit: 'Flowers' | N31: Name: 2 words — 5 + 5 letters, initials M.C. | O31: Sean Paul | P31: Beyonce | Q31: OneRepublic | R31: Miley Cyrus: 10 Hot 100 top-10 hits (2007–2023) | S31: Billboard Hot 100 1958–Oct 2026; Rolling Stone 500 Albums via TidyTuesday 2024-05-07 | T31: Counts are solo-credited entries only (features excluded); Hints rebuilt Oct 2026 for a 75–90% solve target | U31: 10 | V31: fame 141 · 10 top-10s
A32: MUS-G-00108 | B32: Global | C32: Song | D32: Easy | E32: Blank Space | G32: Taylor Swift | H32: 2014 | I32: Vibe: Pop · 2014 | J32: Chart: peaked at #1 on the Billboard Hot 100, 38 weeks on the chart | K32: Album: 1989 (Big Machine Radio Release Special) | L32: Same artist also charted with: 'Cruel Summer' | M32: Artist: Taylor Swift | N32: Title initials: B. S. (2 words) | O32: ...Ready For It? | P32: Too Good At Goodbyes | Q32: Bad Blood — Taylor Swift Featuring Kendrick Lamar | R32: Blank Space by Taylor Swift; peak #1 on the Billboard Hot 100 (2014) | S32: Billboard Hot 100 weekly charts 1958–Oct 2026 (utdata/rwd-billboard-data); genre/album from Spotify via TidyTuesday 2021-09-14 | T32: Hints rebuilt Oct 2026 for a 75–90% solve target | U32: 9.9 | V32: peak #1 · 38 weeks · artist fame 178
A33: MUS-G-00204 | B33: Global | C33: Song | D33: Easy | E33: Disturbia | G33: Rihanna | H33: 2008 | I33: Vibe: Barbadian Pop · 2008 | J33: Chart: peaked at #1 on the Billboard Hot 100, 37 weeks on the chart | K33: Album: Good Girl Gone Bad: Reloaded | L33: Same artist also charted with: 'SOS' | M33: Artist: Rihanna | N33: Title: one word, 9 letters, starts with 'D' | O33: Hate That I Love You | P33: Take A Bow — Rihanna | Q33: Hard | R33: Disturbia by Rihanna; peak #1 on the Billboard Hot 100 (2008) | S33: Billboard Hot 100 weekly charts 1958–Oct 2026 (utdata/rwd-billboard-data); genre/album from Spotify via TidyTuesday 2021-09-14 | T33: Hints rebuilt Oct 2026 for a 75–90% solve target | U33: 9.9 | V33: peak #1 · 37 weeks · artist fame 156
A34: MUS-G-00272 | B34: Global | C34: Song | D34: Easy | E34: Firework | G34: Katy Perry | H34: 2010 | I34: Vibe: Dance Pop · 2010 | J34: Chart: peaked at #1 on the Billboard Hot 100, 39 weeks on the chart | K34: Album: Katy Perry - Teenage Dream: The Complete Confection | L34: Same artist also charted with: 'Roar' | M34: Artist: Katy Perry | N34: Title: one word, 8 letters, starts with 'F' | O34: Eastside | P34: Let Me Love You (Until You Learn To Love Yourself) | Q34: Mirrors | R34: Firework by Katy Perry; peak #1 on the Billboard Hot 100 (2010) | S34: Billboard Hot 100 weekly charts 1958–Oct 2026 (utdata/rwd-billboard-data); genre/album from Spotify via TidyTuesday 2021-09-14 | T34: Hints rebuilt Oct 2026 for a 75–90% solve target | U34: 9.9 | V34: peak #1 · 39 weeks · artist fame 136
A35: MUS-G-00444 | B35: Global | C35: Song | D35: Easy | E35: Just The Way You Are — Bruno Mars | F35: Just The Way You Are Bruno Mars | G35: Bruno Mars | H35: 2010 | I35: Vibe: Pop · 2010 | J35: Chart: peaked at #1 on the Billboard Hot 100, 48 weeks on the chart | K35: Album: Doo-Wops & Hooligans | L35: Same artist also charted with: 'That's What I Like' | M35: Artist: ____ ____ | N35: Title initials: J. T. W. Y. A. B. M. (7 words) | O35: Boo'd Up | P35: Shape Of You | Q35: ...Ready For It? | R35: Just The Way You Are by Bruno Mars; peak #1 on the Billboard Hot 100 (2010) | S35: Billboard Hot 100 weekly charts 1958–Oct 2026 (utdata/rwd-billboard-data); genre/album from Spotify via TidyTuesday 2021-09-14 | T35: Hints rebuilt Oct 2026 for a 75–90% solve target | U35: 9.9 | V35: peak #1 · 48 weeks · artist fame 107
A36: MUS-G-00522 | B36: Global | C36: Artist/Band | D36: Easy | E36: Mariah Carey | G36: Mariah Carey | H36: 1990 | I36: Era: in the Hot 100 top 10 between 1990 and 2026 · Dance Pop | J36: Chart record: 22 top-10 hits, 16 #1 hit(s) on the Billboard Hot 100 | K36: First top-10 hit: 'Vision Of Love' (1990) | L36: Rolling Stone 500 (2020) album: 'The Emancipation of Mimi' (2005), ranked #389 | M36: Biggest hit: 'All I Want For Christmas Is You' | N36: Name: 2 words — 6 + 5 letters, initials M.C. | O36: Monica | P36: En Vogue | Q36: Brandy | R36: Mariah Carey: 22 Hot 100 top-10 hits (1990–2009) | S36: Billboard Hot 100 1958–Oct 2026; Rolling Stone 500 Albums via TidyTuesday 2024-05-07 | T36: Counts are solo-credited entries only (features excluded); Hints rebuilt Oct 2026 for a 75–90% solve target | U36: 9.9 | V36: fame 126 · 22 top-10s
A37: MUS-G-00693 | B37: Global | C37: Song | D37: Easy | E37: Someone Like You | G37: Adele | H37: 2011 | I37: Vibe: British Soul · 2011 | J37: Chart: peaked at #1 on the Billboard Hot 100, 39 weeks on the chart | K37: Album: 21 | L37: Same artist also charted with: 'Rolling In The Deep' | M37: Artist: Adele | N37: Title initials: S. L. Y. (3 words) | O37: Set Fire To The Rain | P37: Skyfall | Q37: Send My Love (To Your New Lover) | R37: Someone Like You by Adele; peak #1 on the Billboard Hot 100 (2011) | S37: Billboard Hot 100 weekly charts 1958–Oct 2026 (utdata/rwd-billboard-data); genre/album from Spotify via TidyTuesday 2021-09-14 | T37: Hints rebuilt Oct 2026 for a 75–90% solve target | U37: 9.9 | V37: peak #1 · 39 weeks · artist fame 136
A38: MUS-G-00749 | B38: Global | C38: Song | D38: Easy | E38: That's What I Like | F38: Thats What I Like | G38: Bruno Mars | H38: 2016 | I38: Vibe: Pop · 2016 | J38: Chart: peaked at #1 on the Billboard Hot 100, 52 weeks on the chart | K38: Album: 24K Magic | L38: Same artist also charted with: 'Just The Way You Are' | M38: Artist: Bruno Mars | N38: Title initials: T. W. I. L. (4 words) | O38: When I Was Your Man | P38: Love Never Felt So Good | Q38: Lay Me Down | R38: That's What I Like by Bruno Mars; peak #1 on the Billboard Hot 100 (2016) | S38: Billboard Hot 100 weekly charts 1958–Oct 2026 (utdata/rwd-billboard-data); genre/album from Spotify via TidyTuesday 2021-09-14 | T38: Hints rebuilt Oct 2026 for a 75–90% solve target | U38: 9.9 | V38: peak #1 · 52 weeks · artist fame 107
A39: MUS-G-00832 | B39: Global | C39: Song | D39: Easy | E39: Viva La Vida | G39: Coldplay | H39: 2008 | I39: Vibe: Permanent Wave · 2008 | J39: Chart: peaked at #1 on the Billboard Hot 100, 51 weeks on the chart | K39: Album: ____ La ____ or Death and All His Friends | L39: Same artist also charted with: 'Speed Of Sound' | M39: Artist: Coldplay | N39: Title initials: V. L. V. (3 words) | O39: Speed Of Sound | P39: Again — Lenny Kravitz | Q39: Oh | R39: Viva La Vida by Coldplay; peak #1 on the Billboard Hot 100 (2008) | S39: Billboard Hot 100 weekly charts 1958–Oct 2026 (utdata/rwd-billboard-data); genre/album from Spotify via TidyTuesday 2021-09-14 | T39: Hints rebuilt Oct 2026 for a 75–90% solve target | U39: 9.9 | V39: peak #1 · 51 weeks · artist fame 103
A40: MUS-G-00213 | B40: Global | C40: Song | D40: Easy | E40: Don't Start Now | F40: Dont Start Now | G40: Dua Lipa | H40: 2019 | I40: Vibe: Dance Pop · 2019 | J40: Chart: peaked at #2 on the Billboard Hot 100, 52 weeks on the chart | K40: Album: ____ ____ ____ | L40: Same artist also charted with: 'Levitating' | M40: Artist: Dua Lipa | N40: Title initials: D. S. N. (3 words) | O40: Just Can't Get Enough | P40: Underneath The Tree | Q40: Suit & Tie | R40: Don't Start Now by Dua Lipa; peak #2 on the Billboard Hot 100 (2019) | S40: Billboard Hot 100 weekly charts 1958–Oct 2026 (utdata/rwd-billboard-data); genre/album from Spotify via TidyTuesday 2021-09-14 | T40: Hints rebuilt Oct 2026 for a 75–90% solve target | U40: 9.8 | V40: peak #2 · 52 weeks · artist fame 113
A41: MUS-G-00530 | B41: Global | C41: Song | D41: Easy | E41: Mirrors | G41: Justin Timberlake | H41: 2013 | I41: Vibe: Dance Pop · 2013 | J41: Chart: peaked at #2 on the Billboard Hot 100, 42 weeks on the chart | K41: Album: The 20/20 Experience (Deluxe Version) | L41: Same artist also charted with: 'Can't Stop The Feeling!' | M41: Artist: Justin Timberlake | N41: Title: one word, 7 letters, starts with 'M' | O41: The Edge Of Glory | P41: Dark Horse | Q41: Drunk In Love | R41: Mirrors by Justin Timberlake; peak #2 on the Billboard Hot 100 (2013) | S41: Billboard Hot 100 weekly charts 1958–Oct 2026 (utdata/rwd-billboard-data); genre/album from Spotify via TidyTuesday 2021-09-14 | T41: Hints rebuilt Oct 2026 for a 75–90% solve target | U41: 9.8 | V41: peak #2 · 42 weeks · artist fame 111
A42: MUS-G-00635 | B42: Global | C42: Song | D42: Easy | E42: Roar | G42: Katy Perry | H42: 2013 | I42: Vibe: Dance Pop · 2013 | J42: Chart: peaked at #1 on the Billboard Hot 100, 35 weeks on the chart | K42: Album: PRISM (Deluxe) | L42: Same artist also charted with: 'Firework' | M42: Artist: Katy Perry | N42: Title: one word, 4 letters, starts with 'R' | O42: Feel This Moment | P42: Counting Stars | Q42: Love Me Like You Do | R42: Roar by Katy Perry; peak #1 on the Billboard Hot 100 (2013) | S42: Billboard Hot 100 weekly charts 1958–Oct 2026 (utdata/rwd-billboard-data); genre/album from Spotify via TidyTuesday 2021-09-14 | T42: Hints rebuilt Oct 2026 for a 75–90% solve target | U42: 9.8 | V42: peak #1 · 35 weeks · artist fame 136
A43: MUS-G-00668 | B43: Global | C43: Song | D43: Easy | E43: SexyBack | G43: Justin Timberlake | H43: 2006 | I43: Vibe: Dance Pop · 2006 | J43: Chart: peaked at #1 on the Billboard Hot 100, 36 weeks on the chart | K43: Album: FutureSex/LoveSounds | L43: Same artist also charted with: 'Can't Stop The Feeling!' | M43: Artist: Justin Timberlake | N43: Title: one word, 8 letters, starts with 'S' | O43: We Be Burnin' | P43: Too Little Too Late | Q43: Be Without You | R43: SexyBack by Justin Timberlake; peak #1 on the Billboard Hot 100 (2006) | S43: Billboard Hot 100 weekly charts 1958–Oct 2026 (utdata/rwd-billboard-data); genre/album from Spotify via TidyTuesday 2021-09-14 | T43: Hints rebuilt Oct 2026 for a 75–90% solve target | U43: 9.8 | V43: peak #1 · 36 weeks · artist fame 111
A44: MUS-G-00889 | B44: Global | C44: Song | D44: Easy | E44: You Belong With Me | G44: Taylor Swift | H44: 2008 | I44: Vibe: Pop · 2008 | J44: Chart: peaked at #2 on the Billboard Hot 100, 50 weeks on the chart | K44: Album: Fearless | L44: Same artist also charted with: 'Cruel Summer' | M44: Artist: Taylor Swift | N44: Title initials: Y. B. W. M. (4 words) | O44: This Love | P44: She Will Be Loved | Q44: You Rock My World | R44: You Belong With Me by Taylor Swift; peak #2 on the Billboard Hot 100 (2008) | S44: Billboard Hot 100 weekly charts 1958–Oct 2026 (utdata/rwd-billboard-data); genre/album from Spotify via TidyTuesday 2021-09-14 | T44: Hints rebuilt Oct 2026 for a 75–90% solve target | U44: 9.8 | V44: peak #2 · 50 weeks · artist fame 178
A45: MUS-G-01058 | B45: Global | C45: Song | D45: Easy | E45: Birds Of A Feather | G45: Billie Eilish | H45: 2024 | I45: Vibe: Chart hit · 2024 | J45: Chart: peaked at #2 on the Billboard Hot 100, 67 weeks on the chart | K45: Same artist also charted with: 'Bad Guy' | L45: Chart year: entered the Hot 100 in 2024 | M45: Artist: Billie Eilish | N45: Title initials: B. O. A. F. (4 words) | O45: I Had Some Help | P45: Come & Go | Q45: TSU | R45: Birds Of A Feather by Billie Eilish; peak #2 on the Billboard Hot 100 (2024) | S45: Billboard Hot 100 weekly charts 1958–Oct 2026 (utdata/rwd-billboard-data); genre/album from Spotify via TidyTuesday 2021-09-14 | T45: Hints rebuilt Oct 2026 for a 75–90% solve target | U45: 9.8 | V45: peak #2 · 67 weeks · artist fame 125
A46: MUS-G-01772 | B46: Global | C46: Song | D46: Easy | E46: Levitating — Dua Lipa | F46: Levitating Dua Lipa | G46: Dua Lipa | H46: 2021 | I46: Vibe: Chart hit · 2021 | J46: Chart: peaked at #2 on the Billboard Hot 100, 77 weeks on the chart | K46: Same artist also charted with: 'Don't Start Now' | L46: Chart year: entered the Hot 100 in 2021 | M46: Artist: ____ ____ | N46: Title initials: L. D. L. (3 words) | O46: Whats Poppin | P46: Make Them Cry | Q46: Popstar | R46: Levitating by Dua Lipa; peak #2 on the Billboard Hot 100 (2021) | S46: Billboard Hot 100 weekly charts 1958–Oct 2026 (utdata/rwd-billboard-data); genre/album from Spotify via TidyTuesday 2021-09-14 | T46: Hints rebuilt Oct 2026 for a 75–90% solve target | U46: 9.8 | V46: peak #2 · 77 weeks · artist fame 113
A47: MUS-G-00148 | B47: Global | C47: Artist/Band | D47: Easy | E47: Carpenters | G47: Carpenters | H47: 1970 | I47: Era: in the Hot 100 top 10 between 1970 and 1975 · Adult Standards | J47: Chart record: 12 top-10 hits, 3 #1 hit(s) on the Billboard Hot 100 | K47: First top-10 hit: '(They Long To Be) Close To You' (1970) | L47: Number of words in name: 1 | M47: Biggest hit: 'Top Of The World' | N47: Name: one word, 10 letters, starts with 'C' | O47: The Stylistics | P47: Leo Sayer | Q47: Linda Ronstadt | R47: Carpenters: 12 Hot 100 top-10 hits (1970–1975) | S47: Billboard Hot 100 1958–Oct 2026; Rolling Stone 500 Albums via TidyTuesday 2024-05-07 | T47: Counts are solo-credited entries only (features excluded); Hints rebuilt Oct 2026 for a 75–90% solve target | U47: 9.7 | V47: fame 195 · 12 top-10s
A48: MUS-G-00159 | B48: Global | C48: Artist/Band | D48: Easy | E48: Chicago | G48: Chicago | H48: 1970 | I48: Era: in the Hot 100 top 10 between 1970 and 1990 · Adult Standards | J48: Chart record: 20 top-10 hits, 3 #1 hit(s) on the Billboard Hot 100 | K48: First top-10 hit: 'Make Me Smile' (1970) | L48: Number of words in name: 1 | M48: Biggest hit: 'Hard To Say I'm Sorry' | N48: Name: one word, 7 letters, starts with 'C' | O48: George Benson | P48: Lobo | Q48: Roberta Flack | R48: Chicago: 20 Hot 100 top-10 hits (1970–1989) | S48: Billboard Hot 100 1958–Oct 2026; Rolling Stone 500 Albums via TidyTuesday 2024-05-07 | T48: Counts are solo-credited entries only (features excluded); Hints rebuilt Oct 2026 for a 75–90% solve target | U48: 9.7 | V48: fame 279 · 20 top-10s
A49: MUS-G-00238 | B49: Global | C49: Artist/Band | D49: Easy | E49: Eagles | G49: Eagles | H49: 1972 | I49: Era: in the Hot 100 top 10 between 1972 and 1980 · Album Rock | J49: Chart record: 10 top-10 hits, 5 #1 hit(s) on the Billboard Hot 100 | K49: First top-10 hit: 'Witchy Woman' (1972) | L49: Rolling Stone 500 (2020) album: 'Hotel California' (1976), ranked #118 | M49: Biggest hit: 'Best Of My Love' | N49: Name: one word, 6 letters, starts with 'E' | O49: Alice Cooper | P49: Fleetwood Mac | Q49: Aerosmith | R49: Eagles: 10 Hot 100 top-10 hits (1972–1980) | S49: Billboard Hot 100 1958–Oct 2026; Rolling Stone 500 Albums via TidyTuesday 2024-05-07 | T49: Counts are solo-credited entries only (features excluded); Hints rebuilt Oct 2026 for a 75–90% solve target | U49: 9.7 | V49: fame 168 · 10 top-10s
A50: MUS-G-00315 | B50: Global | C50: Song | D50: Easy | E50: Grenade | G50: Bruno Mars | H50: 2010 | I50: Vibe: Pop · 2010 | J50: Chart: peaked at #1 on the Billboard Hot 100, 36 weeks on the chart | K50: Album: Doo-Wops & Hooligans | L50: Same artist also charted with: 'That's What I Like' | M50: Artist: Bruno Mars | N50: Title: one word, 7 letters, starts with 'G' | O50: Locked Out Of Heaven | P50: Lay Me Down | Q50: Treasure | R50: Grenade by Bruno Mars; peak #1 on the Billboard Hot 100 (2010) | S50: Billboard Hot 100 weekly charts 1958–Oct 2026 (utdata/rwd-billboard-data); genre/album from Spotify via TidyTuesday 2021-09-14 | T50: Hints rebuilt Oct 2026 for a 75–90% solve target | U50: 9.7 | V50: peak #1 · 36 weeks · artist fame 107
A51: MUS-G-00372 | B51: Global | C51: Song | D51: Easy | E51: I Don't Care | F51: I Dont Care | G51: Ed Sheeran & Justin Bieber | H51: 2019 | I51: Vibe: Pop · 2019 | J51: Chart: peaked at #2 on the Billboard Hot 100, 39 weeks on the chart | K51: Album: I ____ ____ (with Justin Bieber) | L51: Chart year: entered the Hot 100 in 2019 | M51: Artist: Ed Sheeran & Justin Bieber | N51: Title initials: I. D. C. (3 words) | O51: Maps | P51: Animals | Q51: Treasure | R51: I Don't Care by Ed Sheeran & Justin Bieber; peak #2 on the Billboard Hot 100 (2019) | S51: Billboard Hot 100 weekly charts 1958–Oct 2026 (utdata/rwd-billboard-data); genre/album from Spotify via TidyTuesday 2021-09-14 | T51: Hints rebuilt Oct 2026 for a 75–90% solve target | U51: 9.7 | V51: peak #2 · 39 weeks · artist fame 180
A52: MUS-G-00380 | B52: Global | C52: Song | D52: Easy | E52: I Just Might | G52: Bruno Mars | H52: 2026 | I52: Vibe: Chart hit · 2026 | J52: Chart: peaked at #1 on the Billboard Hot 100, 36 weeks on the chart | K52: Same artist also charted with: 'That's What I Like' | L52: Chart year: entered the Hot 100 in 2026 | M52: Artist: Bruno Mars | N52: Title initials: I. J. M. (3 words) | O52: Noid | P52: Exile | Q52: Tit For Tat | R52: I Just Might by Bruno Mars; peak #1 on the Billboard Hot 100 (2026) | S52: Billboard Hot 100 weekly charts 1958–Oct 2026 (utdata/rwd-billboard-data); genre/album from Spotify via TidyTuesday 2021-09-14 | T52: Hints rebuilt Oct 2026 for a 75–90% solve target | U52: 9.7 | V52: peak #1 · 36 weeks · artist fame 107
A53: MUS-G-00424 | B53: Global | C53: Song | D53: Easy | E53: In The End | G53: Linkin Park | H53: 2001 | I53: Vibe: Alternative Metal · 2001 | J53: Chart: peaked at #2 on the Billboard Hot 100, 39 weeks on the chart | K53: Album: Hybrid Theory (Bonus Edition) | L53: Same artist also charted with: 'New Divide' | M53: Artist: Linkin Park | N53: Title initials: I. T. E. (3 words) | O53: Lips Of An Angel | P53: It's Not Over | Q53: Far Away | R53: In The End by Linkin Park; peak #2 on the Billboard Hot 100 (2001) | S53: Billboard Hot 100 weekly charts 1958–Oct 2026 (utdata/rwd-billboard-data); genre/album from Spotify via TidyTuesday 2021-09-14 | T53: Hints rebuilt Oct 2026 for a 75–90% solve target | U53: 9.7 | V53: peak #2 · 39 weeks · artist fame 117
A54: MUS-G-00489 | B54: Global | C54: Song | D54: Easy | E54: Locked Out Of Heaven | G54: Bruno Mars | H54: 2012 | I54: Vibe: Pop · 2012 | J54: Chart: peaked at #1 on the Billboard Hot 100, 36 weeks on the chart | K54: Album: Unorthodox Jukebox | L54: Same artist also charted with: 'That's What I Like' | M54: Artist: Bruno Mars | N54: Title initials: L. O. O. H. (4 words) | O54: It Will Rain | P54: Daylight — Maroon 5 | Q54: Castle On The Hill | R54: Locked Out Of Heaven by Bruno Mars; peak #1 on the Billboard Hot 100 (2012) | S54: Billboard Hot 100 weekly charts 1958–Oct 2026 (utdata/rwd-billboard-data); genre/album from Spotify via TidyTuesday 2021-09-14 | T54: Hints rebuilt Oct 2026 for a 75–90% solve target | U54: 9.7 | V54: peak #1 · 36 weeks · artist fame 107
A55: MUS-G-00529 | B55: Global | C55: Artist/Band | D55: Easy | E55: Michael Jackson | G55: Michael Jackson | H55: 1971 | I55: Era: in the Hot 100 top 10 between 1971 and 2025 · Pop | J55: Chart record: 25 top-10 hits, 12 #1 hit(s) on the Billboard Hot 100 | K55: First top-10 hit: 'Got To Be There' (1971) | L55: Rolling Stone 500 (2020) album: 'Thriller' (1982), ranked #12 | M55: Biggest hit: 'Billie Jean' | N55: Name: 2 words — 7 + 7 letters, initials M.J. | O55: The Steve Miller Band | P55: Sweet | Q55: James Taylor | R55: Michael Jackson: 25 Hot 100 top-10 hits (1971–2026) | S55: Billboard Hot 100 1958–Oct 2026; Rolling Stone 500 Albums via TidyTuesday 2024-05-07 | T55: Counts are solo-credited entries only (features excluded); Hints rebuilt Oct 2026 for a 75–90% solve target | U55: 9.7 | V55: fame 322 · 25 top-10s
A56: MUS-G-00566 | B56: Global | C56: Song | D56: Easy | E56: No One | G56: Alicia Keys | H56: 2007 | I56: Vibe: Hip Pop · 2007 | J56: Chart: peaked at #1 on the Billboard Hot 100, 39 weeks on the chart | K56: Album: As I Am (Expanded Edition) | L56: Same artist also charted with: 'Fallin'' | M56: Artist: Alicia Keys | N56: Title initials: N. O. (2 words) | O56: Addictive | P56: Diary | Q56: A Woman's Worth | R56: No One by Alicia Keys; peak #1 on the Billboard Hot 100 (2007) | S56: Billboard Hot 100 weekly charts 1958–Oct 2026 (utdata/rwd-billboard-data); genre/album from Spotify via TidyTuesday 2021-09-14 | T56: Hints rebuilt Oct 2026 for a 75–90% solve target | U56: 9.7 | V56: peak #1 · 39 weeks · artist fame 98
A57: MUS-G-00864 | B57: Global | C57: Song | D57: Easy | E57: When I Was Your Man | G57: Bruno Mars | H57: 2012 | I57: Vibe: Pop · 2012 | J57: Chart: peaked at #1 on the Billboard Hot 100, 35 weeks on the chart | K57: Album: Unorthodox Jukebox | L57: Same artist also charted with: 'That's What I Like' | M57: Artist: Bruno Mars | N57: Title initials: W. I. W. Y. M. (5 words) | O57: Moves Like Jagger | P57: Bad Blood — Taylor Swift Featuring Kendrick Lamar | Q57: Photograph — Ed Sheeran | R57: When I Was Your Man by Bruno Mars; peak #1 on the Billboard Hot 100 (2012) | S57: Billboard Hot 100 weekly charts 1958–Oct 2026 (utdata/rwd-billboard-data); genre/album from Spotify via TidyTuesday 2021-09-14 | T57: Hints rebuilt Oct 2026 for a 75–90% solve target | U57: 9.7 | V57: peak #1 · 35 weeks · artist fame 107
A58: MUS-G-00004 | B58: Global | C58: Song | D58: Easy | E58: ...Baby One More Time | F58: Baby One More Time | G58: Britney Spears | H58: 1998 | I58: Vibe: Dance Pop · 1998 | J58: Chart: peaked at #1 on the Billboard Hot 100, 32 weeks on the chart | K58: Album: ...____ ____ ____ ____ (Digital Deluxe Version) | L58: Same artist also charted with: 'Womanizer' | M58: Artist: Britney Spears | N58: Title initials: B. O. M. T. (4 words) | O58: Emotions — Mariah Carey | P58: I'll Be There — Mariah Carey | Q58: Whatta Man | R58: ...Baby One More Time by Britney Spears; peak #1 on the Billboard Hot 100 (1998) | S58: Billboard Hot 100 weekly charts 1958–Oct 2026 (utdata/rwd-billboard-data); genre/album from Spotify via TidyTuesday 2021-09-14 | T58: Hints rebuilt Oct 2026 for a 75–90% solve target | U58: 9.6 | V58: peak #1 · 32 weeks · artist fame 146
A59: MUS-G-00013 | B59: Global | C59: Song | D59: Easy | E59: 7 Rings | G59: Ariana Grande | H59: 2019 | I59: Vibe: Dance Pop · 2019 | J59: Chart: peaked at #1 on the Billboard Hot 100, 33 weeks on the chart | K59: Album: thank | L59: Same artist also charted with: 'Positions' | M59: Artist: Ariana Grande | N59: Title initials: 7. R. (2 words) | O59: I Wanna Go | P59: I Cry | Q59: Uptown Funk! | R59: 7 Rings by Ariana Grande; peak #1 on the Billboard Hot 100 (2019) | S59: Billboard Hot 100 weekly charts 1958–Oct 2026 (utdata/rwd-billboard-data); genre/album from Spotify via TidyTuesday 2021-09-14 | T59: Hints rebuilt Oct 2026 for a 75–90% solve target | U59: 9.6 | V59: peak #1 · 33 weeks · artist fame 141
A60: MUS-G-00041 | B60: Global | C60: Song | D60: Easy | E60: Always Be My Baby | G60: Mariah Carey | H60: 1996 | I60: Vibe: Dance Pop · 1996 | J60: Chart: peaked at #1 on the Billboard Hot 100, 32 weeks on the chart | K60: Album: Daydream | L60: Same artist also charted with: 'All I Want For Christmas Is You' | M60: Artist: Mariah Carey | N60: Title initials: A. B. M. B. (4 words) | O60: Secret | P60: Someday — Mariah Carey | Q60: Say You'll Be There | R60: Always Be My Baby by Mariah Carey; peak #1 on the Billboard Hot 100 (1996) | S60: Billboard Hot 100 weekly charts 1958–Oct 2026 (utdata/rwd-billboard-data); genre/album from Spotify via TidyTuesday 2021-09-14 | T60: Hints rebuilt Oct 2026 for a 75–90% solve target | U60: 9.6 | V60: peak #1 · 32 weeks · artist fame 126
A61: MUS-G-00053 | B61: Global | C61: Song | D61: Easy | E61: Another One Bites The Dust | G61: Queen | H61: 1980 | I61: Vibe: Glam Rock · 1980 | J61: Chart: peaked at #1 on the Billboard Hot 100, 31 weeks on the chart | K61: Album: The Game (Deluxe Remastered Version) | L61: Same artist also charted with: 'Crazy Little Thing Called Love' | M61: Artist: Queen | N61: Title initials: A. O. B. T. D. (5 words) | O61: Little Jeannie | P61: I Guess That's Why They Call It The Blues | Q61: Sad Songs (say So Much) | R61: Another One Bites The Dust by Queen; peak #1 on the Billboard Hot 100 (1980) | S61: Billboard Hot 100 weekly charts 1958–Oct 2026 (utdata/rwd-billboard-data); genre/album from Spotify via TidyTuesday 2021-09-14 | T61: Hints rebuilt Oct 2026 for a 75–90% solve target | U61: 9.6 | V61: peak #1 · 31 weeks · artist fame 190
A62: MUS-G-00083 | B62: Global | C62: Song | D62: Easy | E62: Because You Loved Me (From "Up Close & Personal") | F62: Because You Loved Me | Because You Loved Me From Up Close Personal | G62: Celine Dion | H62: 1996 | I62: Vibe: Canadian Pop · 1996 | J62: Chart: peaked at #1 on the Billboard Hot 100, 33 weeks on the chart | K62: Album: Falling into You | L62: Same artist also charted with: 'The Power Of Love' | M62: Artist: Celine Dion | N62: Title initials: B. Y. L. M. (4 words) | O62: Adia | P62: One Week | Q62: If You Asked Me To | R62: Because You Loved Me (From "Up Close & Personal") by Celine Dion; peak #1 on the Billboard Hot 100 (1996) | S62: Billboard Hot 100 weekly charts 1958–Oct 2026 (utdata/rwd-billboard-data); genre/album from Spotify via TidyTuesday 2021-09-14 | T62: Hints rebuilt Oct 2026 for a 75–90% solve target | U62: 9.6 | V62: peak #1 · 33 weeks · artist fame 161
A63: MUS-G-00088 | B63: Global | C63: Song | D63: Easy | E63: Believe | G63: Cher | H63: 1998 | I63: Vibe: Dance Pop · 1998 | J63: Chart: peaked at #1 on the Billboard Hot 100, 31 weeks on the chart | K63: Same artist also charted with: 'Half-Breed' | L63: Chart year: entered the Hot 100 in 1998 | M63: Artist: Cher | N63: Title: one word, 7 letters, starts with 'B' | O63: Fortunate | P63: Faded Pictures | Q63: You Want This/70's Love Groove | R63: Believe by Cher; peak #1 on the Billboard Hot 100 (1998) | S63: Billboard Hot 100 weekly charts 1958–Oct 2026 (utdata/rwd-billboard-data); genre/album from Spotify via TidyTuesday 2021-09-14 | T63: Hints rebuilt Oct 2026 for a 75–90% solve target | U63: 9.6 | V63: peak #1 · 31 weeks · artist fame 120
A64: MUS-G-00099 | B64: Global | C64: Song | D64: Easy | E64: Billie Jean | G64: Michael Jackson | H64: 1983 | I64: Vibe: Pop · 1983 | J64: Chart: peaked at #1 on the Billboard Hot 100, 32 weeks on the chart | K64: Album: Thriller 25 Super Deluxe Edition | L64: Same artist also charted with: 'Beat It' | M64: Artist: Michael Jackson | N64: Title initials: B. J. (2 words) | O64: Off The Wall | P64: The Way You Make Me Feel | Q64: Man In The Mirror | R64: Billie Jean by Michael Jackson; peak #1 on the Billboard Hot 100 (1983) | S64: Billboard Hot 100 weekly charts 1958–Oct 2026 (utdata/rwd-billboard-data); genre/album from Spotify via TidyTuesday 2021-09-14 | T64: Hints rebuilt Oct 2026 for a 75–90% solve target | U64: 9.6 | V64: peak #1 · 32 weeks · artist fame 322
A65: MUS-G-00235 | B65: Global | C65: Song | D65: Easy | E65: Dynamite — BTS | F65: Dynamite BTS | G65: BTS | H65: 2020 | I65: Vibe: K-Pop · 2020 | J65: Chart: peaked at #1 on the Billboard Hot 100, 32 weeks on the chart | K65: Album: BE | L65: Same artist also charted with: 'Butter' | M65: Artist: ____ | N65: Title initials: D. B. (2 words) | O65: ON | P65: Life Goes On | Q65: Make Them Cry | R65: Dynamite by BTS; peak #1 on the Billboard Hot 100 (2020) | S65: Billboard Hot 100 weekly charts 1958–Oct 2026 (utdata/rwd-billboard-data); genre/album from Spotify via TidyTuesday 2021-09-14 | T65: Hints rebuilt Oct 2026 for a 75–90% solve target | U65: 9.6 | V65: peak #1 · 32 weeks · artist fame 125
A66: MUS-G-00241 | B66: Global | C66: Song | D66: Easy | E66: Easy On Me | G66: Adele | H66: 2021 | I66: Vibe: Chart hit · 2021 | J66: Chart: peaked at #1 on the Billboard Hot 100, 31 weeks on the chart | K66: Same artist also charted with: 'Rolling In The Deep' | L66: Chart year: entered the Hot 100 in 2021 | M66: Artist: Adele | N66: Title initials: E. O. M. (3 words) | O66: 30 For 30 | P66: I'm Dat N***a | Q66: The Fate Of Ophelia | R66: Easy On Me by Adele; peak #1 on the Billboard Hot 100 (2021) | S66: Billboard Hot 100 weekly charts 1958–Oct 2026 (utdata/rwd-billboard-data); genre/album from Spotify via TidyTuesday 2021-09-14 | T66: Hints rebuilt Oct 2026 for a 75–90% solve target | U66: 9.6 | V66: peak #1 · 31 weeks · artist fame 136
A67: MUS-G-00290 | B67: Global | C67: Song | D67: Easy | E67: Gettin' Jiggy Wit It | F67: Gettin Jiggy Wit It | G67: Will Smith | H67: 1998 | I67: Vibe: Hip Hop · 1998 | J67: Chart: peaked at #1 on the Billboard Hot 100, 32 weeks on the chart | K67: Album: Big Willie Style | L67: Same artist also charted ____: 'Switch' | M67: Artist: Will Smith | N67: Title initials: G. J. W. I. (4 words) | O67: Get It On Tonite | P67: This Is How We Do It | Q67: Let's Ride | R67: Gettin' Jiggy Wit It by Will Smith; peak #1 on the Billboard Hot 100 (1998) | S67: Billboard Hot 100 weekly charts 1958–Oct 2026 (utdata/rwd-billboard-data); genre/album from Spotify via TidyTuesday 2021-09-14 | T67: Hints rebuilt Oct 2026 for a 75–90% solve target | U67: 9.6 | V67: peak #1 · 32 weeks · artist fame 135
A68: MUS-G-00384 | B68: Global | C68: Song | D68: Easy | E68: I Knew You Were Trouble. | F68: I Knew You Were Trouble | G68: Taylor Swift | H68: 2012 | I68: Vibe: Pop · 2012 | J68: Chart: peaked at #2 on the Billboard Hot 100, 36 weeks on the chart | K68: Album: Red | L68: Same artist also charted with: 'Cruel Summer' | M68: Artist: Taylor Swift | N68: Title initials: I. K. Y. W. T. (5 words) | O68: I Don't Care | P68: Back To December | Q68: Bodak Yellow (Money Moves) | R68: I Knew You Were Trouble. by Taylor Swift; peak #2 on the Billboard Hot 100 (2012) | S68: Billboard Hot 100 weekly charts 1958–Oct 2026 (utdata/rwd-billboard-data); genre/album from Spotify via TidyTuesday 2021-09-14 | T68: Hints rebuilt Oct 2026 for a 75–90% solve target | U68: 9.6 | V68: peak #2 · 36 weeks · artist fame 178
A69: MUS-G-00482 | B69: Global | C69: Song | D69: Easy | E69: Like That | G69: Future, Metro Boomin & Kendrick Lamar | H69: 2024 | I69: Vibe: Chart hit · 2024 | J69: Chart: peaked at #1 on the Billboard Hot 100, 32 weeks on the chart | K69: Chart year: entered the Hot 100 in 2024 | L69: Artist initials: F.M.B.&.K.L. | M69: Artist: Future, Metro Boomin & Kendrick Lamar | N69: Title initials: L. T. (2 words) | O69: Break My Soul | P69: Do We Have A Problem? | Q69: Nokia | R69: Like That by Future, Metro Boomin & Kendrick Lamar; peak #1 on the Billboard Hot 100 (2024) | S69: Billboard Hot 100 weekly charts 1958–Oct 2026 (utdata/rwd-billboard-data); genre/album from Spotify via TidyTuesday 2021-09-14 | T69: Hints rebuilt Oct 2026 for a 75–90% solve target | U69: 9.6 | V69: peak #1 · 32 weeks · artist fame 122
A70: MUS-G-00589 | B70: Global | C70: Song | D70: Easy | E70: Opalite | G70: Taylor Swift | H70: 2025 | I70: Vibe: Chart hit · 2025 | J70: Chart: peaked at #1 on the Billboard Hot 100, 32 weeks on the chart | K70: Same artist also charted with: 'Cruel Summer' | L70: Chart year: entered the Hot 100 in 2025 | M70: Artist: Taylor Swift | N70: Title: one word, 7 letters, starts with 'O' | O70: Please Please Please | P70: Pink Pony Club | Q70: Family Matters | R70: Opalite by Taylor Swift; peak #1 on the Billboard Hot 100 (2025) | S70: Billboard Hot 100 weekly charts 1958–Oct 2026 (utdata/rwd-billboard-data); genre/album from Spotify via TidyTuesday 2021-09-14 | T70: Hints rebuilt Oct 2026 for a 75–90% solve target | U70: 9.6 | V70: peak #1 · 32 weeks · artist fame 178
A71: MUS-G-00602 | B71: Global | C71: Song | D71: Easy | E71: Perfect — Ed Sheeran | F71: Perfect Ed Sheeran | G71: Ed Sheeran | H71: 2017 | I71: Vibe: Pop · 2017 | J71: Chart: peaked at #1 on the Billboard Hot 100, 57 weeks on the chart | K71: Album: ÷ (Deluxe) | L71: Same artist also charted with: 'Shape Of You' | M71: Artist: Ed ____ | N71: Title initials: P. E. S. (3 words) | O71: Moves Like Jagger | P71: Daylight — Maroon 5 | Q71: Begin Again | R71: Perfect by Ed Sheeran; peak #1 on the Billboard Hot 100 (2017) | S71: Billboard Hot 100 weekly charts 1958–Oct 2026 (utdata/rwd-billboard-data); genre/album from Spotify via TidyTuesday 2021-09-14 | T71: Hints rebuilt Oct 2026 for a 75–90% solve target | U71: 9.6 | V71: peak #1 · 57 weeks · artist fame 94
A72: MUS-G-00674 | B72: Global | C72: Song | D72: Easy | E72: Shape Of You | G72: Ed Sheeran | H72: 2017 | I72: Vibe: Pop · 2017 | J72: Chart: peaked at #1 on the Billboard Hot 100, 59 weeks on the chart | K72: Album: ÷ (Deluxe) | L72: Same artist also charted with: 'Perfect' | M72: Artist: Ed Sheeran | N72: Title initials: S. O. Y. (3 words) | O72: Bodak Yellow (Money Moves) | P72: Fight Song | Q72: Someone You Loved | R72: Shape Of You by Ed Sheeran; peak #1 on the Billboard Hot 100 (2017) | S72: Billboard Hot 100 weekly charts 1958–Oct 2026 (utdata/rwd-billboard-data); genre/album from Spotify via TidyTuesday 2021-09-14 | T72: Hints rebuilt Oct 2026 for a 75–90% solve target | U72: 9.6 | V72: peak #1 · 59 weeks · artist fame 94
A73: MUS-G-00740 | B73: Global | C73: Song | D73: Easy | E73: Teenage Dream — Katy Perry | F73: Teenage Dream Katy Perry | G73: Katy Perry | H73: 2010 | I73: Vibe: Dance Pop · 2010 | J73: Chart: peaked at #1 on the Billboard Hot 100, 33 weeks on the chart | K73: Album: ____ ____ - ____ ____: The Complete Confection | L73: Same artist also charted with: 'Firework' | M73: Artist: ____ ____ | N73: Title initials: T. D. K. P. (4 words) | O73: ME! | P73: Turn Me On — David Guetta Featuring Nicki Minaj | Q73: Cooler Than Me | R73: Teenage Dream by Katy Perry; peak #1 on the Billboard Hot 100 (2010) | S73: Billboard Hot 100 weekly charts 1958–Oct 2026 (utdata/rwd-billboard-data); genre/album from Spotify via TidyTuesday 2021-09-14 | T73: Hints rebuilt Oct 2026 for a 75–90% solve target | U73: 9.6 | V73: peak #1 · 33 weeks · artist fame 136
A74: MUS-G-00756 | B74: Global | C74: Song | D74: Easy | E74: The Fate Of Ophelia | F74: Fate Of Ophelia | G74: Taylor Swift | H74: 2025 | I74: Vibe: Chart hit · 2025 | J74: Chart: peaked at #1 on the Billboard Hot 100, 32 weeks on the chart | K74: Same artist also charted with: 'Cruel Summer' | L74: Chart year: entered the Hot 100 in 2025 | M74: Artist: Taylor Swift | N74: Title initials: T. F. O. O. (4 words) | O74: Vegas | P74: I Can Do It With A Broken Heart | Q74: APT. | R74: The Fate Of Ophelia by Taylor Swift; peak #1 on the Billboard Hot 100 (2025) | S74: Billboard Hot 100 weekly charts 1958–Oct 2026 (utdata/rwd-billboard-data); genre/album from Spotify via TidyTuesday 2021-09-14 | T74: Hints rebuilt Oct 2026 for a 75–90% solve target | U74: 9.6 | V74: peak #1 · 32 weeks · artist fame 178
A75: MUS-G-00766 | B75: Global | C75: Song | D75: Easy | E75: The Power Of Love — Celine Dion | F75: Power Of Love — Celine Dion | The Power Of Love Celine Dion | G75: Celine Dion | H75: 1993 | I75: Vibe: Canadian Pop · 1993 | J75: Chart: peaked at #1 on the Billboard Hot 100, 33 weeks on the chart | K75: Album: The Colour Of My ____ | L75: Same artist also charted with: 'Because You ____ Me (From "Up Close & Personal")' | M75: Artist: ____ ____ | N75: Title initials: T. P. O. L. C. D. (6 words) | O75: One Week | P75: Angel — Sarah McLachlan | Q75: Where Does My Heart Beat Now | R75: The Power Of Love by Celine Dion; peak #1 on the Billboard Hot 100 (1993) | S75: Billboard Hot 100 weekly charts 1958–Oct 2026 (utdata/rwd-billboard-data); genre/album from Spotify via TidyTuesday 2021-09-14 | T75: Hints rebuilt Oct 2026 for a 75–90% solve target | U75: 9.6 | V75: peak #1 · 33 weeks · artist fame 161
A76: MUS-G-00853 | B76: Global | C76: Song | D76: Easy | E76: What Do You Mean? | F76: What Do You Mean | G76: Justin Bieber | H76: 2015 | I76: Vibe: Canadian Pop · 2015 | J76: Chart: peaked at #1 on the Billboard Hot 100, 31 weeks on the chart | K76: Album: Purpose (Deluxe) | L76: Same artist also charted with: 'Sorry' | M76: Artist: Justin Bieber | N76: Title initials: W. D. Y. M. (4 words) | O76: Call Me Maybe | P76: As Long As You Love Me | Q76: Never Say Never | R76: What Do You Mean? by Justin Bieber; peak #1 on the Billboard Hot 100 (2015) | S76: Billboard Hot 100 weekly charts 1958–Oct 2026 (utdata/rwd-billboard-data); genre/album from Spotify via TidyTuesday 2021-09-14 | T76: Hints rebuilt Oct 2026 for a 75–90% solve target | U76: 9.6 | V76: peak #1 · 31 weeks · artist fame 180
A77: MUS-G-00884 | B77: Global | C77: Song | D77: Easy | E77: Wrecking Ball | G77: Miley Cyrus | H77: 2013 | I77: Vibe: Dance Pop · 2013 | J77: Chart: peaked at #1 on the Billboard Hot 100, 32 weeks on the chart | K77: Album: Bangerz (Deluxe Version) | L77: Same artist also charted with: 'Flowers' | M77: Artist: Miley Cyrus | N77: Title initials: W. B. (2 words) | O77: Filthy | P77: Malibu | Q77: Love Me Like You Do | R77: Wrecking Ball by Miley Cyrus; peak #1 on the Billboard Hot 100 (2013) | S77: Billboard Hot 100 weekly charts 1958–Oct 2026 (utdata/rwd-billboard-data); genre/album from Spotify via TidyTuesday 2021-09-14 | T77: Hints rebuilt Oct 2026 for a 75–90% solve target | U77: 9.6 | V77: peak #1 · 32 weeks · artist fame 141
A78: MUS-G-00023 | B78: Global | C78: Artist/Band | D78: Easy | E78: Adele | G78: Adele | H78: 2010 | I78: Era: in the Hot 100 top 10 between 2011 and 2022 · British Soul | J78: Chart record: 8 top-10 hits, 5 #1 hit(s) on the Billboard Hot 100 | K78: First top-10 hit: 'Rolling In The Deep' (2010) | L78: Rolling Stone 500 (2020) album: '21' (2011), ranked #137 | M78: Biggest hit: 'Rolling In The Deep' | N78: Name: one word, 5 letters, starts with 'A' | O78: Selena Gomez | P78: Bruno Mars | Q78: The Weeknd | R78: Adele: 8 Hot 100 top-10 hits (2010–2021) | S78: Billboard Hot 100 1958–Oct 2026; Rolling Stone 500 Albums via TidyTuesday 2024-05-07 | T78: Counts are solo-credited entries only (features excluded); Hints rebuilt Oct 2026 for a 75–90% solve target | U78: 9.5 | V78: fame 136 · 8 top-10s
A79: MUS-G-00073 | B79: Global | C79: Song | D79: Easy | E79: Bad Romance | G79: Lady Gaga | H79: 2009 | I79: Vibe: Dance Pop · 2009 | J79: Chart: peaked at #2 on the Billboard Hot 100, 35 weeks on the chart | K79: Album: The Fame Monster (Deluxe Edition) | L79: Same artist also charted with: 'Poker Face' | M79: Artist: Lady Gaga | N79: Title initials: B. R. (2 words) | O79: Beautiful Girls | P79: Run It! | Q79: Rock Wit U (Awww Baby) | R79: Bad Romance by Lady Gaga; peak #2 on the Billboard Hot 100 (2009) | S79: Billboard Hot 100 weekly charts 1958–Oct 2026 (utdata/rwd-billboard-data); genre/album from Spotify via TidyTuesday 2021-09-14 | T79: Hints rebuilt Oct 2026 for a 75–90% solve target | U79: 9.5 | V79: peak #2 · 35 weeks · artist fame 197
A80: MUS-G-00227 | B80: Global | C80: Song | D80: Easy | E80: Dreamlover | G80: Mariah Carey | H80: 1993 | I80: Vibe: Dance Pop · 1993 | J80: Chart: peaked at #1 on the Billboard Hot 100, 29 weeks on the chart | K80: Album: Music Box | L80: Same artist also charted with: 'All I Want For Christmas Is You' | M80: Artist: Mariah Carey | N80: Title: one word, 10 letters, starts with 'D' | O80: Again — Janet Jackson | P80: Giving Him Something He Can Feel | Q80: That's The Way Love Goes | R80: Dreamlover by Mariah Carey; peak #1 on the Billboard Hot 100 (1993) | S80: Billboard Hot 100 weekly charts 1958–Oct 2026 (utdata/rwd-billboard-data); genre/album from Spotify via TidyTuesday 2021-09-14 | T80: Hints rebuilt Oct 2026 for a 75–90% solve target | U80: 9.5 | V80: peak #1 · 29 weeks · artist fame 126
A81: MUS-G-00346 | B81: Global | C81: Song | D81: Easy | E81: Hero — Mariah Carey | F81: Hero Mariah Carey | G81: Mariah Carey | H81: 1993 | I81: Vibe: Dance Pop · 1993 | J81: Chart: peaked at #1 on the Billboard Hot 100, 30 weeks on the chart | K81: Album: Music Box | L81: Same artist also charted with: 'All I Want For Christmas Is You' | M81: Artist: ____ ____ | N81: Title initials: H. M. C. (3 words) | O81: That's The Way Love Goes | P81: Bills, Bills, Bills | Q81: Believe | R81: Hero by Mariah Carey; peak #1 on the Billboard Hot 100 (1993) | S81: Billboard Hot 100 weekly charts 1958–Oct 2026 (utdata/rwd-billboard-data); genre/album from Spotify via TidyTuesday 2021-09-14 | T81: Hints rebuilt Oct 2026 for a 75–90% solve target | U81: 9.5 | V81: peak #1 · 30 weeks · artist fame 126
A82: MUS-G-00349 | B82: Global | C82: Song | D82: Easy | E82: Hey, Soul Sister | F82: Hey Soul Sister | G82: Train | H82: 2009 | I82: Vibe: Neo Mellow · 2009 | J82: Chart: peaked at #3 on the Billboard Hot 100, 54 weeks on the chart | K82: Album: Sav M | L82: Same artist also charted with: 'Drops Of Jupiter (Tell Me)' | M82: Artist: Train | N82: Title initials: H. S. S. (3 words) | O82: Unwell | P82: If You're Gone | Q82: Everything You Want | R82: Hey, Soul Sister by Train; peak #3 on the Billboard Hot 100 (2009) | S82: Billboard Hot 100 weekly charts 1958–Oct 2026 (utdata/rwd-billboard-data); genre/album from Spotify via TidyTuesday 2021-09-14 | T82: Hints rebuilt Oct 2026 for a 75–90% solve target | U82: 9.5 | V82: peak #3 · 54 weeks · artist fame 207
A83: MUS-G-00362 | B83: Global | C83: Song | D83: Easy | E83: Hot N Cold | G83: Katy Perry | H83: 2008 | I83: Vibe: Dance Pop · 2008 | J83: Chart: peaked at #3 on the Billboard ____ 100, 39 weeks on the chart | K83: Album: One Of The Boys | L83: Same artist also charted with: 'Firework' | M83: Artist: Katy Perry | N83: Title initials: H. N. C. (3 words) | O83: Right Now (Na Na Na) | P83: I Wanna Love You | Q83: Ride Wit Me | R83: Hot N Cold by Katy Perry; peak #3 on the Billboard Hot 100 (2008) | S83: Billboard Hot 100 weekly charts 1958–Oct 2026 (utdata/rwd-billboard-data); genre/album from Spotify via TidyTuesday 2021-09-14 | T83: Hints rebuilt Oct 2026 for a 75–90% solve target | U83: 9.5 | V83: peak #3 · 39 weeks · artist fame 136
A84: MUS-G-00399 | B84: Global | C84: Song | D84: Easy | E84: I Will Always Love You | G84: Whitney Houston | H84: 1992 | I84: Vibe: Dance Pop · 1992 | J84: Chart: peaked at #1 on the Billboard Hot 100, 29 weeks on the chart | K84: Album: The Bodyguard - Original Soundtrack Album | L84: Same artist also charted with: 'How ____ I Know' | M84: Artist: Whitney Houston | N84: Title initials: I. W. A. L. Y. (5 words) | O84: Any Time, Any Place/And On And On | P84: Anniversary | Q84: Always Be My Baby | R84: I Will Always Love You by Whitney Houston; peak #1 on the Billboard Hot 100 (1992) | S84: Billboard Hot 100 weekly charts 1958–Oct 2026 (utdata/rwd-billboard-data); genre/album from Spotify via TidyTuesday 2021-09-14 | T84: Hints rebuilt Oct 2026 for a 75–90% solve target | U84: 9.5 | V84: peak #1 · 29 weeks · artist fame 137
A85: MUS-G-00422 | B85: Global | C85: Song | D85: Easy | E85: In Da Club | G85: 50 Cent | H85: 2003 | I85: Vibe: East Coast Hip Hop · 2003 | J85: Chart: peaked at #1 on the Billboard Hot 100, 30 weeks on the chart | K85: Album: Get Rich Or Die Tryin' | L85: Same artist also charted with: 'Disco Inferno' | M85: Artist: 50 Cent | N85: Title initials: I. D. C. (3 words) | O85: Disco Inferno | P85: P.I.M.P. | Q85: Luv U Better | R85: In Da Club by 50 Cent; peak #1 on the Billboard Hot 100 (2003) | S85: Billboard Hot 100 weekly charts 1958–Oct 2026 (utdata/rwd-billboard-data); genre/album from Spotify via TidyTuesday 2021-09-14 | T85: Hints rebuilt Oct 2026 for a 75–90% solve target | U85: 9.5 | V85: peak #1 · 30 weeks · artist fame 111
A86: MUS-G-00428 | B86: Global | C86: Song | D86: Easy | E86: Irreplaceable | G86: Beyonce | H86: 2006 | I86: Vibe: Dance Pop · 2006 | J86: Chart: peaked at #1 on the Billboard Hot 100, 30 weeks on the chart | K86: Album: B'Day Deluxe Edition | L86: Same artist also charted with: 'Single Ladies (Put A Ring On It)' | M86: Artist: Beyonce | N86: Title: one word, 13 letters, starts with 'I' | O86: Miss Independent — Kelly Clarkson | P86: Obsessed | Q86: You — Lloyd Featuring Lil Wayne | R86: Irreplaceable by Beyonce; peak #1 on the Billboard Hot 100 (2006) | S86: Billboard Hot 100 weekly charts 1958–Oct 2026 (utdata/rwd-billboard-data); genre/album from Spotify via TidyTuesday 2021-09-14 | T86: Hints rebuilt Oct 2026 for a 75–90% solve target | U86: 9.5 | V86: peak #1 · 30 weeks · artist fame 175
A87: MUS-G-00474 | B87: Global | C87: Song | D87: Easy | E87: Let Me Love You — Mario | F87: Let Me Love You Mario | G87: Mario | H87: 2004 | I87: Vibe: Dance Pop · 2004 | J87: Chart: peaked at #1 on the Billboard Hot 100, 36 weeks on the chart | K87: Album: ____ Me ____ You | L87: Same artist also charted with: 'Just A Friend 2002' | M87: Artist: ____ | N87: Title initials: L. M. L. Y. M. (5 words) | O87: 4 Minutes | P87: Circus | Q87: Oh | R87: Let Me Love You by Mario; peak #1 on the Billboard Hot 100 (2004) | S87: Billboard Hot 100 weekly charts 1958–Oct 2026 (utdata/rwd-billboard-data); genre/album from Spotify via TidyTuesday 2021-09-14 | T87: Hints rebuilt Oct 2026 for a 75–90% solve target | U87: 9.5 | V87: peak #1 · 36 weeks · artist fame 96
A88: MUS-G-00612 | B88: Global | C88: Song | D88: Easy | E88: Positions | G88: Ariana Grande | H88: 2020 | I88: Vibe: Dance Pop · 2020 | J88: Chart: peaked at #1 on the Billboard Hot 100, 29 weeks on the chart | K88: Same artist also charted with: '7 Rings' | L88: Chart year: entered the Hot 100 in 2020 | M88: Artist: Ariana Grande | N88: Title: one word, 9 letters, starts with 'P' | O88: Up | P88: Stupid Love | Q88: 34+35 — Ariana Grande | R88: Positions by Ariana Grande; peak #1 on the Billboard Hot 100 (2020) | S88: Billboard Hot 100 weekly charts 1958–Oct 2026 (utdata/rwd-billboard-data); genre/album from Spotify via TidyTuesday 2021-09-14 | T88: Hints rebuilt Oct 2026 for a 75–90% solve target | U88: 9.5 | V88: peak #1 · 29 weeks · artist fame 141
A89: MUS-G-00723 | B89: Global | C89: Song | D89: Easy | E89: Super Bass | G89: Nicki Minaj | H89: 2011 | I89: Vibe: Dance Pop · 2011 | J89: Chart: peaked at #3 on the Billboard Hot 100, 39 weeks on the chart | K89: Album: Pink Friday (Deluxe) | L89: Same artist also charted with: 'Say So' | M89: Artist: Nicki Minaj | N89: Title initials: S. B. (2 words) | O89: Without You — David Guetta Featuring Usher | P89: Firework | Q89: Rocketeer | R89: Super Bass by Nicki Minaj; peak #3 on the Billboard Hot 100 (2011) | S89: Billboard Hot 100 weekly charts 1958–Oct 2026 (utdata/rwd-billboard-data); genre/album from Spotify via TidyTuesday 2021-09-14 | T89: Hints rebuilt Oct 2026 for a 75–90% solve target | U89: 9.5 | V89: peak #3 · 39 weeks · artist fame 115
A90: MUS-G-00729 | B90: Global | C90: Song | D90: Easy | E90: Take A Bow — Madonna | F90: Take A Bow Madonna | G90: Madonna | H90: 1994 | I90: Vibe: Dance Pop · 1994 | J90: Chart: peaked at #1 on the Billboard Hot 100, 30 weeks on the chart | K90: Album: Celebration (double disc version) | L90: Same artist also charted with: 'Music' | M90: Artist: ____ | N90: Title initials: T. A. B. M. (4 words) | O90: You'll See | P90: Make It Happen | Q90: Heartbreak Hotel | R90: Take A Bow by Madonna; peak #1 on the Billboard Hot 100 (1994) | S90: Billboard Hot 100 weekly charts 1958–Oct 2026 (utdata/rwd-billboard-data); genre/album from Spotify via TidyTuesday 2021-09-14 | T90: Hints rebuilt Oct 2026 for a 75–90% solve target | U90: 9.5 | V90: peak #1 · 30 weeks · artist fame 193
A91: MUS-G-01121 | B91: Global | C91: Song | D91: Easy | E91: Calm Down | G91: Rema & Selena Gomez | H91: 2022 | I91: Vibe: Chart hit · 2022 | J91: Chart: peaked at #3 on the Billboard Hot 100, 57 weeks on the chart | K91: Chart year: entered the Hot 100 in 2022 | L91: Artist initials: R.&.S.G. | M91: Artist: Rema & Selena Gomez | N91: Title initials: C. D. (2 words) | O91: abcdefu | P91: What I Want | Q91: Nobody Gets Me | R91: Calm Down by Rema & Selena Gomez; peak #3 on the Billboard Hot 100 (2022) | S91: Billboard Hot 100 weekly charts 1958–Oct 2026 (utdata/rwd-billboard-data); genre/album from Spotify via TidyTuesday 2021-09-14 | T91: Hints rebuilt Oct 2026 for a 75–90% solve target | U91: 9.5 | V91: peak #3 · 57 weeks · artist fame 175
A92: MUS-G-01148 | B92: Global | C92: Artist/Band | D92: Easy | E92: Celine Dion | G92: Celine Dion | H92: 1990 | I92: Era: in the Hot 100 top 10 between 1991 and 2000 · Canadian Pop | J92: Chart record: 8 top-10 hits, 3 #1 hit(s) on the Billboard Hot 100 | K92: First top-10 hit: 'Where Does My Heart Beat Now' (1990) | L92: Number of words in name: 2 | M92: Biggest hit: 'Because You Loved Me' | N92: Name: 2 words — 6 + 4 letters, initials C.D. | O92: Jennifer Lopez | P92: R. Kelly | Q92: Savage Garden | R92: Celine Dion: 8 Hot 100 top-10 hits (1990–1999) | S92: Billboard Hot 100 1958–Oct 2026; Rolling Stone 500 Albums via TidyTuesday 2024-05-07 | T92: Counts are solo-credited entries only (features excluded); Hints rebuilt Oct 2026 for a 75–90% solve target | U92: 9.5 | V92: fame 161 · 8 top-10s
A93: MUS-G-01204 | B93: Global | C93: Song | D93: Easy | E93: Daisies | G93: Justin Bieber | H93: 2025 | I93: Vibe: Chart hit · 2025 | J93: Chart: peaked at #2 on the Billboard Hot 100, 34 weeks on the chart | K93: Same artist also charted with: 'Sorry' | L93: Chart year: entered the Hot 100 in 2025 | M93: Artist: Justin Bieber | N93: Title: one word, 7 letters, starts with 'D' | O93: Texas Hold 'Em | P93: I Remember Everything | Q93: The Giver | R93: Daisies by Justin Bieber; peak #2 on the Billboard Hot 100 (2025) | S93: Billboard Hot 100 weekly charts 1958–Oct 2026 (utdata/rwd-billboard-data); genre/album from Spotify via TidyTuesday 2021-09-14 | T93: Hints rebuilt Oct 2026 for a 75–90% solve target | U93: 9.5 | V93: peak #2 · 34 weeks · artist fame 180
A94: MUS-G-01449 | B94: Global | C94: Artist/Band | D94: Easy | E94: Heart | G94: Heart | H94: 1976 | I94: Era: in the Hot 100 top 10 between 1976 and 1990 · Folk-Pop | J94: Chart record: 9 top-10 hits, 2 #1 hit(s) on the Billboard Hot 100 | K94: First top-10 hit: 'Magic Man' (1976) | L94: Number of words in name: 1 | M94: Biggest hit: 'Alone' | N94: Name: one word, 5 letters, starts with 'H' | O94: The Steve Miller Band | P94: America — America | Q94: George Benson | R94: Heart: 9 Hot 100 top-10 hits (1976–1990) | S94: Billboard Hot 100 1958–Oct 2026; Rolling Stone 500 Albums via TidyTuesday 2024-05-07 | T94: Counts are solo-credited entries only (features excluded); Hints rebuilt Oct 2026 for a 75–90% solve target | U94: 9.5 | V94: fame 256 · 9 top-10s
A95: MUS-G-01714 | B95: Global | C95: Artist/Band | D95: Easy | E95: Justin Bieber | G95: Justin Bieber | H95: 2012 | I95: Era: in the Hot 100 top 10 between 2012 and 2026 · Canadian Pop | J95: Chart record: 8 top-10 hits, 3 #1 hit(s) on the Billboard Hot 100 | K95: First top-10 hit: 'Boyfriend' (2012) | L95: Number of words in name: 2 | M95: Biggest hit: 'Stay' | N95: Name: 2 words — 6 + 6 letters, initials J.B. | O95: Shawn Mendes | P95: Adele | Q95: Kendrick Lamar | R95: Justin Bieber: 8 Hot 100 top-10 hits (2012–2025) | S95: Billboard Hot 100 1958–Oct 2026; Rolling Stone 500 Albums via TidyTuesday 2024-05-07 | T95: Counts are solo-credited entries only (features excluded); Hints rebuilt Oct 2026 for a 75–90% solve target | U95: 9.5 | V95: fame 180 · 8 top-10s
A96: MUS-G-00015 | B96: Global | C96: Song | D96: Easy | E96: 9 To 5 | G96: Dolly Parton | H96: 1980 | I96: Vibe: Classic Country Pop · 1980 | J96: Chart: peaked at #1 on the Billboard Hot 100, 28 weeks on the chart | K96: Album: 9 To 5 And Odd Jobs | L96: Same artist also charted with: 'Here You Come Again' | M96: Artist: Dolly Parton | N96: Title initials: 9. T. 5. (3 words) | O96: Lookin' For Love | P96: Always On My Mind — Willie Nelson | Q96: Elvira | R96: 9 To 5 by Dolly Parton; peak #1 on the Billboard Hot 100 (1980) | S96: Billboard Hot 100 weekly charts 1958–Oct 2026 (utdata/rwd-billboard-data); genre/album from Spotify via TidyTuesday 2021-09-14 | T96: Hints rebuilt Oct 2026 for a 75–90% solve target | U96: 9.4 | V96: peak #1 · 28 weeks · artist fame 123
A97: MUS-G-00078 | B97: Global | C97: Song | D97: Easy | E97: Beat It | G97: Michael Jackson | H97: 1983 | I97: Vibe: Pop · 1983 | J97: Chart: peaked at #1 on the Billboard Hot 100, 28 weeks on the chart | K97: Album: Thriller 25 Super Deluxe Edition | L97: Same artist also charted with: 'Billie Jean' | M97: Artist: Michael Jackson | N97: Title initials: B. I. (2 words) | O97: Dirty Diana | P97: Wanna Be Startin' Somethin' | Q97: Thriller | R97: Beat It by Michael Jackson; peak #1 on the Billboard Hot 100 (1983) | S97: Billboard Hot 100 weekly charts 1958–Oct 2026 (utdata/rwd-billboard-data); genre/album from Spotify via TidyTuesday 2021-09-14 | T97: Hints rebuilt Oct 2026 for a 75–90% solve target | U97: 9.4 | V97: peak #1 · 28 weeks · artist fame 322
A98: MUS-G-00116 | B98: Global | C98: Song | D98: Easy | E98: Bohemian Rhapsody | G98: Queen | H98: 1976 | I98: Vibe: Glam Rock · 1976 | J98: Chart: peaked at #2 on the Billboard Hot 100, 44 weeks on the chart | K98: Album: A Night At The Opera (Deluxe Remastered Version) | L98: Same artist also charted with: 'Another One Bites The Dust' | M98: Artist: Queen | N98: Title initials: B. R. (2 words) | O98: Someone Saved My Life Tonight | P98: Daniel | Q98: Your Song | R98: Bohemian Rhapsody by Queen; peak #2 on the Billboard Hot 100 (1976) | S98: Billboard Hot 100 weekly charts 1958–Oct 2026 (utdata/rwd-billboard-data); genre/album from Spotify via TidyTuesday 2021-09-14 | T98: Hints rebuilt Oct 2026 for a 75–90% solve target | U98: 9.4 | V98: peak #2 · 44 weeks · artist fame 190
A99: MUS-G-00261 | B99: Global | C99: Song | D99: Easy | E99: Fallin' | F99: Fallin | G99: Alicia Keys | H99: 2001 | I99: Vibe: Hip Pop · 2001 | J99: Chart: peaked at #1 on the Billboard Hot 100, 34 weeks on the chart | K99: Album: Songs In A Minor (Expanded Edition) | L99: Same artist also charted with: 'No One' | M99: Artist: Alicia Keys | N99: Title: one word, 7 letters, starts with 'F' | O99: Move Ya Body | P99: No One | Q99: What Would You Do? | R99: Fallin' by Alicia Keys; peak #1 on the Billboard Hot 100 (2001) | S99: Billboard Hot 100 weekly charts 1958–Oct 2026 (utdata/rwd-billboard-data); genre/album from Spotify via TidyTuesday 2021-09-14 | T99: Hints rebuilt Oct 2026 for a 75–90% solve target | U99: 9.4 | V99: peak #1 · 34 weeks · artist fame 98
A100: MUS-G-00306 | B100: Global | C100: Song | D100: Easy | E100: Good 4 U | G100: Olivia Rodrigo | H100: 2021 | I100: Vibe: Pop · 2021 | J100: Chart: peaked at #1 on the Billboard Hot 100, 51 weeks on the chart | K100: Album: ____ 4 u | L100: Same artist also charted with: 'Vampire' | M100: Artist: Olivia Rodrigo | N100: Title initials: G. 4. U. (3 words) | O100: Good Days | P100: Before You Go | Q100: Drivers License | R100: Good 4 U by Olivia Rodrigo; peak #1 on the Billboard Hot 100 (2021) | S100: Billboard Hot 100 weekly charts 1958–Oct 2026 (utdata/rwd-billboard-data); genre/album from Spotify via TidyTuesday 2021-09-14 | T100: Hints rebuilt Oct 2026 for a 75–90% solve target | U100: 9.4 | V100: peak #1 · 51 weeks · artist fame 86
...

Sheet Icons
A1: ID | B1: Edition | C1: Answer type | D1: Category | E1: Difficulty | F1: Answer | G1: Accepted aliases | H1: Hint 1 (shown at start) | I1: Hint 2 (after miss 1) | J1: Hint 3 (after miss 2) | K1: Hint 4 (after miss 3) | L1: Hint 5 (after miss 4) | M1: Hint 6 (after miss 5, with options) | N1: Wrong option A | O1: Wrong option B | P1: Wrong option C | Q1: Reveal-card fact | R1: Source | S1: Verify flag | T1: Fame score (0-10) | U1: Score signals
A2: ICO-G-00001 | B2: Global | C2: Band | D2: Band | E2: Easy | F2: ABBA | H2: Field: Band · Formed in the 1970s · Swedish | I2: Moment: Won Eurovision with "Waterloo" in 1974 | J2: Known for: "Dancing Queen" | K2: Connection: Digital avatar concerts in London | L2: Initials: A. | M2: Name: one word, 4 letters, starts with 'A' | N2: Queen | O2: U2 | P2: AC/DC | Q2: ABBA — band, Swedish | R2: Curated by Claude from general knowledge | S2: Curated – verify facts before scheduling; Hints rebuilt Oct 2026 for a 75–90% solve target | T2: 10 | U2: 162 Wikipedias
A3: ICO-G-00007 | B3: Global | C3: Person | D3: Mathematician | E3: Easy | F3: Alan Turing | H3: Field: Mathematician · Born in the 1910s · British | I3: Moment: Helped break the Enigma code in World War II | J3: Known for: Father of computer science | K3: Connection: ____ test | L3: Initials: A.T. | M3: Name: 2 words — 4 + 6 letters, initials A.T. | N3: Ada Lovelace | O3: Mother Teresa | P3: Tim Berners-Lee | Q3: Alan Turing — mathematician, British | R3: Curated by Claude from general knowledge | S3: Curated – verify facts before scheduling; Hints rebuilt Oct 2026 for a 75–90% solve target | T3: 10 | U3: 190 Wikipedias
A4: ICO-G-00008 | B4: Global | C4: Person | D4: Physicist | E4: Easy | F4: Albert Einstein | H4: Field: Physicist · Born in the 1870s · German-born | I4: Moment: Explained E = mc² | J4: Known for: Theory of relativity | K4: Connection: Nobel Prize in 1921 | L4: Initials: A.E. | M4: Name: 2 words — 6 + 8 letters, initials A.E. | N4: Stephen Hawking | O4: Mother Teresa | P4: Tim Berners-Lee | Q4: Albert Einstein — physicist, German-born | R4: Curated by Claude from general knowledge | S4: Curated – verify facts before scheduling; Hints rebuilt Oct 2026 for a 75–90% solve target | T4: 10 | U4: 322 Wikipedias
A5: ICO-G-00010 | B5: Global | C5: Person | D5: Artist | E5: Easy | F5: Andy Warhol | H5: Field: Artist · Born in the 1920s · American | I5: Moment: Painted Campbell's Soup cans | J5: Known for: Pop Art pioneer | K5: Connection: "15 minutes of fame" | L5: Initials: A.W. | M5: Name: 2 words — 4 + 6 letters, initials A.W. | N5: Frida Kahlo | O5: Stephen King | P5: George R. R. Martin | Q5: Andy Warhol — artist, American | R5: Curated by Claude from general knowledge | S5: Curated – verify facts before scheduling; Hints rebuilt Oct 2026 for a 75–90% solve target | T5: 10 | U5: 179 Wikipedias
A6: ICO-G-00011 | B6: Global | C6: Person | D6: Actor | E6: Easy | F6: Angelina Jolie | H6: Field: Actor · Born in the 1970s · American | I6: Moment: Became a UN refugee agency special envoy | J6: Known for: Lara Croft, Maleficent | K6: Connection: Oscar winner for Girl, Interrupted | L6: Initials: A.J. | M6: Name: 2 words — 8 + 5 letters, initials A.J. | N6: Harvey Keitel | O6: Cillian Murphy | P6: Jodie Foster | Q6: Angelina Jolie — actor, American | R6: Curated by Claude from general knowledge | S6: Curated – verify facts before scheduling; Hints rebuilt Oct 2026 for a 75–90% solve target | T6: 10 | U6: 172 Wikipedias
A7: ICO-G-00014 | B7: Global | C7: Brand | D7: Technology | E7: Easy | F7: Apple | H7: Industry: Technology · United States · founded in the 1970s | I7: Iconic: iPhone, launched 2007 | J7: Founded by: Steve Jobs, Steve Wozniak and Ronald Wayne | K7: Tagline: "Think Different" | L7: Logo: A piece of fruit with a bite taken out | M7: Name: one word, 5 letters, starts with 'A' | N7: Microsoft | O7: IBM | P7: Zoom | Q7: Apple — technology, United States | R7: Curated by Claude from general knowledge | S7: Curated – verify tagline, founders and logo description; replace logo text with the logo image later; Hints rebuilt Oct 2026 for a 75–90% solve target | T7: 10 | U7: 242 Wikipedias
A8: ICO-G-00015 | B8: Global | C8: Person | D8: Singer and actor | E8: Easy | F8: Ariana Grande | H8: Field: Singer and actor · Born in the 1990s · American | I8: Moment: Played Glinda in Wicked | J8: Known for: "Thank U, Next" | K8: Connection: Four-octave range | L8: Initials: A.G. | M8: Name: 2 words — 6 + 6 letters, initials A.G. | N8: Ashton Kutcher | O8: Forest Whitaker | P8: Luke Wilson | Q8: Ariana Grande — singer and actor, American | R8: Curated by Claude from general knowledge | S8: Curated – verify facts before scheduling; Hints rebuilt Oct 2026 for a 75–90% solve target | T8: 10 | U8: 141 Wikipedias
A9: ICO-G-00016 | B9: Global | C9: Person | D9: Actor and bodybuilder | E9: Easy | F9: Arnold Schwarzenegger | H9: Field: Actor and bodybuilder · Born in the 1940s · Austrian-American | I9: Moment: Promised "I'll be back" in The Terminator | J9: Known for: Seven-time Mr. Olympia | K9: Connection: Governor of California | L9: Initials: A.S. | M9: Name: 2 words — 6 + 14 letters, initials A.S. | N9: Vin Diesel | O9: Marlon Brando | P9: Michael Fassbender | Q9: Arnold Schwarzenegger — actor and bodybuilder, Austrian-American | R9: Curated by Claude from general knowledge | S9: Curated – verify facts before scheduling; Hints rebuilt Oct 2026 for a 75–90% solve target | T9: 10 | U9: 153 Wikipedias
A10: ICO-G-00018 | B10: Global | C10: Brand | D10: Broadcasting | E10: Easy | F10: BBC | H10: Industry: Broadcasting · United Kingdom · founded in the 1920s | I10: Iconic: Doctor Who | J10: Founded by: John Reith (first director-general) | K10: Tagline: "Inform, educate and entertain" | L10: Logo: Three letters in three black boxes | M10: Name: one word, 3 letters, starts with 'B' | N10: Red Bull | O10: Samsung | P10: Shell | Q10: BBC — broadcasting, United Kingdom | R10: Curated by Claude from general knowledge | S10: Curated – verify tagline, founders and logo description; replace logo text with the logo image later; Hints rebuilt Oct 2026 for a 75–90% solve target | T10: 10 | U10: 149 Wikipedias
A11: ICO-G-00024 | B11: Global | C11: Person | D11: Singer | E11: Easy | F11: Beyoncé | H11: Field: Singer · Born in the 1980s · American | I11: Moment: Won Album of the Year for Cowboy Carter in 2025 | J11: Known for: Most Grammy wins ever | K11: Connection: Destiny's Child; "Queen Bey" | L11: Initials: B. | M11: Name: one word, 7 letters, starts with 'B' | N11: Katy Perry | O11: Lady Gaga | P11: Bruno Mars | Q11: Beyoncé — singer, American | R11: Curated by Claude from general knowledge | S11: Curated – verify facts before scheduling; Hints rebuilt Oct 2026 for a 75–90% solve target | T11: 10 | U11: 175 Wikipedias
A12: ICO-G-00025 | B12: Global | C12: Person | D12: Entrepreneur and philanthropist | E12: Easy | F12: Bill Gates | H12: Field: Entrepreneur and philanthropist · Born in the 1950s · American | I12: Moment: Dropped out of Harvard to start a software company | J12: Known for: Co-founded Microsoft | K12: Connection: ____ Foundation | L12: Initials: B.G. | M12: Name: 2 words — 4 + 5 letters, initials B.G. | N12: Ferruccio Lamborghini | O12: Jack Dorsey | P12: Mark Zuckerberg | Q12: Bill Gates — entrepreneur and philanthropist, American | R12: Curated by Claude from general knowledge | S12: Curated – verify facts before scheduling; Hints rebuilt Oct 2026 for a 75–90% solve target | T12: 10 | U12: 243 Wikipedias
A13: ICO-G-00028 | B13: Global | C13: Person | D13: Singer | E13: Easy | F13: Bob Marley | H13: Field: Singer · Born in the 1940s · Jamaican | I13: Moment: Brought rival politicians together on stage in 1978 | J13: Known for: Reggae ambassador; "One Love" | K13: Connection: The Wailers | L13: Initials: B.M. | M13: Name: 2 words — 3 + 6 letters, initials B.M. | N13: Elton John | O13: Freddie Mercury | P13: Mick Jagger | Q13: Bob Marley — singer, Jamaican | R13: Curated by Claude from general knowledge | S13: Curated – verify facts before scheduling; Hints rebuilt Oct 2026 for a 75–90% solve target | T13: 10 | U13: 164 Wikipedias
... A16: ICO-G-00039 | B16: Global | C16: Person | D16: Actor and filmmaker | E16: Easy | F16: Charlie Chaplin | H16: Field: Actor and filmmaker · Born in the 1880s · British | I16: Moment: Created "The Tramp" with bowler hat and cane | J16: Known for: Modern Times, The Great Dictator | K16: Connection: Silent-era icon | L16: Initials: C.C. | M16: Name: 2 words — 7 + 7 letters, initials C.C. | N16: Peter Jackson | O16: Wes Craven | P16: Brett Ratner | Q16: Charlie Chaplin — actor and filmmaker, British | R16: Curated by Claude from general knowledge | S16: Curated – verify facts before scheduling; Hints rebuilt Oct 2026 for a 75–90% solve target | T16: 10 | U16: 262 Wikipedias
A17: ICO-G-00043 | B17: Global | C17: Brand | D17: Beverages | E17: Easy | F17: Coca-Cola | G17: CocaCola | H17: Industry: Beverages · United States · founded in the 1880s | I17: Iconic: Secret formula; contour bottle | J17: Founded by: John Pemberton (inventor) | K17: Tagline: "Open Happiness" / "Taste the Feeling" | L17: Logo: Flowing red Spencerian script | M17: Name: one word, 9 letters, starts with 'C' | N17: Pepsi | O17: Monster Energy | P17: Lipton | Q17: Coca-Cola — beverages, United States | R17: Curated by Claude from general knowledge | S17: Curated – verify tagline, founders and logo description; replace logo text with the logo image later; Hints rebuilt Oct 2026 for a 75–90% solve target | T17: 10 | U17: 151 Wikipedias
A18: ICO-G-00049 | B18: Global | C18: Person | D18: Footballer | E18: Easy | F18: Cristiano Ronaldo | H18: Field: Footballer · Born in the 1980s · Portuguese | I18: Moment: Won Euro 2016 with his national team | J18: Known for: All-time top scorer in men's international football | K18: Connection: Manchester United, Real Madrid, Juventus, Al Nassr; "CR7" | L18: Initials: C.R. | M18: Name: 2 words — 9 + 7 letters, initials C.R. | N18: Andrés Iniesta | O18: Xavi | P18: Ronaldinho | Q18: Cristiano Ronaldo — footballer, Portuguese | R18: Curated by Claude from general knowledge | S18: Curated – verify facts before scheduling; Hints rebuilt Oct 2026 for a 75–90% solve target | T18: 10 | U18: 214 Wikipedias
A19: ICO-G-00057 | B19: Global | C19: Person | D19: Footballer | E19: Easy | F19: Diego Maradona | H19: Field: Footballer · Born in the 1960s · Argentine | I19: Moment: Scored the "Hand of God" goal against England in 1986 | J19: Known for: Led his country to the 1986 World Cup | K19: Connection: Napoli, Barcelona, Boca Juniors | L19: Initials: D.M. | M19: Name: 2 words — 5 + 8 letters, initials D.M. | N19: Paolo Maldini | O19: Wayne Rooney | P19: Vinícius Júnior | Q19: Diego Maradona — footballer, Argentine | R19: Curated by Claude from general knowledge | S19: Curated – verify facts before scheduling; Hints rebuilt Oct 2026 for a 75–90% solve target | T19: 10 | U19: 175 Wikipedias
A20: ICO-G-00058 | B20: Global | C20: Brand | D20: Entertainment | E20: Easy | F20: Disney | H20: Industry: Entertainment · United States · founded in the 1920s | I20: Iconic: Mickey Mouse; theme parks | J20: Founded by: Walt and Roy ____ | K20: Tagline: "The Happiest Place on Earth" | L20: Logo: Signature-style script under a castle | M20: Name: one word, 6 letters, starts with 'D' | N20: Warner Bros. | O20: Marvel | P20: Paramount | Q20: Disney — entertainment, United States | R20: Curated by Claude from general knowledge | S20: Curated – verify tagline, founders and logo description; replace logo text with the logo image later; Hints rebuilt Oct 2026 for a 75–90% solve target | T20: 10 | U20: 142 Wikipedias
A21: ICO-G-00060 | B21: Global | C21: Brand | D21: Personal care | E21: Easy | F21: Dove | H21: Industry: Personal care · United States / United Kingdom · founded in the 1950s | I21: Iconic: Beauty bar with moisturising cream | J21: Founded by: Lever Brothers | K21: Tagline: "Real Beauty" | L21: Logo: A ____ in profile | M21: Name: one word, 4 letters, starts with 'D' | N21: Gillette | O21: Colgate | P21: Nestlé | Q21: Dove — personal care, United States / United Kingdom | R21: Curated by Claude from general knowledge | S21: Curated – verify tagline, founders and logo description; replace logo text with the logo image later; Hints rebuilt Oct 2026 for a 75–90% solve target | T21: 10 | U21: 179 Wikipedias
A22: ICO-G-00069 | B22: Global | C22: Person | D22: Entrepreneur | E22: Easy | F22: Elon Musk | H22: Field: Entrepreneur · Born in the 1970s · South African-American | I22: Moment: Landed and reused an orbital rocket booster | J22: Known for: Runs Tesla and SpaceX | K22: Connection: Bought Twitter and renamed it X | L22: Initials: E.M. | M22: Name: 2 words — 4 + 4 letters, initials E.M. | N22: Jack Dorsey | O22: Travis Kalanick | P22: Sara Blakely | Q22: Elon Musk — entrepreneur, South African-American | R22: Curated by Claude from general knowledge | S22: Curated – verify facts before scheduling; Hints rebuilt Oct 2026 for a 75–90% solve target | T22: 10 | U22: 202 Wikipedias
A23: ICO-G-00071 | B23: Global | C23: Person | D23: Singer | E23: Easy | F23: Elvis Presley | H23: Field: Singer · Born in the 1930s · American | I23: Moment: Filmed only from the waist up on The Ed Sullivan Show | J23: Known for: "King of Rock and Roll" | K23: Connection: Graceland, Memphis | L23: Initials: E.P. | M23: Name: 2 words — 5 + 7 letters, initials E.P. | N23: Katy Perry | O23: Michael Jackson | P23: Bob Marley | Q23: Elvis Presley — singer, American | R23: Curated by Claude from general knowledge | S23: Curated – verify facts before scheduling; Hints rebuilt Oct 2026 for a 75–90% solve target | T23: 10 | U23: 216 Wikipedias
